Workbook
Name tc: Set!$N$1
Name tc: Ago!$N$1

Sheet Dic (2)
A1: Período de Cálculo: | E1: 44531 | U1: Días en el mes | W1: 31
A2: PERUPETRO S.A.
A3: DETERMINACION DEL CANON, SOBRECANON y PARTICIPACION (US$)
A4: ="Correspondiente a "&TEXT(E1,"MMMMMMM YYYY") -> Correspondiente a Diciembre 2021
A5: ="Tipo de Cambio= "&TEXT(F1,"0.000") -> Tipo de Cambio= 0.000
A7: Localidad | C7: Modalidad de Contrato | D7: Calculo del Canon | F7: Volumen Producción / Venta | I7: Canasta o Valor Venta (US$/Unidad) | K7: Deducción de Gastos para determinación de valor de producción en Punto de Fiscalización (US$) | O7: Valor de la Producción (US$) | P7: Canon y Sobrecanon / Participación (US$) | U7: Resumen por Petróleo y Condensados | AA7: Resumen por Gas Natural | AG7: Control
A8: - Lote | D8: Período | E8: Fórmula | F8: Unidades | G8: 1ra. Q | H8: 2da. Q / Mes | I8: 1ra. Q | J8: 2da. Q / Mes | K8: Flete Marítimo | L8: Comercialización | M8: Oleoducto | N8: Fiscalización | P8: Total | Q8: Localidad 1 | S8: Localidad 2 | U8: Producción / Venta | X8: Valor Prod | Y8: Valor Canon | AA8: Producción / Venta | AD8: Valor Prod | AE8: Valor Canon | AG8: Total
A9: Piura / Tumbes | Q9: Piura | S9: Tumbes | U9: Bls/Mes | V9: V P (US$) | W9: Bls/Día | X9: US$/Bl | Y9: US$/Bl | Z9: US$ | AA9: MM BTU/Mes | AB9: V P (US$) | AC9: MM BTU/Día | AD9: US$/MM BTU | AE9: US$/MM BTU | AF9: US$ | AG9: Canon
A10: - | B10: I | C10: Servicios | D10: Mes | E10: F1 | F10: Bls | H10: 25833 | J10: 62.2551 | N10: 672.29 | O10: =ROUND(G10*I10,2)+ROUND(H10*J10,2)-K10-L10-M10-N10 -> 1607563.7 | P10: =ROUND(18.75%*O10,2) -> 301418.2 | Q10: =ROUND($O10*R10,2) -> 241134.56 | R10: 0.15 | S10: =ROUND($O10*T10,2) -> 60283.64 | T10: 0.0375 | U10: =IF($F10&"/Día"=W$9,SUM($G10:$H10),"") -> 25833 | V10: =IF(U10<>"",$O10,"") -> 1607563.7 | W10: =IF($F10&"/Día"=W$9,ROUND(U10/$W$1,1),"") -> 833.3 | X10: =IF(U10=0,0,IF($F10&"/Día"=W$9,ROUND(V10/U10,4),"")) -> 62.2291 | Y10: =IF(U10=0,0,IF($F10&"/Día"=W$9,ROUND(Z10/U10,4),"")) -> 11.668 | Z10: =IF(U10<>"",$P10,"") -> 301418.2 | AA10: =IF($F10&"/Día"=AC$9,SUM($G10:$H10),"") | AB10: =IF(AA10<>"",$O10,"") | AC10: =IF($F10&"/Día"=AC$9,ROUND(AA10/$W$1,1),"") | AD10: =IF(AA10=0,0,IF($F10&"/Día"=AC$9,ROUND(AB10/AA10,4),"")) | AE10: =IF(AA10=0,0,IF($F10&"/Día"=AC$9,ROUND(AF10/AA10,4),"")) | AF10: =IF(AA10<>"",$P10,"")
A11: - | B11: I GAS | C11: Servicios | D11: Mes | E11: F1 | F11: MM BTU | H11: 254280.4 | J11: 3.0812 | N11: 1882.44 | O11: =ROUND(G11*I11,2)+ROUND(H11*J11,2)-K11-L11-M11-N11 -> 781606.33 | P11: =ROUND(18.75%*O11,2) -> 146551.19 | Q11: =ROUND($O11*R11,2) -> 117240.95 | R11: 0.15 | S11: =ROUND($O11*T11,2) -> 29310.24 | T11: 0.0375 | U11: =IF($F11&"/Día"=W$9,SUM($G11:$H11),"") | V11: =IF(U11<>"",$O11,"") | W11: =IF($F11&"/Día"=W$9,ROUND(U11/$W$1,1),"") | X11: =IF(U11=0,0,IF($F11&"/Día"=W$9,ROUND(V11/U11,4),"")) | Y11: =IF(U11=0,0,IF($F11&"/Día"=W$9,ROUND(Z11/U11,4),"")) | Z11: =IF(U11<>"",$P11,"") | AA11: =IF($F11&"/Día"=AC$9,SUM($G11:$H11),"") -> 254280.4 | AB11: =IF(AA11<>"",$O11,"") -> 781606.33 | AC11: =IF($F11&"/Día"=AC$9,ROUND(AA11/$W$1,1),"") -> 8202.6 | AD11: =IF(AA11=0,0,IF($F11&"/Día"=AC$9,ROUND(AB11/AA11,4),"")) -> 3.0738 | AE11: =IF(AA11=0,0,IF($F11&"/Día"=AC$9,ROUND(AF11/AA11,4),"")) -> 0.5763 | AF11: =IF(AA11<>"",$P11,"") -> 146551.19
A12: - | B12: II | C12: Licencia | D12: Quincena | E12: F2 | F12: Bls | G12: 4603 | H12: 4743 | I12: 59.4397 | J12: 61.3637 | N12: 1735.69 | O12: =ROUND(G12*I12,2)+ROUND(H12*J12,2)-K12-L12-M12-N12 -> 562913.28 | P12: =ROUND(18.75%*O12,2) -> 105546.24 | Q12: =ROUND($O12*R12,2) -> 84436.99 | R12: 0.15 | S12: =ROUND($O12*T12,2) -> 21109.25 | T12: 0.0375 | U12: =IF($F12&"/Día"=W$9,SUM($G12:$H12),"") -> 9346 | V12: =IF(U12<>"",$O12,"") -> 562913.28 | W12: =IF($F12&"/Día"=W$9,ROUND(U12/$W$1,1),"") -> 301.5 | X12: =IF(U12=0,0,IF($F12&"/Día"=W$9,ROUND(V12/U12,4),"")) -> 60.2304 | Y12: =IF(U12=0,0,IF($F12&"/Día"=W$9,ROUND(Z12/U12,4),"")) -> 11.2932 | Z12: =IF(U12<>"",$P12,"") -> 105546.24 | AA12: =IF($F12&"/Día"=AC$9,SUM($G12:$H12),"") | AB12: =IF(AA12<>"",$O12,"") | AC12: =IF($F12&"/Día"=AC$9,ROUND(AA12/$W$1,1),"") | AD12: =IF(AA12=0,0,IF($F12&"/Día"=AC$9,ROUND(AB12/AA12,4),"")) | AE12: =IF(AA12=0,0,IF($F12&"/Día"=AC$9,ROUND(AF12/AA12,4),"")) | AF12: =IF(AA12<>"",$P12,"")
A13: - | B13: II-GAS | C13: Servicios | D13: Mes | E13: F1 | F13: MM BTU | G13: 46670.52 | H13: 44626.41 | I13: 2.55 | J13: 2.55 | N13: 1853.41 | O13: =ROUND(G13*I13,2)+ROUND(H13*J13,2)-K13-L13-M13-N13 -> 230953.77 | P13: =ROUND(18.75%*O13,2) -> 43303.83 | Q13: =ROUND($P13*R13/(R13+T13),2) -> 34643.06 | R13: 0.15 | S13: =P13-Q13 -> 8660.77 | T13: 0.0375 | U13: =IF($F13&"/Día"=W$9,SUM($G13:$H13),"") | V13: =IF(U13<>"",$O13,"") | W13: =IF($F13&"/Día"=W$9,ROUND(U13/$W$1,1),"") | X13: =IF(U13=0,0,IF($F13&"/Día"=W$9,ROUND(V13/U13,4),"")) | Y13: =IF(U13=0,0,IF($F13&"/Día"=W$9,ROUND(Z13/U13,4),"")) | Z13: =IF(U13<>"",$P13,"") | AA13: =IF($F13&"/Día"=AC$9,SUM($G13:$H13),"") -> 91296.93 | AB13: =IF(AA13<>"",$O13,"") -> 230953.77 | AC13: =IF($F13&"/Día"=AC$9,ROUND(AA13/$W$1,1),"") -> 2945.1 | AD13: =IF(AA13=0,0,IF($F13&"/Día"=AC$9,ROUND(AB13/AA13,4),"")) -> 2.5297 | AE13: =IF(AA13=0,0,IF($F13&"/Día"=AC$9,ROUND(AF13/AA13,4),"")) -> 0.4743 | AF13: =IF(AA13<>"",$P13,"") -> 43303.83
A14: - | B14: III | C14: Licencia | D14: Quincena | E14: F2 | F14: Bls | G14: 12465 | H14: 13437 | I14: 61.5768 | J14: 63.1877 | N14: 1236.55 | O14: =ROUND(G14*I14,2)+ROUND(H14*J14,2)-K14-L14-M14-N14 -> 1615371.4 | P14: =ROUND(18.75%*O14,2) -> 302882.13 | Q14: =ROUND($O14*R14,2) -> 242305.71 | R14: 0.15 | S14: =ROUND($O14*T14,2) -> 60576.43 | T14: 0.0375 | U14: =IF($F14&"/Día"=W$9,SUM($G14:$H14),"") -> 25902 | V14: =IF(U14<>"",$O14,"") -> 1615371.4 | W14: =IF($F14&"/Día"=W$9,ROUND(U14/$W$1,1),"") -> 835.5 | X14: =IF(U14=0,0,IF($F14&"/Día"=W$9,ROUND(V14/U14,4),"")) -> 62.3647 | Y14: =IF(U14=0,0,IF($F14&"/Día"=W$9,ROUND(Z14/U14,4),"")) -> 11.6934 | Z14: =IF(U14<>"",$P14,"") -> 302882.13 | AA14: =IF($F14&"/Día"=AC$9,SUM($G14:$H14),"") | AB14: =IF(AA14<>"",$O14,"") | AC14: =IF($F14&"/Día"=AC$9,ROUND(AA14/$W$1,1),"") | AD14: =IF(AA14=0,0,IF($F14&"/Día"=AC$9,ROUND(AB14/AA14,4),"")) | AE14: =IF(AA14=0,0,IF($F14&"/Día"=AC$9,ROUND(AF14/AA14,4),"")) | AF14: =IF(AA14<>"",$P14,"")
A15: - | B15: IV | C15: Licencia | D15: Quincena | E15: F2 | F15: Bls | G15: 17654 | H15: 19218 | I15: 61.5768 | J15: 63.1877 | N15: 4217.85 | O15: =ROUND(G15*I15,2)+ROUND(H15*J15,2)-K15-L15-M15-N15 -> 2297200.2 | P15: =ROUND(18.75%*O15,2) -> 430725.04 | Q15: =ROUND($O15*R15,2) -> 344580.03 | R15: 0.15 | S15: =ROUND($O15*T15,2) -> 86145.01 | T15: 0.0375 | U15: =IF($F15&"/Día"=W$9,SUM($G15:$H15),"") -> 36872 | V15: =IF(U15<>"",$O15,"") -> 2297200.2 | W15: =IF($F15&"/Día"=W$9,ROUND(U15/$W$1,1),"") -> 1189.4 | X15: =IF(U15=0,0,IF($F15&"/Día"=W$9,ROUND(V15/U15,4),"")) -> 62.302 | Y15: =IF(U15=0,0,IF($F15&"/Día"=W$9,ROUND(Z15/U15,4),"")) -> 11.6816 | Z15: =IF(U15<>"",$P15,"") -> 430725.04 | AA15: =IF($F15&"/Día"=AC$9,SUM($G15:$H15),"") | AB15: =IF(AA15<>"",$O15,"") | AC15: =IF($F15&"/Día"=AC$9,ROUND(AA15/$W$1,1),"") | AD15: =IF(AA15=0,0,IF($F15&"/Día"=AC$9,ROUND(AB15/AA15,4),"")) | AE15: =IF(AA15=0,0,IF($F15&"/Día"=AC$9,ROUND(AF15/AA15,4),"")) | AF15: =IF(AA15<>"",$P15,"")
A16: - | B16: V | C16: Servicios | D16: Mes | E16: F1 | F16: Bls | H16: 2501 | J16: 62.2551 | N16: 1463.01 | O16: =ROUND(G16*I16,2)+ROUND(H16*J16,2)-K16-L16-M16-N16 -> 154237 | P16: =ROUND(18.75%*O16,2) -> 28919.44 | Q16: =ROUND($O16*R16,2) -> 23135.55 | R16: 0.15 | S16: =ROUND($O16*T16,2) -> 5783.89 | T16: 0.0375 | U16: =IF($F16&"/Día"=W$9,SUM($G16:$H16),"") -> 2501 | V16: =IF(U16<>"",$O16,"") -> 154237 | W16: =IF($F16&"/Día"=W$9,ROUND(U16/$W$1,1),"") -> 80.7 | X16: =IF(U16=0,0,IF($F16&"/Día"=W$9,ROUND(V16/U16,4),"")) -> 61.6701 | Y16: =IF(U16=0,0,IF($F16&"/Día"=W$9,ROUND(Z16/U16,4),"")) -> 11.5632 | Z16: =IF(U16<>"",$P16,"") -> 28919.44 | AA16: =IF($F16&"/Día"=AC$9,SUM($G16:$H16),"") | AB16: =IF(AA16<>"",$O16,"") | AC16: =IF($F16&"/Día"=AC$9,ROUND(AA16/$W$1,1),"") | AD16: =IF(AA16=0,0,IF($F16&"/Día"=AC$9,ROUND(AB16/AA16,4),"")) | AE16: =IF(AA16=0,0,IF($F16&"/Día"=AC$9,ROUND(AF16/AA16,4),"")) | AF16: =IF(AA16<>"",$P16,"")
A17: - | B17: VII/VI | C17: Licencia | D17: Quincena | E17: F2 | F17: Bls | G17: 46539 | H17: 63257 | I17: 61.0268 | J17: 62.6377 | N17: 2185.19 | O17: =ROUND(G17*I17,2)+ROUND(H17*J17,2)-K17-L17-M17-N17 -> 6800214 | P17: =ROUND(18.75%*O17,2) -> 1275040.1 | Q17: =ROUND($O17*R17,2) -> 1020032.1 | R17: 0.15 | S17: =ROUND($O17*T17,2) -> 255008.03 | T17: 0.0375 | U17: =IF($F17&"/Día"=W$9,SUM($G17:$H17),"") -> 109796 | V17: =IF(U17<>"",$O17,"") -> 6800214 | W17: =IF($F17&"/Día"=W$9,ROUND(U17/$W$1,1),"") -> 3541.8 | X17: =IF(U17=0,0,IF($F17&"/Día"=W$9,ROUND(V17/U17,4),"")) -> 61.935 | Y17: =IF(U17=0,0,IF($F17&"/Día"=W$9,ROUND(Z17/U17,4),"")) -> 11.6128 | Z17: =IF(U17<>"",$P17,"") -> 1275040.1 | AA17: =IF($F17&"/Día"=AC$9,SUM($G17:$H17),"") | AB17: =IF(AA17<>"",$O17,"") | AC17: =IF($F17&"/Día"=AC$9,ROUND(AA17/$W$1,1),"") | AD17: =IF(AA17=0,0,IF($F17&"/Día"=AC$9,ROUND(AB17/AA17,4),"")) | AE17: =IF(AA17=0,0,IF($F17&"/Día"=AC$9,ROUND(AF17/AA17,4),"")) | AF17: =IF(AA17<>"",$P17,"")
A18: - | B18: VII | C18: Servicios | D18: Mes | E18: F1 | F18: Bls | O18: =ROUND(G18*I18,2)+ROUND(H18*J18,2)-K18-L18-M18-N18 -> 0 | P18: =ROUND(18.75%*O18,2) -> 0 | Q18: =ROUND($O18*R18,2) -> 0 | R18: 0.15 | S18: =ROUND($O18*T18,2) -> 0 | T18: 0.0375 | U18: =IF($F18&"/Día"=W$9,SUM($G18:$H18),"") -> 0 | V18: =IF(U18<>"",$O18,"") -> 0 | W18: =IF($F18&"/Día"=W$9,ROUND(U18/$W$1,1),"") -> 0 | X18: =IF(U18=0,0,IF($F18&"/Día"=W$9,ROUND(V18/U18,4),"")) -> 0 | Y18: =IF(U18=0,0,IF($F18&"/Día"=W$9,ROUND(Z18/U18,4),"")) -> 0 | Z18: =IF(U18<>"",$P18,"") -> 0 | AA18: =IF($F18&"/Día"=AC$9,SUM($G18:$H18),"") | AB18: =IF(AA18<>"",$O18,"") | AC18: =IF($F18&"/Día"=AC$9,ROUND(AA18/$W$1,1),"") | AD18: =IF(AA18=0,0,IF($F18&"/Día"=AC$9,ROUND(AB18/AA18,4),"")) | AE18: =IF(AA18=0,0,IF($F18&"/Día"=AC$9,ROUND(AF18/AA18,4),"")) | AF18: =IF(AA18<>"",$P18,"")
A19: - | B19: VII/VI-GAS | C19: Licencia | D19: Quincena | E19: F2 | F19: MM BTU | G19: 54248.37 | H19: 59860.6 | I19: 1.8097 | J19: 2.1734 | N19: 2086.61 | O19: =ROUND(G19*I19,2)+ROUND(H19*J19,2)-K19-L19-M19-N19 -> 226187.7 | P19: =ROUND(18.75%*O19,2) -> 42410.19 | Q19: =ROUND($O19*R19,2) -> 33928.16 | R19: 0.15 | S19: =ROUND($O19*T19,2) -> 8482.04 | T19: 0.0375 | U19: =IF($F19&"/Día"=W$9,SUM($G19:$H19),"") | V19: =IF(U19<>"",$O19,"") | W19: =IF($F19&"/Día"=W$9,ROUND(U19/$W$1,1),"") | X19: =IF(U19=0,0,IF($F19&"/Día"=W$9,ROUND(V19/U19,4),"")) | Y19: =IF(U19=0,0,IF($F19&"/Día"=W$9,ROUND(Z19/U19,4),"")) | Z19: =IF(U19<>"",$P19,"") | AA19: =IF($F19&"/Día"=AC$9,SUM($G19:$H19),"") -> 114108.97 | AB19: =IF(AA19<>"",$O19,"") -> 226187.7 | AC19: =IF($F19&"/Día"=AC$9,ROUND(AA19/$W$1,1),"") -> 3680.9 | AD19: =IF(AA19=0,0,IF($F19&"/Día"=AC$9,ROUND(AB19/AA19,4),"")) -> 1.9822 | AE19: =IF(AA19=0,0,IF($F19&"/Día"=AC$9,ROUND(AF19/AA19,4),"")) -> 0.3717 | AF19: =IF(AA19<>"",$P19,"") -> 42410.19
A20: - | B20: IX | C20: Licencia | D20: Quincena | E20: F2 | F20: Bls | G20: 1870 | H20: 3543 | I20: 61.5768 | J20: 63.1877 | N20: 725.6 | O20: =ROUND(G20*I20,2)+ROUND(H20*J20,2)-K20-L20-M20-N20 -> 338297.04 | P20: =ROUND(18.75%*O20,2) -> 63430.7 | Q20: =ROUND($O20*R20,2) -> 50744.56 | R20: 0.15 | S20: =ROUND($O20*T20,2) -> 12686.14 | T20: 0.0375 | U20: =IF($F20&"/Día"=W$9,SUM($G20:$H20),"") -> 5413 | V20: =IF(U20<>"",$O20,"") -> 338297.04 | W20: =IF($F20&"/Día"=W$9,ROUND(U20/$W$1,1),"") -> 174.6 | X20: =IF(U20=0,0,IF($F20&"/Día"=W$9,ROUND(V20/U20,4),"")) -> 62.4971 | Y20: =IF(U20=0,0,IF($F20&"/Día"=W$9,ROUND(Z20/U20,4),"")) -> 11.7182 | Z20: =IF(U20<>"",$P20,"") -> 63430.7 | AA20: =IF($F20&"/Día"=AC$9,SUM($G20:$H20),"") | AB20: =IF(AA20<>"",$O20,"") | AC20: =IF($F20&"/Día"=AC$9,ROUND(AA20/$W$1,1),"") | AD20: =IF(AA20=0,0,IF($F20&"/Día"=AC$9,ROUND(AB20/AA20,4),"")) | AE20: =IF(AA20=0,0,IF($F20&"/Día"=AC$9,ROUND(AF20/AA20,4),"")) | AF20: =IF(AA20<>"",$P20,"")
A21: - | B21: X | C21: Licencia | D21: Quincena | E21: F2 | F21: Bls | G21: 195510 | H21: 209490 | I21: 61.5768 | J21: 63.1877 | N21: 4262.61 | O21: =ROUND(G21*I21,2)+ROUND(H21*J21,2)-K21-L21-M21-N21 -> 25271809 | P21: =ROUND(18.75%*O21,2) -> 4738464.2 | Q21: =ROUND($O21*R21,2) -> 3790771.3 | R21: 0.15 | S21: =ROUND($O21*T21,2) -> 947692.83 | T21: 0.0375 | U21: =IF($F21&"/Día"=W$9,SUM($G21:$H21),"") -> 405000 | V21: =IF(U21<>"",$O21,"") -> 25271809 | W21: =IF($F21&"/Día"=W$9,ROUND(U21/$W$1,1),"") -> 13064.5 | X21: =IF(U21=0,0,IF($F21&"/Día"=W$9,ROUND(V21/U21,4),"")) -> 62.3995 | Y21: =IF(U21=0,0,IF($F21&"/Día"=W$9,ROUND(Z21/U21,4),"")) -> 11.6999 | Z21: =IF(U21<>"",$P21,"") -> 4738464.2 | AA21: =IF($F21&"/Día"=AC$9,SUM($G21:$H21),"") | AB21: =IF(AA21<>"",$O21,"") | AC21: =IF($F21&"/Día"=AC$9,ROUND(AA21/$W$1,1),"") | AD21: =IF(AA21=0,0,IF($F21&"/Día"=AC$9,ROUND(AB21/AA21,4),"")) | AE21: =IF(AA21=0,0,IF($F21&"/Día"=AC$9,ROUND(AF21/AA21,4),"")) | AF21: =IF(AA21<>"",$P21,"")
A22: - | B22: X-GAS | C22: Licencia | D22: Mes | E22: F2 | F22: MM BTU | G22: 253486.59 | H22: 270429.23 | I22: 1.9713 | J22: 1.9713 | N22: 2198.25 | O22: =ROUND(G22*I22,2)+ROUND(H22*J22,2)-K22-L22-M22-N22 -> 1030597 | P22: =ROUND(18.75%*O22,2) -> 193236.94 | Q22: =ROUND($O22*R22,2) -> 154589.55 | R22: 0.15 | S22: =ROUND($O22*T22,2) -> 38647.39 | T22: 0.0375 | U22: =IF($F22&"/Día"=W$9,SUM($G22:$H22),"") | V22: =IF(U22<>"",$O22,"") | W22: =IF($F22&"/Día"=W$9,ROUND(U22/$W$1,1),"") | X22: =IF(U22=0,0,IF($F22&"/Día"=W$9,ROUND(V22/U22,4),"")) | Y22: =IF(U22=0,0,IF($F22&"/Día"=W$9,ROUND(Z22/U22,4),"")) | Z22: =IF(U22<>"",$P22,"") | AA22: =IF($F22&"/Día"=AC$9,SUM($G22:$H22),"") -> 523915.82 | AB22: =IF(AA22<>"",$O22,"") -> 1030597 | AC22: =IF($F22&"/Día"=AC$9,ROUND(AA22/$W$1,1),"") -> 16900.5 | AD22: =IF(AA22=0,0,IF($F22&"/Día"=AC$9,ROUND(AB22/AA22,4),"")) -> 1.9671 | AE22: =IF(AA22=0,0,IF($F22&"/Día"=AC$9,ROUND(AF22/AA22,4),"")) -> 0.3688 | AF22: =IF(AA22<>"",$P22,"") -> 193236.94
A23: - | B23: XIV | C23: Licencia | D23: Mes | E23: F2 | F23: Bls | O23: =ROUND(G23*I23,2)+ROUND(H23*J23,2)-K23-L23-M23-N23 -> 0 | P23: =ROUND(18.75%*O23,2) -> 0 | Q23: =ROUND($O23*R23,2) -> 0 | R23: 0.15 | S23: =ROUND($O23*T23,2) -> 0 | T23: 0.0375 | U23: =IF($F23&"/Día"=W$9,SUM($G23:$H23),"") -> 0 | V23: =IF(U23<>"",$O23,"") -> 0 | W23: =IF($F23&"/Día"=W$9,ROUND(U23/$W$1,1),"") -> 0 | X23: =IF(U23=0,0,IF($F23&"/Día"=W$9,ROUND(V23/U23,4),"")) -> 0 | Y23: =IF(U23=0,0,IF($F23&"/Día"=W$9,ROUND(Z23/U23,4),"")) -> 0 | Z23: =IF(U23<>"",$P23,"") -> 0 | AA23: =IF($F23&"/Día"=AC$9,SUM($G23:$H23),"") | AB23: =IF(AA23<>"",$O23,"") | AC23: =IF($F23&"/Día"=AC$9,ROUND(AA23/$W$1,1),"") | AD23: =IF(AA23=0,0,IF($F23&"/Día"=AC$9,ROUND(AB23/AA23,4),"")) | AE23: =IF(AA23=0,0,IF($F23&"/Día"=AC$9,ROUND(AF23/AA23,4),"")) | AF23: =IF(AA23<>"",$P23,"")
A24: - | B24: XV | C24: Licencia | D24: Quincena | E24: F2 | F24: Bls | G24: 542 | H24: 479 | I24: 61.4585 | J24: 63.27 | N24: 789.01 | O24: =ROUND(G24*I24,2)+ROUND(H24*J24,2)-K24-L24-M24-N24 -> 62827.83 | P24: =ROUND(18.75%*O24,2) -> 11780.22 | Q24: =ROUND($O24*R24,2) -> 9424.17 | R24: 0.15 | S24: =ROUND($O24*T24,2) -> 2356.04 | T24: 0.0375 | U24: =IF($F24&"/Día"=W$9,SUM($G24:$H24),"") -> 1021 | V24: =IF(U24<>"",$O24,"") -> 62827.83 | W24: =IF($F24&"/Día"=W$9,ROUND(U24/$W$1,1),"") -> 32.9 | X24: =IF(U24=0,0,IF($F24&"/Día"=W$9,ROUND(V24/U24,4),"")) -> 61.5356 | Y24: =IF(U24=0,0,IF($F24&"/Día"=W$9,ROUND(Z24/U24,4),"")) -> 11.5379 | Z24: =IF(U24<>"",$P24,"") -> 11780.22 | AA24: =IF($F24&"/Día"=AC$9,SUM($G24:$H24),"") | AB24: =IF(AA24<>"",$O24,"") | AC24: =IF($F24&"/Día"=AC$9,ROUND(AA24/$W$1,1),"") | AD24: =IF(AA24=0,0,IF($F24&"/Día"=AC$9,ROUND(AB24/AA24,4),"")) | AE24: =IF(AA24=0,0,IF($F24&"/Día"=AC$9,ROUND(AF24/AA24,4),"")) | AF24: =IF(AA24<>"",$P24,"")
A25: - | B25: XIII Crudo | C25: Licencia | D25: Quincena | E25: F2 | F25: Bls | G25: 29886 | H25: 39223 | I25: 61.5768 | J25: 63.1877 | N25: 1505.2 | O25: =ROUND(G25*I25,2)+ROUND(H25*J25,2)-K25-L25-M25-N25 -> 4317190.2 | P25: =ROUND(18.75%*O25,2) -> 809473.16 | Q25: =ROUND($O25*R25,2) -> 647578.53 | R25: 0.15 | S25: =ROUND($O25*T25,2) -> 161894.63 | T25: 0.0375 | U25: =IF($F25&"/Día"=W$9,SUM($G25:$H25),"") -> 69109 | V25: =IF(U25<>"",$O25,"") -> 4317190.2 | W25: =IF($F25&"/Día"=W$9,ROUND(U25/$W$1,1),"") -> 2229.3 | X25: =IF(U25=0,0,IF($F25&"/Día"=W$9,ROUND(V25/U25,4),"")) -> 62.4693 | Y25: =IF(U25=0,0,IF($F25&"/Día"=W$9,ROUND(Z25/U25,4),"")) -> 11.713 | Z25: =IF(U25<>"",$P25,"") -> 809473.16 | AA25: =IF($F25&"/Día"=AC$9,SUM($G25:$H25),"") | AB25: =IF(AA25<>"",$O25,"") | AC25: =IF($F25&"/Día"=AC$9,ROUND(AA25/$W$1,1),"") | AD25: =IF(AA25=0,0,IF($F25&"/Día"=AC$9,ROUND(AB25/AA25,4),"")) | AE25: =IF(AA25=0,0,IF($F25&"/Día"=AC$9,ROUND(AF25/AA25,4),"")) | AF25: =IF(AA25<>"",$P25,"")
A26: - | B26: XIII COND | C26: Licencia | D26: Quincena | E26: F2 | F26: Bls | O26: =ROUND(G26*I26,2)+ROUND(H26*J26,2)-K26-L26-M26-N26 -> 0 | P26: =ROUND(18.75%*O26,2) -> 0 | Q26: =ROUND($O26*R26,2) -> 0 | R26: 0.15 | S26: =ROUND($O26*T26,2) -> 0 | T26: 0.0375 | U26: =IF($F26&"/Día"=W$9,SUM($G26:$H26),"") -> 0 | V26: =IF(U26<>"",$O26,"") -> 0 | W26: =IF($F26&"/Día"=W$9,ROUND(U26/$W$1,1),"") -> 0 | X26: =IF(U26=0,0,IF($F26&"/Día"=W$9,ROUND(V26/U26,4),"")) -> 0 | Y26: =IF(U26=0,0,IF($F26&"/Día"=W$9,ROUND(Z26/U26,4),"")) -> 0 | Z26: =IF(U26<>"",$P26,"") -> 0 | AA26: =IF($F26&"/Día"=AC$9,SUM($G26:$H26),"") | AB26: =IF(AA26<>"",$O26,"") | AC26: =IF($F26&"/Día"=AC$9,ROUND(AA26/$W$1,1),"") | AD26: =IF(AA26=0,0,IF($F26&"/Día"=AC$9,ROUND(AB26/AA26,4),"")) | AE26: =IF(AA26=0,0,IF($F26&"/Día"=AC$9,ROUND(AF26/AA26,4),"")) | AF26: =IF(AA26<>"",$P26,"")
A27: - | B27: XIII Gas | C27: Licencia | D27: Quincena | E27: F2 | F27: MM BTU | G27: =66398.35+67054.56 -> 133452.91 | H27: =103068.34+75979.36 -> 179047.7 | I27: 2.7629297 | J27: 2.5652523 | N27: 3111.05 | O27: =ROUND(G27*I27,2)+ROUND(H27*J27,2)-K27-L27-M27-N27 -> 824912.48 | P27: =ROUND(18.75%*O27,2) -> 154671.09 | Q27: =ROUND($O27*R27,2) -> 123736.87 | R27: 0.15 | S27: =ROUND($O27*T27,2) -> 30934.22 | T27: 0.0375 | U27: =IF($F27&"/Día"=W$9,SUM($G27:$H27),"") | V27: =IF(U27<>"",$O27,"") | W27: =IF($F27&"/Día"=W$9,ROUND(U27/$W$1,1),"") | X27: =IF(U27=0,0,IF($F27&"/Día"=W$9,ROUND(V27/U27,4),"")) | Y27: =IF(U27=0,0,IF($F27&"/Día"=W$9,ROUND(Z27/U27,4),"")) | Z27: =IF(U27<>"",$P27,"") | AA27: =IF($F27&"/Día"=AC$9,SUM($G27:$H27),"") -> 312500.61 | AB27: =IF(AA27<>"",$O27,"") -> 824912.48 | AC27: =IF($F27&"/Día"=AC$9,ROUND(AA27/$W$1,1),"") -> 10080.7 | AD27: =IF(AA27=0,0,IF($F27&"/Día"=AC$9,ROUND(AB27/AA27,4),"")) -> 2.6397 | AE27: =IF(AA27=0,0,IF($F27&"/Día"=AC$9,ROUND(AF27/AA27,4),"")) -> 0.4949 | AF27: =IF(AA27<>"",$P27,"") -> 154671.09
A28: - | B28: Z-2B | C28: Servicios | D28: Mes | E28: F1 | F28: Bls | H28: =213883+40740 -> 254623 | J28: 59.458 | N28: 2405.36 | O28: =ROUND(G28*I28,2)+ROUND(H28*J28,2)-K28-L28-M28-N28 -> 15136969 | P28: =ROUND(18.75%*O28,2) -> 2838181.7 | Q28: =ROUND($O28*R28,2) -> 2270545.4 | R28: 0.15 | S28: =ROUND($O28*T28,2) -> 567636.34 | T28: 0.0375 | U28: =IF($F28&"/Día"=W$9,SUM($G28:$H28),"") -> 254623 | V28: =IF(U28<>"",$O28,"") -> 15136969 | W28: =IF($F28&"/Día"=W$9,ROUND(U28/$W$1,1),"") -> 8213.6 | X28: =IF(U28=0,0,IF($F28&"/Día"=W$9,ROUND(V28/U28,4),"")) -> 59.4486 | Y28: =IF(U28=0,0,IF($F28&"/Día"=W$9,ROUND(Z28/U28,4),"")) -> 11.1466 | Z28: =IF(U28<>"",$P28,"") -> 2838181.7 | AA28: =IF($F28&"/Día"=AC$9,SUM($G28:$H28),"") | AB28: =IF(AA28<>"",$O28,"") | AC28: =IF($F28&"/Día"=AC$9,ROUND(AA28/$W$1,1),"") | AD28: =IF(AA28=0,0,IF($F28&"/Día"=AC$9,ROUND(AB28/AA28,4),"")) | AE28: =IF(AA28=0,0,IF($F28&"/Día"=AC$9,ROUND(AF28/AA28,4),"")) | AF28: =IF(AA28<>"",$P28,"")
A29: - | B29: Z-2B GAS | C29: Servicios | D29: Mes | E29: F1 | F29: MM BTU | H29: =268464.02+1104.74+50031.27 -> 319600.03 | J29: 5.2256954 | N29: 2121.14 | O29: =ROUND(G29*I29,2)+ROUND(H29*J29,2)-K29-L29-M29-N29 -> 1668011.3 | P29: =ROUND(18.75%*O29,2) -> 312752.11 | Q29: =ROUND($O29*R29,2) -> 250201.69 | R29: 0.15 | S29: =ROUND($O29*T29,2) -> 62550.42 | T29: 0.0375 | U29: =IF($F29&"/Día"=W$9,SUM($G29:$H29),"") | V29: =IF(U29<>"",$O29,"") | W29: =IF($F29&"/Día"=W$9,ROUND(U29/$W$1,1),"") | X29: =IF(U29=0,0,IF($F29&"/Día"=W$9,ROUND(V29/U29,4),"")) | Y29: =IF(U29=0,0,IF($F29&"/Día"=W$9,ROUND(Z29/U29,4),"")) | Z29: =IF(U29<>"",$P29,"") | AA29: =IF($F29&"/Día"=AC$9,SUM($G29:$H29),"") -> 319600.03 | AB29: =IF(AA29<>"",$O29,"") -> 1668011.3 | AC29: =IF($F29&"/Día"=AC$9,ROUND(AA29/$W$1,1),"") -> 10309.7 | AD29: =IF(AA29=0,0,IF($F29&"/Día"=AC$9,ROUND(AB29/AA29,4),"")) -> 5.2191 | AE29: =IF(AA29=0,0,IF($F29&"/Día"=AC$9,ROUND(AF29/AA29,4),"")) -> 0.9786 | AF29: =IF(AA29<>"",$P29,"") -> 312752.11
A30: - | B30: XX | C30: Licencia | D30: Quincena | E30: F2 | F30: Bls | G30: 389 | H30: 344 | I30: 61.5768 | J30: 63.1877 | N30: 463.42 | O30: =ROUND(G30*I30,2)+ROUND(H30*J30,2)-K30-L30-M30-N30 -> 45226.53 | P30: =ROUND(18.75%*O30,2) -> 8479.97 | Q30: =ROUND($O30*R30,2) -> 1695.99 | R30: 0.0375 | S30: =ROUND($O30*T30,2) -> 6783.98 | T30: 0.15 | U30: =IF($F30&"/Día"=W$9,SUM($G30:$H30),"") -> 733 | V30: =IF(U30<>"",$O30,"") -> 45226.53 | W30: =IF($F30&"/Día"=W$9,ROUND(U30/$W$1,1),"") -> 23.6 | X30: =IF(U30=0,0,IF($F30&"/Día"=W$9,ROUND(V30/U30,4),"")) -> 61.7006 | Y30: =IF(U30=0,0,IF($F30&"/Día"=W$9,ROUND(Z30/U30,4),"")) -> 11.5689 | Z30: =IF(U30<>"",$P30,"") -> 8479.97 | AA30: =IF($F30&"/Día"=AC$9,SUM($G30:$H30),"") | AB30: =IF(AA30<>"",$O30,"") | AC30: =IF($F30&"/Día"=AC$9,ROUND(AA30/$W$1,1),"") | AD30: =IF(AA30=0,0,IF($F30&"/Día"=AC$9,ROUND(AB30/AA30,4),"")) | AE30: =IF(AA30=0,0,IF($F30&"/Día"=AC$9,ROUND(AF30/AA30,4),"")) | AF30: =IF(AA30<>"",$P30,"")
A31: - | B31: Z1 Crudo | C31: Licencia | D31: Quincena | E31: F2 | F31: Bls | H31: 55112 | J31: 63.1877 | N31: 1427.03 | O31: =ROUND(G31*I31,2)+ROUND(H31*J31,2)-K31-L31-M31-N31 -> 3480973.5 | P31: =ROUND(18.75%*O31,2) -> 652682.53 | Q31: =ROUND($O31*R31,2) -> 130536.51 | R31: 0.0375 | S31: =ROUND($O31*T31,2) -> 522146.02 | T31: 0.15 | U31: =IF($F31&"/Día"=W$9,SUM($G31:$H31),"") -> 55112 | V31: =IF(U31<>"",$O31,"") -> 3480973.5 | W31: =IF($F31&"/Día"=W$9,ROUND(U31/$W$1,1),"") -> 1777.8 | X31: =IF(U31=0,0,IF($F31&"/Día"=W$9,ROUND(V31/U31,4),"")) -> 63.1618 | Y31: =IF(U31=0,0,IF($F31&"/Día"=W$9,ROUND(Z31/U31,4),"")) -> 11.8428 | Z31: =IF(U31<>"",$P31,"") -> 652682.53 | AA31: =IF($F31&"/Día"=AC$9,SUM($G31:$H31),"") | AB31: =IF(AA31<>"",$O31,"") | AC31: =IF($F31&"/Día"=AC$9,ROUND(AA31/$W$1,1),"") | AD31: =IF(AA31=0,0,IF($F31&"/Día"=AC$9,ROUND(AB31/AA31,4),"")) | AE31: =IF(AA31=0,0,IF($F31&"/Día"=AC$9,ROUND(AF31/AA31,4),"")) | AF31: =IF(AA31<>"",$P31,"")
A32: - | B32: Z1 Gas | C32: Licencia | D32: Quincena | E32: F2 | F32: MM BTU | O32: =ROUND(G32*I32,2)+ROUND(H32*J32,2)-K32-L32-M32-N32 -> 0 | P32: =ROUND(18.75%*O32,2) -> 0 | Q32: =ROUND($O32*R32,2) -> 0 | R32: 0.0375 | S32: =ROUND($O32*T32,2) -> 0 | T32: 0.15 | U32: =IF($F32&"/Día"=W$9,SUM($G32:$H32),"") | V32: =IF(U32<>"",$O32,"") | W32: =IF($F32&"/Día"=W$9,ROUND(U32/$W$1,1),"") | X32: =IF(U32=0,0,IF($F32&"/Día"=W$9,ROUND(V32/U32,4),"")) | Y32: =IF(U32=0,0,IF($F32&"/Día"=W$9,ROUND(Z32/U32,4),"")) | Z32: =IF(U32<>"",$P32,"") | AA32: =IF($F32&"/Día"=AC$9,SUM($G32:$H32),"") -> 0 | AB32: =IF(AA32<>"",$O32,"") -> 0 | AC32: =IF($F32&"/Día"=AC$9,ROUND(AA32/$W$1,1),"") -> 0 | AD32: =IF(AA32=0,0,IF($F32&"/Día"=AC$9,ROUND(AB32/AA32,4),"")) -> 0 | AE32: =IF(AA32=0,0,IF($F32&"/Día"=AC$9,ROUND(AF32/AA32,4),"")) -> 0 | AF32: =IF(AA32<>"",$P32,"") -> 0
A33: - | B33: Z-2B - LGN | C33: Servicios | D33: Mes | E33: F1 | F33: Bls | H33: =23156+4411 -> 27567 | J33: 58.768 | N33: 2310.53 | O33: =ROUND(G33*I33,2)+ROUND(H33*J33,2)-K33-L33-M33-N33 -> 1617746.9 | P33: =ROUND(18.75%*O33,2) -> 303327.55 | Q33: =ROUND($O33*R33,2) -> 242662.04 | R33: 0.15 | S33: =ROUND($O33*T33,2) -> 60665.51 | T33: 0.0375 | U33: =IF($F33&"/Día"=W$9,SUM($G33:$H33),"") -> 27567 | V33: =IF(U33<>"",$O33,"") -> 1617746.9 | W33: =IF($F33&"/Día"=W$9,ROUND(U33/$W$1,1),"") -> 889.3 | X33: =IF(U33=0,0,IF($F33&"/Día"=W$9,ROUND(V33/U33,4),"")) -> 58.6842 | Y33: =IF(U33=0,0,IF($F33&"/Día"=W$9,ROUND(Z33/U33,4),"")) -> 11.0033 | Z33: =IF(U33<>"",$P33,"") -> 303327.55 | AA33: =IF($F33&"/Día"=AC$9,SUM($G33:$H33),"") | AB33: =IF(AA33<>"",$O33,"") | AC33: =IF($F33&"/Día"=AC$9,ROUND(AA33/$W$1,1),"") | AD33: =IF(AA33=0,0,IF($F33&"/Día"=AC$9,ROUND(AB33/AA33,4),"")) | AE33: =IF(AA33=0,0,IF($F33&"/Día"=AC$9,ROUND(AF33/AA33,4),"")) | AF33: =IF(AA33<>"",$P33,"")
A34: - | B34: Z-6 | C34: Licencia | D34: Quincena | E34: F2 | F34: MM BTU | O34: =ROUND(G34*I34,2)+ROUND(H34*J34,2)-K34-L34-M34-N34 -> 0 | P34: =ROUND(18.75%*O34,2) -> 0 | Q34: =ROUND($O34*R34,2) -> 0 | R34: 0.15 | S34: =ROUND($O34*T34,2) -> 0 | T34: 0.0375
A35: - | B35: Ajustes meses anteriores (1) | O35: =+O139 -> -23595.85 | P35: =+P139 -> -4424.22 | Q35: =+Q139 -> -3539.38 | S35: =+S139 -> -884.84 | U35: =IF($F35&"/Día"=W$9,SUM($G35:$H35),"") | V35: =IF(U35<>"",$O35,"") | W35: =IF($F35&"/Día"=W$9,ROUND(U35/$W$1,1),"") | X35: =IF(U35=0,0,IF($F35&"/Día"=W$9,ROUND(V35/U35,4),"")) | Y35: =IF(U35=0,0,IF($F35&"/Día"=W$9,ROUND(Z35/U35,4),"")) | Z35: =IF(U35<>"",$P35,"") | AA35: =IF($F35&"/Día"=AC$9,SUM($G35:$H35),"") | AB35: =IF(AA35<>"",$O35,"") | AC35: =IF($F35&"/Día"=AC$9,ROUND(AA35/$W$1,1),"") | AD35: =IF(AA35=0,0,IF($F35&"/Día"=AC$9,ROUND(AB35/AA35,4),"")) | AE35: =IF(AA35=0,0,IF($F35&"/Día"=AC$9,ROUND(AF35/AA35,4),"")) | AF35: =IF(AA35<>"",$P35,"")
B36: Subtotal | C36: =TEXT(A$9,)&" US$" -> Piura / Tumbes US$ | O36: =SUM(O10:O35) -> 68047212 | P36: =SUM(P10:P35) -> 12758852 | Q36: =SUM(Q10:Q35) -> 9810384.3 | S36: =SUM(S10:S35) -> 2948468 | U36: =SUM(U10:U35) -> 1028828 | V36: =SUM(V10:V35) -> 63308539 | W36: =SUM(W10:W35) -> 33187.8 | X36: =ROUND(V36/U36,4) -> 61.5346 | Y36: =ROUND(Z36/U36,4) -> 11.5377 | Z36: =SUM(Z10:Z35) -> 11870351 | AA36: =SUM(AA10:AA35) -> 1615702.8 | AB36: =SUM(AB10:AB35) -> 4762268.5 | AC36: =SUM(AC10:AC35) -> 52119.5 | AD36: =ROUND(AB36/AA36,4) -> 2.9475 | AE36: =ROUND(AF36/AA36,4) -> 0.5527 | AF36: =SUM(AF10:AF35) -> 892925.35 | AG36: =P36-Z36-AF36 -> -4424.22
C37: =TEXT(A$9,)&" S/." -> Piura / Tumbes S/. | P37: =ROUND($F$1*P36,2) -> 0 | Q37: =ROUND($F$1*Q36,2) -> 0 | S37: =ROUND($F$1*S36,2) -> 0
A38: Provincia Puerto Inca Huanuco | Q38: Puerto Inca
A39: - | B39: 31-D | C39: Licencia | D39: Quincena | E39: F2 | F39: Bls | G39: 2739 | I39: 61.5964 | N39: 1094.07 | O39: =ROUND(G39*I39,2)+ROUND(H39*J39,2)-K39-L39-M39-N39 -> 167618.47 | P39: =ROUND(15%*O39,2) -> 25142.77 | Q39: =ROUND($O39*R39,2) -> 25142.77 | R39: 0.15 | U39: =IF($F39&"/Día"=W$9,SUM($G39:$H39),"") -> 2739 | V39: =IF(U39<>"",$O39,"") -> 167618.47 | W39: =IF($F39&"/Día"=W$9,ROUND(U39/$W$1,1),"") -> 88.4 | X39: =IF(U39=0,0,IF($F39&"/Día"=W$9,ROUND(V39/U39,4),"")) -> 61.197 | Y39: =IF(U39=0,0,IF($F39&"/Día"=W$9,ROUND(Z39/U39,4),"")) -> 9.1795 | Z39: =IF(U39<>"",$P39,"") -> 25142.77 | AA39: =IF($F39&"/Día"=AC$9,SUM($G39:$H39),"") | AB39: =IF(AA39<>"",$O39,"") | AC39: =IF($F39&"/Día"=AC$9,ROUND(AA39/$W$1,1),"") | AD39: =IF(AA39=0,0,IF($F39&"/Día"=AC$9,ROUND(AB39/AA39,4),"")) | AE39: =IF(AA39=0,0,IF($F39&"/Día"=AC$9,ROUND(AF39/AA39,4),"")) | AF39: =IF(AA39<>"",$P39,"")
A40: - | B40: 131 | C40: Licencia | D40: Quincena | E40: F2 | F40: Bls | G40: 43803 | H40: 47994 | I40: 58.7224 | J40: 60.6102 | N40: 9288.93 | O40: =ROUND(G40*I40,2)+ROUND(H40*J40,2)-K40-L40-M40-N40 -> 5471854.3 | P40: =ROUND(15%*O40,2) -> 820778.15 | Q40: =ROUND($O40*R40,2) -> 820778.15 | R40: 0.15 | U40: =IF($F40&"/Día"=W$9,SUM($G40:$H40),"") -> 91797 | V40: =IF(U40<>"",$O40,"") -> 5471854.3 | W40: =IF($F40&"/Día"=W$9,ROUND(U40/$W$1,1),"") -> 2961.2 | X40: =IF(U40=0,0,IF($F40&"/Día"=W$9,ROUND(V40/U40,4),"")) -> 59.6082 | Y40: =IF(U40=0,0,IF($F40&"/Día"=W$9,ROUND(Z40/U40,4),"")) -> 8.9412 | Z40: =IF(U40<>"",$P40,"") -> 820778.15 | AA40: =IF($F40&"/Día"=AC$9,SUM($G40:$H40),"") | AB40: =IF(AA40<>"",$O40,"") | AC40: =IF($F40&"/Día"=AC$9,ROUND(AA40/$W$1,1),"") | AD40: =IF(AA40=0,0,IF($F40&"/Día"=AC$9,ROUND(AB40/AA40,4),"")) | AE40: =IF(AA40=0,0,IF($F40&"/Día"=AC$9,ROUND(AF40/AA40,4),"")) | AF40: =IF(AA40<>"",$P40,"")
A41: - | B41: Ajustes meses anteriores (2) | U41: =IF($F41&"/Día"=W$9,SUM($G41:$H41),"") | V41: =IF(U41<>"",$O41,"") | W41: =IF($F41&"/Día"=W$9,ROUND(U41/$W$1,1),"") | X41: =IF(U41=0,0,IF($F41&"/Día"=W$9,ROUND(V41/U41,4),"")) | Y41: =IF(U41=0,0,IF($F41&"/Día"=W$9,ROUND(Z41/U41,4),"")) | Z41: =IF(U41<>"",$P41,"") | AA41: =IF($F41&"/Día"=AC$9,SUM($G41:$H41),"") | AB41: =IF(AA41<>"",$O41,"") | AC41: =IF($F41&"/Día"=AC$9,ROUND(AA41/$W$1,1),"") | AD41: =IF(AA41=0,0,IF($F41&"/Día"=AC$9,ROUND(AB41/AA41,4),"")) | AE41: =IF(AA41=0,0,IF($F41&"/Día"=AC$9,ROUND(AF41/AA41,4),"")) | AF41: =IF(AA41<>"",$P41,"")
B42: Subtotal | C42: =TEXT(A$38,)&" US$" -> Provincia Puerto Inca Huanuco US$ | O42: =SUM(O39:O41) -> 5639472.8 | P42: =SUM(P39:P41) -> 845920.92 | Q42: =SUM(Q39:Q41) -> 845920.92 | S42: =SUM(S39:S41) -> 0 | U42: =SUM(U39:U41) -> 94536 | V42: =SUM(V39:V41) -> 5639472.8 | W42: =SUM(W39:W41) -> 3049.6 | X42: =ROUND(V42/U42,4) -> 59.6542 | Y42: =ROUND(Z42/U42,4) -> 8.9481 | Z42: =SUM(Z39:Z41) -> 845920.92 | AA42: =SUM(AA39:AA41) -> 0 | AB42: =SUM(AB39:AB41) -> 0 | AC42: =SUM(AC39:AC41) -> 0 | AD42: =IF(AA42=0,0,ROUND(AB42/AA42,4)) -> 0 | AE42: =IF(AA42=0,0,ROUND(AF42/AA42,4)) -> 0 | AF42: =SUM(AF39:AF41) -> 0 | AG42: =P42-Z42-AF42 -> 0
C43: =TEXT(A$38,)&" S/." -> Provincia Puerto Inca Huanuco S/. | P43: =ROUND($F$1*P42,2) -> 0 | Q43: =ROUND($F$1*Q42,2) -> 0 | S43: =ROUND($F$1*S42,2) -> 0
A44: Loreto / Ucayali | Q44: Loreto | S44: Ucayali
A45: - | B45: 31-E | C45: Licencia | D45: Mes | E45: F2 | F45: Bls | G45: 1368 | I45: 50.7155 | N45: 505.22 | O45: =ROUND(G45*I45,2)+ROUND(H45*J45,2)-K45-L45-M45-N45 -> 68873.58 | P45: =ROUND(18.75%*O45,2) -> 12913.8 | Q45: =ROUND($O45*R45,2) -> 10331.04 | R45: 0.15 | S45: =ROUND($O45*T45,2) -> 2582.76 | T45: 0.0375 | U45: =IF($F45&"/Día"=W$9,SUM($G45:$H45),"") -> 1368 | V45: =IF(U45<>"",$O45,"") -> 68873.58 | W45: =IF($F45&"/Día"=W$9,ROUND(U45/$W$1,1),"") -> 44.1 | X45: =IF(U45=0,0,IF($F45&"/Día"=W$9,ROUND(V45/U45,4),"")) -> 50.3462 | Y45: =IF(U45=0,0,IF($F45&"/Día"=W$9,ROUND(Z45/U45,4),"")) -> 9.4399 | Z45: =IF(U45<>"",$P45,"") -> 12913.8 | AA45: =IF($F45&"/Día"=AC$9,SUM($G45:$H45),"") | AB45: =IF(AA45<>"",$O45,"") | AC45: =IF($F45&"/Día"=AC$9,ROUND(AA45/$W$1,1),"") | AD45: =IF(AA45=0,0,IF($F45&"/Día"=AC$9,ROUND(AB45/AA45,4),"")) | AE45: =IF(AA45=0,0,IF($F45&"/Día"=AC$9,ROUND(AF45/AA45,4),"")) | AF45: =IF(AA45<>"",$P45,"")
A46: - | B46: 192 | C46: Servicios | D46: Mes | E46: F1 | F46: Bls | H46: 158494 | J46: 47.0722 | N46: 8353.78 | O46: =ROUND(G46*I46,2)+ROUND(H46*J46,2)-K46-L46-M46-N46 -> 7452307.5 | P46: =ROUND(18.75%*O46,2) -> 1397307.6 | Q46: =ROUND($O46*R46,2) -> 1117846.1 | R46: 0.15 | S46: =ROUND($O46*T46,2) -> 279461.53 | T46: 0.0375 | U46: =IF($F46&"/Día"=W$9,SUM($G46:$H46),"") -> 158494 | V46: =IF(U46<>"",$O46,"") -> 7452307.5 | W46: =IF($F46&"/Día"=W$9,ROUND(U46/$W$1,1),"") -> 5112.7 | X46: =IF(U46=0,0,IF($F46&"/Día"=W$9,ROUND(V46/U46,4),"")) -> 47.0195 | Y46: =IF(U46=0,0,IF($F46&"/Día"=W$9,ROUND(Z46/U46,4),"")) -> 8.8162 | Z46: =IF(U46<>"",$P46,"") -> 1397307.6 | AA46: =IF($F46&"/Día"=AC$9,SUM($G46:$H46),"") | AB46: =IF(AA46<>"",$O46,"") | AC46: =IF($F46&"/Día"=AC$9,ROUND(AA46/$W$1,1),"") | AD46: =IF(AA46=0,0,IF($F46&"/Día"=AC$9,ROUND(AB46/AA46,4),"")) | AE46: =IF(AA46=0,0,IF($F46&"/Día"=AC$9,ROUND(AF46/AA46,4),"")) | AF46: =IF(AA46<>"",$P46,"")
A47: - | B47: 8 | C47: Licencia | D47: Quincena | E47: F2 | F47: Bls | G47: 81642 | H47: 125328 | I47: 46.2682 | J47: 48.4628 | N47: 12445.28 | O47: =ROUND(G47*I47,2)+ROUND(H47*J47,2)-K47-L47-M47-N47 -> 9838728.9 | P47: =ROUND(18.75%*O47,2) -> 1844761.7 | Q47: =ROUND($O47*R47,2) -> 1475809.3 | R47: 0.15 | S47: =ROUND($O47*T47,2) -> 368952.33 | T47: 0.0375 | U47: =IF($F47&"/Día"=W$9,SUM($G47:$H47),"") -> 206970 | V47: =IF(U47<>"",$O47,"") -> 9838728.9 | W47: =IF($F47&"/Día"=W$9,ROUND(U47/$W$1,1),"") -> 6676.5 | X47: =IF(U47=0,0,IF($F47&"/Día"=W$9,ROUND(V47/U47,4),"")) -> 47.537 | Y47: =IF(U47=0,0,IF($F47&"/Día"=W$9,ROUND(Z47/U47,4),"")) -> 8.9132 | Z47: =IF(U47<>"",$P47,"") -> 1844761.7 | AA47: =IF($F47&"/Día"=AC$9,SUM($G47:$H47),"") | AB47: =IF(AA47<>"",$O47,"") | AC47: =IF($F47&"/Día"=AC$9,ROUND(AA47/$W$1,1),"") | AD47: =IF(AA47=0,0,IF($F47&"/Día"=AC$9,ROUND(AB47/AA47,4),"")) | AE47: =IF(AA47=0,0,IF($F47&"/Día"=AC$9,ROUND(AF47/AA47,4),"")) | AF47: =IF(AA47<>"",$P47,"")
A48: - | B48: 31-B | C48: Licencia | D48: Quincena | E48: F2 | F48: Bls | G48: 1236 | I48: 61.5964 | N48: 646.22 | O48: =ROUND(G48*I48,2)+ROUND(H48*J48,2)-K48-L48-M48-N48 -> 75486.93 | P48: =ROUND(18.75%*O48,2) -> 14153.8 | Q48: =ROUND($O48*R48,2) -> 11323.04 | R48: 0.15 | S48: =ROUND($O48*T48,2) -> 2830.76 | T48: 0.0375 | U48: =IF($F48&"/Día"=W$9,SUM($G48:$H48),"") -> 1236 | V48: =IF(U48<>"",$O48,"") -> 75486.93 | W48: =IF($F48&"/Día"=W$9,ROUND(U48/$W$1,1),"") -> 39.9 | X48: =IF(U48=0,0,IF($F48&"/Día"=W$9,ROUND(V48/U48,4),"")) -> 61.0736 | Y48: =IF(U48=0,0,IF($F48&"/Día"=W$9,ROUND(Z48/U48,4),"")) -> 11.4513 | Z48: =IF(U48<>"",$P48,"") -> 14153.8 | AA48: =IF($F48&"/Día"=AC$9,SUM($G48:$H48),"") | AB48: =IF(AA48<>"",$O48,"") | AC48: =IF($F48&"/Día"=AC$9,ROUND(AA48/$W$1,1),"") | AD48: =IF(AA48=0,0,IF($F48&"/Día"=AC$9,ROUND(AB48/AA48,4),"")) | AE48: =IF(AA48=0,0,IF($F48&"/Día"=AC$9,ROUND(AF48/AA48,4),"")) | AF48: =IF(AA48<>"",$P48,"")
A49: - | B49: 31-C GAS | C49: Licencia | D49: Quincena | E49: F2 | F49: MM BTU | G49: 84478.392 | H49: 7574.7703 | I49: 3.7464 | J49: 3.7464 | N49: 1164.7 | O49: =ROUND(G49*I49,2)+ROUND(H49*J49,2)-K49-L49-M49-N49 -> 343703.27 | P49: =ROUND(18.75%*O49,2) -> 64444.36 | Q49: =ROUND($O49*R49,2) -> 12888.87 | R49: 0.0375 | S49: =ROUND($O49*T49,2) -> 51555.49 | T49: 0.15 | U49: =IF($F49&"/Día"=W$9,SUM($G49:$H49),"") | V49: =IF(U49<>"",$O49,"") | W49: =IF($F49&"/Día"=W$9,ROUND(U49/$W$1,1),"") | X49: =IF(U49=0,0,IF($F49&"/Día"=W$9,ROUND(V49/U49,4),"")) | Y49: =IF(U49=0,0,IF($F49&"/Día"=W$9,ROUND(Z49/U49,4),"")) | Z49: =IF(U49<>"",$P49,"") | AA49: =IF($F49&"/Día"=AC$9,SUM($G49:$H49),"") -> 92053.162 | AB49: =IF(AA49<>"",$O49,"") -> 343703.27 | AC49: =IF($F49&"/Día"=AC$9,ROUND(AA49/$W$1,1),"") -> 2969.5 | AD49: =IF(AA49=0,0,IF($F49&"/Día"=AC$9,ROUND(AB49/AA49,4),"")) -> 3.7337 | AE49: =IF(AA49=0,0,IF($F49&"/Día"=AC$9,ROUND(AF49/AA49,4),"")) -> 0.7001 | AF49: =IF(AA49<>"",$P49,"") -> 64444.36
A50: - | B50: 31-C LGN (*) | C50: Licencia | D50: Quincena | E50: F3 | F50: Bls | G50: 16329 | H50: 15499 | I50: 54.8234 | J50: 55.0094 | N50: 5271.08 | O50: =ROUND(G50*I50,2)+ROUND(H50*J50,2)-K50-L50-M50-N50 -> 1742530.9 | P50: =ROUND(18.75%*O50,2) -> 326724.55 | Q50: =ROUND($O50*R50,2) -> 65344.91 | R50: 0.0375 | S50: =ROUND($O50*T50,2) -> 261379.64 | T50: 0.15 | U50: =IF($F50&"/Día"=W$9,SUM($G50:$H50),"") -> 31828 | V50: =IF(U50<>"",$O50,"") -> 1742530.9 | W50: =IF($F50&"/Día"=W$9,ROUND(U50/$W$1,1),"") -> 1026.7 | X50: =IF(U50=0,0,IF($F50&"/Día"=W$9,ROUND(V50/U50,4),"")) -> 54.7484 | Y50: =IF(U50=0,0,IF($F50&"/Día"=W$9,ROUND(Z50/U50,4),"")) -> 10.2653 | Z50: =IF(U50<>"",$P50,"") -> 326724.55 | AA50: =IF($F50&"/Día"=AC$9,SUM($G50:$H50),"") | AB50: =IF(AA50<>"",$O50,"") | AC50: =IF($F50&"/Día"=AC$9,ROUND(AA50/$W$1,1),"") | AD50: =IF(AA50=0,0,IF($F50&"/Día"=AC$9,ROUND(AB50/AA50,4),"")) | AE50: =IF(AA50=0,0,IF($F50&"/Día"=AC$9,ROUND(AF50/AA50,4),"")) | AF50: =IF(AA50<>"",$P50,"")
A51: - | B51: 31-C COND | C51: Licencia | D51: Quincena | E51: F2 | F51: Bls | O51: =ROUND(G51*I51,2)+ROUND(H51*J51,2)-K51-L51-M51-N51 -> 0 | P51: =ROUND(18.75%*O51,2) -> 0 | Q51: =ROUND($O51*R51,2) -> 0 | R51: 0.0375 | S51: =ROUND($O51*T51,2) -> 0 | T51: 0.15 | U51: =IF($F51&"/Día"=W$9,SUM($G51:$H51),"") -> 0 | V51: =IF(U51<>"",$O51,"") -> 0 | W51: =IF($F51&"/Día"=W$9,ROUND(U51/$W$1,1),"") -> 0 | X51: =IF(U51=0,0,IF($F51&"/Día"=W$9,ROUND(V51/U51,4),"")) -> 0 | Y51: =IF(U51=0,0,IF($F51&"/Día"=W$9,ROUND(Z51/U51,4),"")) -> 0 | Z51: =IF(U51<>"",$P51,"") -> 0 | AA51: =IF($F51&"/Día"=AC$9,SUM($G51:$H51),"") | AB51: =IF(AA51<>"",$O51,"") | AC51: =IF($F51&"/Día"=AC$9,ROUND(AA51/$W$1,1),"") | AD51: =IF(AA51=0,0,IF($F51&"/Día"=AC$9,ROUND(AB51/AA51,4),"")) | AE51: =IF(AA51=0,0,IF($F51&"/Día"=AC$9,ROUND(AF51/AA51,4),"")) | AF51: =IF(AA51<>"",$P51,"")
A52: - | B52: 102 | C52: Licencia | D52: Quincena | E52: F2 | F52: Bls | O52: =ROUND(G52*I52,2)+ROUND(H52*J52,2)-K52-L52-M52-N52 -> 0 | P52: =ROUND(18.75%*O52,2) -> 0 | Q52: =P52-S52 -> 0 | R52: 0.15 | S52: =ROUND($O52*T52,2) -> 0 | T52: 0.0375 | U52: =IF($F52&"/Día"=W$9,SUM($G52:$H52),"") -> 0 | V52: =IF(U52<>"",$O52,"") -> 0 | W52: =IF($F52&"/Día"=W$9,ROUND(U52/$W$1,1),"") -> 0 | X52: =IF(U52=0,0,IF($F52&"/Día"=W$9,ROUND(V52/U52,4),"")) -> 0 | Y52: =IF(U52=0,0,IF($F52&"/Día"=W$9,ROUND(Z52/U52,4),"")) -> 0 | Z52: =IF(U52<>"",$P52,"") -> 0 | AA52: =IF($F52&"/Día"=AC$9,SUM($G52:$H52),"") | AB52: =IF(AA52<>"",$O52,"") | AC52: =IF($F52&"/Día"=AC$9,ROUND(AA52/$W$1,1),"") | AD52: =IF(AA52=0,0,IF($F52&"/Día"=AC$9,ROUND(AB52/AA52,4),"")) | AE52: =IF(AA52=0,0,IF($F52&"/Día"=AC$9,ROUND(AF52/AA52,4),"")) | AF52: =IF(AA52<>"",$P52,"")
A53: - | B53: 95 | C53: Licencia | D53: Quincena | E53: F2 | F53: Bls | O53: =ROUND(G53*I53,2)+ROUND(H53*J53,2)-K53-L53-M53-N53 -> 0 | P53: =ROUND(18.75%*O53,2) -> 0 | Q53: =P53-S53 -> 0 | R53: 0.15 | S53: =ROUND($O53*T53,2) -> 0 | T53: 0.0375 | U53: =IF($F53&"/Día"=W$9,SUM($G53:$H53),"") -> 0 | V53: =IF(U53<>"",$O53,"") -> 0 | W53: =IF($F53&"/Día"=W$9,ROUND(U53/$W$1,1),"") -> 0 | X53: =IF(U53=0,0,IF($F53&"/Día"=W$9,ROUND(V53/U53,4),"")) -> 0 | Y53: =IF(U53=0,0,IF($F53&"/Día"=W$9,ROUND(Z53/U53,4),"")) -> 0 | Z53: =IF(U53<>"",$P53,"") -> 0 | AA53: =IF($F53&"/Día"=AC$9,SUM($G53:$H53),"") | AB53: =IF(AA53<>"",$O53,"") | AC53: =IF($F53&"/Día"=AC$9,ROUND(AA53/$W$1,1),"") | AD53: =IF(AA53=0,0,IF($F53&"/Día"=AC$9,ROUND(AB53/AA53,4),"")) | AE53: =IF(AA53=0,0,IF($F53&"/Día"=AC$9,ROUND(AF53/AA53,4),"")) | AF53: =IF(AA53<>"",$P53,"")
A54: - | B54: 67 | C54: Licencia | D54: Quincena | E54: F2 | F54: Bls | O54: =ROUND(G54*I54,2)+ROUND(H54*J54,2)-K54-L54-M54-N54 -> 0 | P54: =ROUND(18.75%*O54,2) -> 0 | Q54: =P54-S54 -> 0 | R54: 0.15 | S54: =ROUND($O54*T54,2) -> 0 | T54: 0.0375 | U54: =IF($F54&"/Día"=W$9,SUM($G54:$H54),"") -> 0 | V54: =IF(U54<>"",$O54,"") -> 0 | W54: =IF($F54&"/Día"=W$9,ROUND(U54/$W$1,1),"") -> 0 | X54: =IF(U54=0,0,IF($F54&"/Día"=W$9,ROUND(V54/U54,4),"")) -> 0 | Y54: =IF(U54=0,0,IF($F54&"/Día"=W$9,ROUND(Z54/U54,4),"")) -> 0 | Z54: =IF(U54<>"",$P54,"") -> 0 | AA54: =IF($F54&"/Día"=AC$9,SUM($G54:$H54),"") | AB54: =IF(AA54<>"",$O54,"") | AC54: =IF($F54&"/Día"=AC$9,ROUND(AA54/$W$1,1),"") | AD54: =IF(AA54=0,0,IF($F54&"/Día"=AC$9,ROUND(AB54/AA54,4),"")) | AE54: =IF(AA54=0,0,IF($F54&"/Día"=AC$9,ROUND(AF54/AA54,4),"")) | AF54: =IF(AA54<>"",$P54,"")
A55: - | B55: Ajustes meses anteriores (3) | O55: =+O142 -> 599.98 | P55: =ROUND(18.75%*O55,2) -> 112.5 | Q55: =+Q142 -> 89.99 | S55: =+S142 -> 22.5 | U55: =IF($F55&"/Día"=W$9,SUM($G55:$H55),"") | V55: =IF(U55<>"",$O55,"") | W55: =IF($F55&"/Día"=W$9,ROUND(U55/$W$1,1),"") | X55: =IF(U55=0,0,IF($F55&"/Día"=W$9,ROUND(V55/U55,4),"")) | Y55: =IF(U55=0,0,IF($F55&"/Día"=W$9,ROUND(Z55/U55,4),"")) | Z55: =IF(U55<>"",$P55,"") | AA55: =IF($F55&"/Día"=AC$9,SUM($G55:$H55),"") | AB55: =IF(AA55<>"",$O55,"") | AC55: =IF($F55&"/Día"=AC$9,ROUND(AA55/$W$1,1),"") | AD55: =IF(AA55=0,0,IF($F55&"/Día"=AC$9,ROUND(AB55/AA55,4),"")) | AE55: =IF(AA55=0,0,IF($F55&"/Día"=AC$9,ROUND(AF55/AA55,4),"")) | AF55: =IF(AA55<>"",$P55,"")
B56: Subtotal | C56: =TEXT(A$44,)&" US$" -> Loreto / Ucayali US$ | O56: =SUM(O45:O55) -> 19522231 | P56: =SUM(P45:P55) -> 3660418.3 | Q56: =SUM(Q45:Q55) -> 2693633.3 | S56: =SUM(S45:S55) -> 966785.01 | U56: =SUM(U45:U55) -> 399896 | V56: =SUM(V45:V55) -> 19177928 | W56: =SUM(W45:W55) -> 12899.9 | X56: =ROUND(V56/U56,4) -> 47.9573 | Y56: =ROUND(Z56/U56,4) -> 8.992 | Z56: =SUM(Z45:Z55) -> 3595861.5 | AA56: =SUM(AA45:AA55) -> 92053.162 | AB56: =SUM(AB45:AB55) -> 343703.27 | AC56: =SUM(AC45:AC55) -> 2969.5 | AD56: =ROUND(AB56/AA56,4) -> 3.7337 | AE56: =ROUND(AF56/AA56,4) -> 0.7001 | AF56: =SUM(AF45:AF55) -> 64444.36 | AG56: =P56-Z56-AF56 -> 112.5
C57: =TEXT(A$44,)&" S/." -> Loreto / Ucayali S/. | P57: =ROUND($F$1*P56,2) -> 0 | Q57: =ROUND($F$1*Q56,2) -> 0 | S57: =ROUND($F$1*S56,2) -> 0
A58: Cusco | P58: V. Regalías | Q58: Cusco
A59: - | B59: 88 LGN | C59: Licencia | D59: Quincena | E59: F4 | F59: Bls | G59: 723802 | H59: 818485 | I59: 41.5391 | J59: 43.4762 | O59: =G59*I59+H59*J59 -> 65650701 | P59: =ROUND(37.24%*(G59*I59+H59*J59),2) -> 24448321 | Q59: =ROUND(R59*P59,2) -> 12224161 | R59: 0.5 | U59: =IF($F59&"/Día"=W$9,SUM($G59:$H59),"") -> 1542287 | V59: =IF(U59<>"",$O59,"") -> 65650701 | W59: =IF($F59&"/Día"=W$9,ROUND(U59/$W$1,1),"") -> 49751.2 | X59: =IF(U59=0,0,IF($F59&"/Día"=W$9,ROUND(V59/U59,4),"")) -> 42.5671 | Y59: =IF(U59=0,0,IF($F59&"/Día"=W$9,ROUND(Z59/U59,4),"")) -> 7.926 | Z59: =IF(U59<>"",$Q59,"") -> 12224161 | AA59: =IF($F59&"/Día"=AC$9,SUM($G59:$H59),"") | AB59: =IF(AA59<>"",$O59,"") | AC59: =IF($F59&"/Día"=AC$9,ROUND(AA59/$W$1,1),"") | AD59: =IF(AA59=0,0,IF($F59&"/Día"=AC$9,ROUND(AB59/AA59,4),"")) | AE59: =IF(AA59=0,0,IF($F59&"/Día"=AC$9,ROUND(AF59/AA59,4),"")) | AF59: =IF(AA59<>"",$Q59,"")
A60: - | B60: 88 GAS | C60: Licencia | D60: Quincena | E60: F4 | F60: MM BTU | G60: 10073303 | H60: 9746635 | I60: 1.9083 | J60: 1.9083 | O60: =G60*I60+H60*J60 -> 37822387 | P60: =ROUND(37.24%*(G60*I60+H60*J60),2) -> 14085057 | Q60: =ROUND(R60*P60,2) -> 7042528.5 | R60: 0.5 | U60: =IF($F60&"/Día"=W$9,SUM($G60:$H60),"") | V60: =IF(U60<>"",$O60,"") | W60: =IF($F60&"/Día"=W$9,ROUND(U60/$W$1,1),"") | X60: =IF(U60=0,0,IF($F60&"/Día"=W$9,ROUND(V60/U60,4),"")) | Y60: =IF(U60=0,0,IF($F60&"/Día"=W$9,ROUND(Z60/U60,4),"")) | Z60: =IF(U60<>"",$Q60,"") | AA60: =IF($F60&"/Día"=AC$9,SUM($G60:$H60),"") -> 19819938 | AB60: =IF(AA60<>"",$O60,"") -> 37822387 | AC60: =IF($F60&"/Día"=AC$9,ROUND(AA60/$W$1,1),"") -> 639352.8 | AD60: =IF(AA60=0,0,IF($F60&"/Día"=AC$9,ROUND(AB60/AA60,4),"")) -> 1.9083 | AE60: =IF(AA60=0,0,IF($F60&"/Día"=AC$9,ROUND(AF60/AA60,4),"")) -> 0.3553 | AF60: =IF(AA60<>"",$Q60,"") -> 7042528.5
A61: - | B61: 88 GAS -Mlocal | C61: Licencia | D61: Quincena | E61: F4 | F61: MM BTU | G61: 24300.12 | H61: 25520.17 | I61: 2.7753 | J61: 2.7753 | O61: =G61*I61+H61*J61 -> 138266.25 | P61: =ROUND(37.24%*O61,2) -> 51490.35 | Q61: =ROUND(R61*P61,2) -> 25745.18 | R61: 0.5 | U61: =IF($F61&"/Día"=W$9,SUM($G61:$H61),"") | V61: =IF(U61<>"",$O61,"") | W61: =IF($F61&"/Día"=W$9,ROUND(U61/$W$1,1),"") | X61: =IF(U61=0,0,IF($F61&"/Día"=W$9,ROUND(V61/U61,4),"")) | Y61: =IF(U61=0,0,IF($F61&"/Día"=W$9,ROUND(Z61/U61,4),"")) | Z61: =IF(U61<>"",$Q61,"") | AA61: =IF($F61&"/Día"=AC$9,SUM($G61:$H61),"") -> 49820.29 | AB61: =IF(AA61<>"",$O61,"") -> 138266.25 | AC61: =IF($F61&"/Día"=AC$9,ROUND(AA61/$W$1,1),"") -> 1607.1 | AD61: =IF(AA61=0,0,IF($F61&"/Día"=AC$9,ROUND(AB61/AA61,4),"")) -> 2.7753 | AE61: =IF(AA61=0,0,IF($F61&"/Día"=AC$9,ROUND(AF61/AA61,4),"")) -> 0.5168 | AF61: =IF(AA61<>"",$Q61,"") -> 25745.18
A62: - | B62: 88 GAS -PM | C62: Licencia | D62: Quincena | E62: F4 | F62: MM BTU | G62: 897806.7 | H62: 933949.05 | I62: 3.022 | J62: 3.211 | O62: =G62*I62+H62*J62 -> 5712082.2 | P62: =ROUND(38%*G62*I62,2)+ROUND(38%*H62*J62,2) -> 2170591.2 | Q62: =ROUND(R62*P62,2) -> 1085295.6 | R62: 0.5 | U62: =IF($F62&"/Día"=W$9,SUM($G62:$H62),"") | V62: =IF(U62<>"",$O62,"") | W62: =IF($F62&"/Día"=W$9,ROUND(U62/$W$1,1),"") | X62: =IF(U62=0,0,IF($F62&"/Día"=W$9,ROUND(V62/U62,4),"")) | Y62: =IF(U62=0,0,IF($F62&"/Día"=W$9,ROUND(Z62/U62,4),"")) | Z62: =IF(U62<>"",$Q62,"") | AA62: =IF($F62&"/Día"=AC$9,SUM($G62:$H62),"") -> 1831755.8 | AB62: =IF(AA62<>"",$O62,"") -> 5712082.2 | AC62: =IF($F62&"/Día"=AC$9,ROUND(AA62/$W$1,1),"") -> 59088.9 | AD62: =IF(AA62=0,0,IF($F62&"/Día"=AC$9,ROUND(AB62/AA62,4),"")) -> 3.1184 | AE62: =IF(AA62=0,0,IF($F62&"/Día"=AC$9,ROUND(AF62/AA62,4),"")) -> 0.5925 | AF62: =IF(AA62<>"",$Q62,"") -> 1085295.6
A63: - | B63: 56 LGN | C63: Licencia | D63: Quincena | E63: F4 | F63: Bls | G63: 454424 | H63: 474083 | I63: 41.5341 | J63: 43.4761 | O63: =G63*I63+H63*J63 -> 39485372 | P63: =ROUND(40%*G63*I63,2)+ROUND(40%*H63*J63,2) -> 15794149 | Q63: =ROUND(R63*P63,2) -> 7897074.4 | R63: 0.5 | U63: =IF($F63&"/Día"=W$9,SUM($G63:$H63),"") -> 928507 | V63: =IF(U63<>"",$O63,"") -> 39485372 | W63: =IF($F63&"/Día"=W$9,ROUND(U63/$W$1,1),"") -> 29951.8 | X63: =IF(U63=0,0,IF($F63&"/Día"=W$9,ROUND(V63/U63,4),"")) -> 42.5257 | Y63: =IF(U63=0,0,IF($F63&"/Día"=W$9,ROUND(Z63/U63,4),"")) -> 8.5051 | Z63: =IF(U63<>"",$Q63,"") -> 7897074.4 | AA63: =IF($F63&"/Día"=AC$9,SUM($G63:$H63),"") | AB63: =IF(AA63<>"",$O63,"") | AC63: =IF($F63&"/Día"=AC$9,ROUND(AA63/$W$1,1),"") | AD63: =IF(AA63=0,0,IF($F63&"/Día"=AC$9,ROUND(AB63/AA63,4),"")) | AE63: =IF(AA63=0,0,IF($F63&"/Día"=AC$9,ROUND(AF63/AA63,4),"")) | AF63: =IF(AA63<>"",$Q63,"")
A64: - | B64: 56 GAS | C64: Licencia | D64: Quincena | E64: F4 | F64: MM BTU | G64: 7019870 | H64: 7244483.5 | I64: 3.022 | J64: 3.211 | O64: =G64*I64+H64*J64 -> 44476084 | P64: =ROUND(38%*G64*I64,2)+ROUND(38%*H64*J64,2) -> 16900912 | Q64: =ROUND(R64*P64,2) -> 8450455.9 | R64: 0.5 | U64: =IF($F64&"/Día"=W$9,SUM($G64:$H64),"") | V64: =IF(U64<>"",$O64,"") | W64: =IF($F64&"/Día"=W$9,ROUND(U64/$W$1,1),"") | X64: =IF(U64=0,0,IF($F64&"/Día"=W$9,ROUND(V64/U64,4),"")) | Y64: =IF(U64=0,0,IF($F64&"/Día"=W$9,ROUND(Z64/U64,4),"")) | Z64: =IF(U64<>"",$Q64,"") | AA64: =IF($F64&"/Día"=AC$9,SUM($G64:$H64),"") -> 14264354 | AB64: =IF(AA64<>"",$O64,"") -> 44476084 | AC64: =IF($F64&"/Día"=AC$9,ROUND(AA64/$W$1,1),"") -> 460140.4 | AD64: =IF(AA64=0,0,IF($F64&"/Día"=AC$9,ROUND(AB64/AA64,4),"")) -> 3.118 | AE64: =IF(AA64=0,0,IF($F64&"/Día"=AC$9,ROUND(AF64/AA64,4),"")) -> 0.5924 | AF64: =IF(AA64<>"",$Q64,"") -> 8450455.9
A65: - | B65: 56 GAS-Mlocal | C65: Licencia | D65: Quincena | E65: F4 | F65: MM BTU | G65: 275481.21 | H65: 272627.36 | I65: 1.8204 | J65: 1.8204 | O65: =G65*I65+H65*J65 -> 997776.84 | P65: =ROUND(37.24%*(G65*I65+H65*J65),2) -> 371572.1 | Q65: =ROUND(R65*P65,2) -> 185786.05 | R65: 0.5 | U65: =IF($F65&"/Día"=W$9,SUM($G65:$H65),"") | V65: =IF(U65<>"",$O65,"") | W65: =IF($F65&"/Día"=W$9,ROUND(U65/$W$1,1),"") | X65: =IF(U65=0,0,IF($F65&"/Día"=W$9,ROUND(V65/U65,4),"")) | Y65: =IF(U65=0,0,IF($F65&"/Día"=W$9,ROUND(Z65/U65,4),"")) | Z65: =IF(U65<>"",$Q65,"") | AA65: =IF($F65&"/Día"=AC$9,SUM($G65:$H65),"") -> 548108.57 | AB65: =IF(AA65<>"",$O65,"") -> 997776.84 | AC65: =IF($F65&"/Día"=AC$9,ROUND(AA65/$W$1,1),"") -> 17680.9 | AD65: =IF(AA65=0,0,IF($F65&"/Día"=AC$9,ROUND(AB65/AA65,4),"")) -> 1.8204 | AE65: =IF(AA65=0,0,IF($F65&"/Día"=AC$9,ROUND(AF65/AA65,4),"")) -> 0.339 | AF65: =IF(AA65<>"",$Q65,"") -> 185786.05
A66: - | B66: 57 LGN | C66: Licencia | D66: Quincena | E66: F4 | F66: Bls | G66: 174422 | H66: 182442 | I66: 37.1662 | J66: 39.1077 | O66: =G66*I66+H66*J66 -> 13617490 | P66: =ROUND(G66*I66,2)*6.05%+ROUND(H66*J66,2)*6.01% -> 821004.19 | Q66: =ROUND(R66*P66,2) -> 410502.09 | R66: 0.5 | U66: =IF($F66&"/Día"=W$9,SUM($G66:$H66),"") -> 356864 | V66: =IF(U66<>"",$O66,"") -> 13617490 | W66: =IF($F66&"/Día"=W$9,ROUND(U66/$W$1,1),"") -> 11511.7 | X66: =IF(U66=0,0,IF($F66&"/Día"=W$9,ROUND(V66/U66,4),"")) -> 38.1588 | Y66: =IF(U66=0,0,IF($F66&"/Día"=W$9,ROUND(Z66/U66,4),"")) -> 1.1503 | Z66: =IF(U66<>"",$Q66,"") -> 410502.09 | AA66: =IF($F66&"/Día"=AC$9,SUM($G66:$H66),"") | AB66: =IF(AA66<>"",$O66,"") | AC66: =IF($F66&"/Día"=AC$9,ROUND(AA66/$W$1,1),"") | AD66: =IF(AA66=0,0,IF($F66&"/Día"=AC$9,ROUND(AB66/AA66,4),"")) | AE66: =IF(AA66=0,0,IF($F66&"/Día"=AC$9,ROUND(AF66/AA66,4),"")) | AF66: =IF(AA66<>"",$Q66,"")
A67: - | B67: 57 GAS | C67: Licencia | D67: Quincena | E67: F4 | F67: MM BTU | G67: 2724943 | H67: 2811643.4 | I67: 1.974 | J67: 1.974 | O67: =G67*I67+H67*J67 -> 10929222 | P67: =ROUND(G67*I67,2)*8.99%+ROUND(H67*J67,2)*8.83% -> 973656.73 | Q67: =ROUND(R67*P67,2) -> 486828.37 | R67: 0.5 | U67: =IF($F67&"/Día"=W$9,SUM($G67:$H67),"") | V67: =IF(U67<>"",$O67,"") | W67: =IF($F67&"/Día"=W$9,ROUND(U67/$W$1,1),"") | X67: =IF(U67=0,0,IF($F67&"/Día"=W$9,ROUND(V67/U67,4),"")) | Y67: =IF(U67=0,0,IF($F67&"/Día"=W$9,ROUND(Z67/U67,4),"")) | Z67: =IF(U67<>"",$Q67,"") | AA67: =IF($F67&"/Día"=AC$9,SUM($G67:$H67),"") -> 5536586.4 | AB67: =IF(AA67<>"",$O67,"") -> 10929222 | AC67: =IF($F67&"/Día"=AC$9,ROUND(AA67/$W$1,1),"") -> 178599.6 | AD67: =IF(AA67=0,0,IF($F67&"/Día"=AC$9,ROUND(AB67/AA67,4),"")) -> 1.974 | AE67: =IF(AA67=0,0,IF($F67&"/Día"=AC$9,ROUND(AF67/AA67,4),"")) -> 0.0879 | AF67: =IF(AA67<>"",$Q67,"") -> 486828.37
A68: - | B68: Ajustes meses anteriores (4) | O68: =+O149 -> 4353435.1 | P68: =+P149 -> 335777.48 | Q68: =+Q149 -> 167888.73 | U68: =IF($F68&"/Día"=W$9,SUM($G68:$H68),"") | V68: =IF(U68<>"",$O68,"") | W68: =IF($F68&"/Día"=W$9,ROUND(U68/$W$1,1),"") | X68: =IF(U68=0,0,IF($F68&"/Día"=W$9,ROUND(V68/U68,4),"")) | Y68: =IF(U68=0,0,IF($F68&"/Día"=W$9,ROUND(Z68/U68,4),"")) | Z68: =IF(U68<>"",$Q68,"") | AA68: =IF($F68&"/Día"=AC$9,SUM($G68:$H68),"") | AB68: =IF(AA68<>"",$O68,"") | AC68: =IF($F68&"/Día"=AC$9,ROUND(AA68/$W$1,1),"") | AD68: =IF(AA68=0,0,IF($F68&"/Día"=AC$9,ROUND(AB68/AA68,4),"")) | AE68: =IF(AA68=0,0,IF($F68&"/Día"=AC$9,ROUND(AF68/AA68,4),"")) | AF68: =IF(AA68<>"",$Q68,"")
B69: Subtotal | C69: =TEXT(A$58,)&" US$" -> Cusco US$ | G69: =SUM(G64:G65) -> 7295351.2 | H69: =SUM(H64:H65) -> 7517110.9 | O69: =SUM(O59:O68) -> 2.2318282e+08 | P69: =SUM(P59:P68) -> 75952531 | Q69: =SUM(Q59:Q68) -> 37976265 | U69: =SUM(U59:U68) -> 2827658 | V69: =SUM(V59:V68) -> 1.1875356e+08 | W69: =SUM(W59:W68) -> 91214.7 | X69: =ROUND(V69/U69,4) -> 41.9971 | Y69: =ROUND(Z69/U69,4) -> 7.261 | Z69: =SUM(Z59:Z68) -> 20531737 | AA69: =SUM(AA59:AA68) -> 42050562 | AB69: =SUM(AB59:AB68) -> 1.0007582e+08 | AC69: =SUM(AC59:AC68) -> 1356469.7 | AD69: =ROUND(AB69/AA69,4) -> 2.3799 | AE69: =ROUND(AF69/AA69,4) -> 0.4109 | AF69: =SUM(AF59:AF68) -> 17276640 | AG69: =Q69-Z69-AF69 -> 167888.73
C70: =TEXT(A$58,)&" S/." -> Cusco S/. | G70: =SUMPRODUCT(I64:I65,G64:G65)/SUM(G64:G65) -> 2.9766261 | H70: =SUMPRODUCT(J64:J65,H64:H65)/SUM(H64:H65) -> 3.1605663 | Q70: =Q69*F1 -> 0
A71: Total General | G71: =G69*G70 -> 21715533 | H71: =H69*H70 -> 23758327 | I71: =H71+G71 -> 45473861 | J71: =+O64+O65 -> 45473861 | K71: =I71-J71 -> 0 | N71: =SUM(N10:N69) -> 77421.52 | O71: =O36+O42+O56+O69 -> 3.1639173e+08 | P71: =Q69+P56+P42+P36 -> 55241457 | Q71: =Q70+P57+P43+P37 -> 0 | U71: =U36+U42+U56+U69 -> 4350918 | V71: =V36+V42+V56+V69 -> 2.068795e+08 | W71: =W36+W42+W56+W69 -> 140352 | X71: =ROUND(V71/U71,4) -> 47.5485 | Y71: =ROUND(Z71/U71,4) -> 8.4681 | Z71: =Z36+Z42+Z56+Z69 -> 36843871 | AA71: =AA36+AA42+AA56+AA69 -> 43758318 | AB71: =AB36+AB42+AB56+AB69 -> 1.0518179e+08 | AC71: =AC36+AC42+AC56+AC69 -> 1411558.7 | AD71: =ROUND(AB71/AA71,4) -> 2.4037 | AE71: =ROUND(AF71/AA71,4) -> 0.4167 | AF71: =AF36+AF42+AF56+AF69 -> 18234009 | AG71: =P71-Z71-AF71 -> 163577.01
A73: (*) | B73: Determinación de Canasta de los Líquidos de Gas Natural (VLGNF) | H73: = ( VC * %P + (PB - TF - TT) * (1 - %P)) | O73: =132524706.83-0.42+151199109.41-0.56+4330439.21-77421.52+28437650.25-3320.68-19431.32+0.44 -> 3.1639173e+08 | U73: Regalía 1Q | V73: =5784791.08-V79 -> 5143627.6 | W73: =+P36 -> 12758852 | X73: Piura / Tumbes
B74: Simbolo | C74: Descripcion | E74: 1ra. Q | F74: 2da. Q | H74: 1ra. Q | O74: =+O73-O71 -> -0.22663754 | U74: Regalía 2Q | V74: =7252550.18-V82 -> 6793106.2 | W74: =+P56 -> 3660418.3 | X74: Loreto / Ucayali
B75: VC | C75: Canasta de Petróleo | E75: =I39 -> 61.5964 | F75: =J39 -> 0 | H75: ="= ("&TEXT(E75,"0.0000")&" * "&TEXT(E78,"0.00%")&" + ("&TEXT(E76,"0.0000")&" - "&TEXT(E77,"0.0000")&" - "&TEXT(E80,"0.0000")&") * (1 - "&TEXT(E78,"0.00%")&"))" -> = (61.5964 * 0.00% + (0.0000 - 0.0000 - 0.0000) * (1 - 0.00%)) | U75: Servicios | V75: 5328457.8 | W75: =+P42 -> 845920.92 | X75: Huanuco
B76: PB | C76: Precio del GLP | H76: =((85.98%*E75+4.4221)*E78+(E76-E77-E80)*(1-E78)) -> 0 | N76: 19431.32 | O76: =392197.48/6482602.94 -> 0.0605 | P76: =428806.71/7134887 -> 0.0601 | V76: =SUM(V73:V75) -> 17265192 | W76: =SUM(W73:W75) -> 17265192 | X76: =+V76-W76 -> 0.064374998
B77: TF | C77: Tarifa de Fraccionam. | N77: 3320.68 | O77: =7549636.74/18874091.86 -> 0.4 | P77: =8244511.97/20611279.92 -> 0.4 | U77: Lote 56 1Q | V77: 7899397.6
B78: %P | C78: % Contenido Pentanos | H78: 2da. Q | N78: =SUM(N76:N77) -> 22752 | O78: =483575.48/5379037.59 -> 0.0899 | P78: =490081.25/5550184.07 -> 0.088299999 | U78: Lote 88 1Q | V78: 9669743.9
B79: QLGNF | C79: Volumen de LGN | H79: ="= ("&TEXT(F75,"0.0000")&" * "&TEXT(F78,"0.00%")&" + ("&TEXT(F76,"0.0000")&" - "&TEXT(F77,"0.0000")&" - "&TEXT(F80,"0.0000")&") * (1 - "&TEXT(F78,"0.00%")&"))" -> = (0.0000 * 0.00% + (0.0000 - 0.0000 - 0.0000) * (1 - 0.00%)) | O79: =8061337.96/21214047.26 -> 0.38 | P79: =8839573.9/23262036.59 -> 0.38 | U79: Lote 57 1Q | V79: 641163.5
B80: TT | C80: Tarifa de Transporte | E80: 0 | F80: 0 | H80: =((85.98%*F75+4.4221)*F78+(F76-F77-F80)*(1-F78)) -> 0 | O80: =1031005.3/2713171.84 -> 0.38 | P80: =1139585.95/2998910.39 -> 0.38 | U80: Lote 56 2Q | V80: 10672064
U81: Lote 88 2Q | V81: 8634452.3
U82: Lote 57 2Q | V82: 459443.99
A83: ="AJUSTES PARA "&UPPER(TEXT(E1,"MMMMMMM YYYY")) -> AJUSTES PARA DICIEMBRE 2021 | V83: =SUM(V77:V82) -> 37976265 | W83: =Q69 -> 37976265 | X83: =V83-W83 -> 0.050000004
A85: (4) | B85: Ajuste correspondiente de Noviembre 2017 (Reporte de Regalía 1ra. Quincena de Diciembre 2017) - Liq. 1187 | V85: =+V73+V77+V78+V79 -> 23353933
A86: Cusco | D86: Período | E86: Fórmula | F86: Unidades | G86: 1ra. Q | H86: 2da. Q / Mes | I86: 1ra. Q | J86: 2da. Q / Mes | K86: Flete Marítimo | L86: Comercialización | M86: Oleoducto | N86: Fiscalización | O86: Valor Producción | P86: V. Regalías | Q86: Cuzco | V86: =+V74+V80+V81+V82 -> 26559067
A87: - | B87: 56 GAS-Mlocal | C87: Licencia | D87: Quincena | E87: F4 | F87: MM BTU | G87: 265775.19 | H87: 255199.54 | I87: 1.8149 | J87: 1.8149 | O87: =G87*I87+H87*J87 -> 945517.03 | P87: =ROUND(37.24%*(G87*I87+H87*J87),2) -> 352110.54 | Q87: =ROUND(R87*P87,2) -> 176055.27 | R87: 0.5 | V87: =+V75 -> 5328457.8
A88: - | B88: =B87 -> 56 GAS-Mlocal | C88: Licencia | D88: Modificación | F88: =F87 -> MM BTU | G88: =+G87 -> 265775.19 | H88: =+H87 -> 255199.54 | I88: 1.8204 | J88: 1.8204 | O88: =G88*I88+H88*J88 -> 948382.39 | P88: =ROUND(37.24%*(G88*I88+H88*J88),2) -> 353177.6 | Q88: =ROUND(R88*P88,2) -> 176588.8 | R88: 0.5 | V88: =SUM(V85:V87) -> 55241457 | X88: =+V88-P71 -> 0.114375
B89: Ajuste | G89: =G88-G87 -> 0 | H89: =H88-H87 -> 0 | I89: =I88-I87 -> 0.0055 | J89: =J88-J87 -> 0.0055 | K89: =K88-K87 -> 0 | L89: =L88-L87 -> 0 | M89: =M88-M87 -> 0 | N89: =N88-N87 -> 0 | ... Q89: =Q88-Q87 -> 533.53 | S89: ok
A91: (4) | B91: Ajuste correspondiente de Noviembre 2017 (Reporte de Regalía 1ra. Quincena de Diciembre 2017) - Liq. 1187
A92: Cusco | D92: Período | E92: Fórmula | F92: Unidades | G92: 1ra. Q | H92: 2da. Q / Mes | I92: 1ra. Q | J92: 2da. Q / Mes | K92: Flete Marítimo | L92: Comercialización | M92: Oleoducto | N92: Fiscalización | O92: Valor Producción | P92: V. Regalías | Q92: Cuzco
A93: - | B93: 57 GAS | C93: Licencia | D93: Quincena | E93: F4 | F93: MM BTU | G93: 2799271.5 | H93: 2505225.3 | I93: 1.097 | J93: 1.097 | O93: =G93*I93+H93*J93 -> 5819033 | P93: =ROUND(G93*I93,2)*9.12%+ROUND(H93*J93,2)*8.61% -> 516679.82 | Q93: =ROUND(R93*P93,2) -> 258339.91 | R93: 0.5
A94: - | B94: =B93 -> 57 GAS | C94: Licencia | D94: Modificación | F94: =F93 -> MM BTU | G94: =+G93 -> 2799271.5 | H94: =+H93 -> 2505225.3 | I94: 1.974 | J94: 1.974 | O94: =G94*I94+H94*J94 -> 10471077 | P94: =ROUND(G94*I94,2)*9.12%+ROUND(H94*J94,2)*8.61% -> 929741.08 | Q94: =ROUND(R94*P94,2) -> 464870.54 | R94: 0.5
B95: Ajuste | G95: =G94-G93 -> 0 | H95: =H94-H93 -> 0 | I95: =I94-I93 -> 0.877 | J95: =J94-J93 -> 0.877 | K95: =K94-K93 -> 0 | L95: =L94-L93 -> 0 | M95: =M94-M93 -> 0 | N95: =N94-N93 -> 0 | ... Q95: =Q94-Q93 -> 206530.63 | S95: ok
A97: (4) | B97: Ajuste correspondiente de Setiembre 2017 (Reporte de Regalía 1ra. Quincena de Diciembre 2017) - Liq. 1187
A98: Cusco | D98: Período | E98: Fórmula | F98: Unidades | G98: 1ra. Q | H98: 2da. Q / Mes | I98: 1ra. Q | J98: 2da. Q / Mes | K98: Flete Marítimo | L98: Comercialización | M98: Oleoducto | N98: Fiscalización | O98: Valor Producción | P98: V. Regalías | Q98: Cuzco
A99: - | B99: 88-GAS | C99: Licencia | D99: Calculo Efectuado | F99: MM BTU | G99: 9787700 | H99: 9337097.3 | I99: 1.9096 | J99: 1.9096 | O99: =G99*I99+H99*J99 -> 36520713 | P99: =ROUND(37.24%*(G99*I99+H99*J99),2) -> 13600314 | Q99: =ROUND(R99*P99,2) -> 6800156.8 | R99: 0.5
A100: - | B100: =B99 -> 88-GAS | C100: Licencia | D100: Modificación | F100: =F99 -> MM BTU | G100: =+G99 -> 9787700 | H100: =+H99 -> 9337097.3 | I100: 1.9157 | J100: 1.9157 | O100: =G100*I100+H100*J100 -> 36637374 | P100: =ROUND(37.24%*(G100*I100+H100*J100),2) -> 13643758 | Q100: =ROUND(R100*P100,2) -> 6821879.1 | R100: 0.5
B101: Ajuste | G101: =G100-G99 -> 0 | H101: =H100-H99 -> 0 | I101: =I100-I99 -> 0.0061 | J101: =J100-J99 -> 0.0061 | K101: =K100-K99 -> 0 | L101: =L100-L99 -> 0 | M101: =M100-M99 -> 0 | N101: =N100-N99 -> 0 | ... Q101: =Q100-Q99 -> 21722.32 | S101: ok
A103: (4) | B103: Ajuste correspondiente de Octubre 2017 (Reporte de Regalía 1ra. Quincena de Diciembre 2017) - Liq. 1187
A104: Cusco | D104: Período | E104: Fórmula | F104: Unidades | G104: 1ra. Q | H104: 2da. Q / Mes | I104: 1ra. Q | J104: 2da. Q / Mes | K104: Flete Marítimo | L104: Comercialización | M104: Oleoducto | N104: Fiscalización | O104: Valor Producción | P104: V. Regalías | Q104: Cuzco
A105: - | B105: 88 GAS | C105: Licencia | D105: Quincena | E105: F4 | F105: MM BTU | G105: 11524972 | H105: 10703362 | I105: 1.9211 | J105: 1.9211 | O105: =G105*I105+H105*J105 -> 42702851 | P105: =ROUND(37.24%*(G105*I105+H105*J105),2) -> 15902542 | Q105: =ROUND(R105*P105,2) -> 7951270.9 | R105: 0.5
A106: - | B106: =B105 -> 88 GAS | C106: Licencia | D106: Modificación | F106: =F105 -> MM BTU | G106: =+G105 -> 11524972 | H106: =+H105 -> 10703362 | I106: 1.9194 | J106: 1.9194 | O106: =G106*I106+H106*J106 -> 42665063 | P106: =ROUND(37.24%*(G106*I106+H106*J106),2) -> 15888469 | Q106: =ROUND(R106*P106,2) -> 7944234.7 | R106: 0.5
...

Sheet Feb (2)
A1: Período de Cálculo: | E1: 43132 | S1: , | U1: Días en el mes | W1: =DATE(YEAR(E1),MONTH(E1)+1,1)-DATE(YEAR(E1),MONTH(E1),1) -> 28
A2: PERUPETRO S.A.
A3: DETERMINACION DEL CANON, SOBRECANON y PARTICIPACION (US$)
A4: ="Correspondiente a "&TEXT(E1,"MMMMMMM YYYY") -> Correspondiente a febrero 2018
A5: ="Tipo de Cambio= "&TEXT(F1,"0.000") -> Tipo de Cambio= 0.000
A7: Localidad | C7: Modalidad de Contrato | D7: Calculo del Canon | F7: Volumen Producción / Venta | I7: Canasta o Valor Venta (US$/Unidad) | K7: Deducción de Gastos para determinación de valor de producción en Punto de Fiscalización (US$) | O7: Valor de la Producción (US$) | P7: Canon y Sobrecanon / Participación (US$) | U7: Resumen por Petróleo y Condensados | AA7: Resumen por Gas Natural | AG7: Control
A8: - Lote | D8: Período | E8: Fórmula | F8: Unidades | G8: 1ra. Q | H8: 2da. Q / Mes | I8: 1ra. Q | J8: 2da. Q / Mes | K8: Flete Marítimo | L8: Comercialización | M8: Oleoducto | N8: Fiscalización | P8: Total | Q8: Localidad 1 | S8: Localidad 2 | U8: Producción / Venta | X8: Valor Prod | Y8: Valor Canon | AA8: Producción / Venta | AD8: Valor Prod | AE8: Valor Canon | AG8: Total
A9: Piura / Tumbes | Q9: Piura | S9: Tumbes | U9: Bls/Mes | V9: V P (US$) | W9: Bls/Día | X9: US$/Bl | Y9: US$/Bl | Z9: US$ | AA9: MM BTU/Mes | AB9: V P (US$) | AC9: MM BTU/Día | AD9: US$/MM BTU | AE9: US$/MM BTU | AF9: US$ | AG9: Canon
A10: - | B10: I | C10: Servicios | D10: Mes | E10: F1 | F10: Bls | H10: 21037 | J10: 63.0188 | N10: 668.38 | O10: =ROUND(G10*I10,2)+ROUND(H10*J10,2)-K10-L10-M10-N10 -> 1325058.1 | P10: =ROUND(18.75%*O10,2) -> 248448.4 | Q10: =ROUND($O10*R10,2) -> 198758.72 | R10: 0.15 | S10: =ROUND($O10*T10,2) -> 49689.68 | T10: 0.0375 | U10: =IF($F10&"/Día"=W$9,SUM($G10:$H10),"") -> 21037 | V10: =IF(U10<>"",$O10,"") -> 1325058.1 | W10: =IF($F10&"/Día"=W$9,ROUND(U10/$W$1,1),"") -> 751.3 | X10: =IF(U10=0,0,IF($F10&"/Día"=W$9,ROUND(V10/U10,4),"")) -> 62.987 | Y10: =IF(U10=0,0,IF($F10&"/Día"=W$9,ROUND(Z10/U10,4),"")) -> 11.8101 | Z10: =IF(U10<>"",$P10,"") -> 248448.4 | AA10: =IF($F10&"/Día"=AC$9,SUM($G10:$H10),"") | AB10: =IF(AA10<>"",$O10,"") | AC10: =IF($F10&"/Día"=AC$9,ROUND(AA10/$W$1,1),"") | AD10: =IF(AA10=0,0,IF($F10&"/Día"=AC$9,ROUND(AB10/AA10,4),"")) | AE10: =IF(AA10=0,0,IF($F10&"/Día"=AC$9,ROUND(AF10/AA10,4),"")) | AF10: =IF(AA10<>"",$P10,"")
A11: - | B11: I GAS | C11: Servicios | D11: Mes | E11: F1 | F11: MM BTU | H11: 216169.9 | J11: 3.0904 | N11: 1871.49 | O11: =ROUND(G11*I11,2)+ROUND(H11*J11,2)-K11-L11-M11-N11 -> 666179.97 | P11: =ROUND(18.75%*O11,2) -> 124908.74 | Q11: =ROUND($O11*R11,2) -> 99927 | R11: 0.15 | S11: =ROUND($O11*T11,2) -> 24981.75 | T11: 0.0375 | U11: =IF($F11&"/Día"=W$9,SUM($G11:$H11),"") | V11: =IF(U11<>"",$O11,"") | W11: =IF($F11&"/Día"=W$9,ROUND(U11/$W$1,1),"") | X11: =IF(U11=0,0,IF($F11&"/Día"=W$9,ROUND(V11/U11,4),"")) | Y11: =IF(U11=0,0,IF($F11&"/Día"=W$9,ROUND(Z11/U11,4),"")) | Z11: =IF(U11<>"",$P11,"") | AA11: =IF($F11&"/Día"=AC$9,SUM($G11:$H11),"") -> 216169.9 | AB11: =IF(AA11<>"",$O11,"") -> 666179.97 | AC11: =IF($F11&"/Día"=AC$9,ROUND(AA11/$W$1,1),"") -> 7720.4 | AD11: =IF(AA11=0,0,IF($F11&"/Día"=AC$9,ROUND(AB11/AA11,4),"")) -> 3.0817 | AE11: =IF(AA11=0,0,IF($F11&"/Día"=AC$9,ROUND(AF11/AA11,4),"")) -> 0.5778 | AF11: =IF(AA11<>"",$P11,"") -> 124908.74
A12: - | B12: II | C12: Licencia | D12: Quincena | E12: F2 | F12: Bls | G12: 4983 | H12: 4008 | I12: 61.567 | J12: 62.1667 | N12: 1725.59 | O12: =ROUND(G12*I12,2)+ROUND(H12*J12,2)-K12-L12-M12-N12 -> 554226.9 | P12: =ROUND(18.75%*O12,2) -> 103917.54 | Q12: =ROUND($O12*R12,2) -> 83134.04 | R12: 0.15 | S12: =ROUND($O12*T12,2) -> 20783.51 | T12: 0.0375 | U12: =IF($F12&"/Día"=W$9,SUM($G12:$H12),"") -> 8991 | V12: =IF(U12<>"",$O12,"") -> 554226.9 | W12: =IF($F12&"/Día"=W$9,ROUND(U12/$W$1,1),"") -> 321.1 | X12: =IF(U12=0,0,IF($F12&"/Día"=W$9,ROUND(V12/U12,4),"")) -> 61.6424 | Y12: =IF(U12=0,0,IF($F12&"/Día"=W$9,ROUND(Z12/U12,4),"")) -> 11.558 | Z12: =IF(U12<>"",$P12,"") -> 103917.54 | AA12: =IF($F12&"/Día"=AC$9,SUM($G12:$H12),"") | AB12: =IF(AA12<>"",$O12,"") | AC12: =IF($F12&"/Día"=AC$9,ROUND(AA12/$W$1,1),"") | AD12: =IF(AA12=0,0,IF($F12&"/Día"=AC$9,ROUND(AB12/AA12,4),"")) | AE12: =IF(AA12=0,0,IF($F12&"/Día"=AC$9,ROUND(AF12/AA12,4),"")) | AF12: =IF(AA12<>"",$P12,"")
A13: - | B13: II-GAS | C13: Servicios | D13: Mes | E13: F1 | F13: MM BTU | G13: 43900.054 | H13: 35893.615 | I13: 2.6775 | J13: 2.6775 | N13: 1842.63 | O13: =ROUND(G13*I13,2)+ROUND(H13*J13,2)-K13-L13-M13-N13 -> 211804.92 | P13: =ROUND(18.75%*O13,2) -> 39713.42 | Q13: =ROUND($O13*R13,2) -> 31770.74 | R13: 0.15 | S13: =ROUND($O13*T13,2) -> 7942.68 | T13: 0.0375 | U13: =IF($F13&"/Día"=W$9,SUM($G13:$H13),"") | V13: =IF(U13<>"",$O13,"") | W13: =IF($F13&"/Día"=W$9,ROUND(U13/$W$1,1),"") | X13: =IF(U13=0,0,IF($F13&"/Día"=W$9,ROUND(V13/U13,4),"")) | Y13: =IF(U13=0,0,IF($F13&"/Día"=W$9,ROUND(Z13/U13,4),"")) | Z13: =IF(U13<>"",$P13,"") | AA13: =IF($F13&"/Día"=AC$9,SUM($G13:$H13),"") -> 79793.67 | AB13: =IF(AA13<>"",$O13,"") -> 211804.92 | AC13: =IF($F13&"/Día"=AC$9,ROUND(AA13/$W$1,1),"") -> 2849.8 | AD13: =IF(AA13=0,0,IF($F13&"/Día"=AC$9,ROUND(AB13/AA13,4),"")) -> 2.6544 | AE13: =IF(AA13=0,0,IF($F13&"/Día"=AC$9,ROUND(AF13/AA13,4),"")) -> 0.4977 | AF13: =IF(AA13<>"",$P13,"") -> 39713.42
A14: - | B14: III | C14: Licencia | D14: Quincena | E14: F2 | F14: Bls | G14: 12004 | H14: 10139 | I14: 62.8598 | J14: 63.2373 | N14: 1229.36 | O14: =ROUND(G14*I14,2)+ROUND(H14*J14,2)-K14-L14-M14-N14 -> 1394502.7 | P14: =ROUND(18.75%*O14,2) -> 261469.25 | Q14: =ROUND($O14*R14,2) -> 209175.4 | R14: 0.15 | S14: =ROUND($O14*T14,2) -> 52293.85 | T14: 0.0375 | U14: =IF($F14&"/Día"=W$9,SUM($G14:$H14),"") -> 22143 | V14: =IF(U14<>"",$O14,"") -> 1394502.7 | W14: =IF($F14&"/Día"=W$9,ROUND(U14/$W$1,1),"") -> 790.8 | X14: =IF(U14=0,0,IF($F14&"/Día"=W$9,ROUND(V14/U14,4),"")) -> 62.9771 | Y14: =IF(U14=0,0,IF($F14&"/Día"=W$9,ROUND(Z14/U14,4),"")) -> 11.8082 | Z14: =IF(U14<>"",$P14,"") -> 261469.25 | AA14: =IF($F14&"/Día"=AC$9,SUM($G14:$H14),"") | AB14: =IF(AA14<>"",$O14,"") | AC14: =IF($F14&"/Día"=AC$9,ROUND(AA14/$W$1,1),"") | AD14: =IF(AA14=0,0,IF($F14&"/Día"=AC$9,ROUND(AB14/AA14,4),"")) | AE14: =IF(AA14=0,0,IF($F14&"/Día"=AC$9,ROUND(AF14/AA14,4),"")) | AF14: =IF(AA14<>"",$P14,"")
A15: - | B15: IV | C15: Licencia | D15: Quincena | E15: F2 | F15: Bls | G15: 23016 | H15: 24801 | I15: 62.8598 | J15: 63.2373 | N15: 3175.04 | O15: =ROUND(G15*I15,2)+ROUND(H15*J15,2)-K15-L15-M15-N15 -> 3011954.4 | P15: =ROUND(18.75%*O15,2) -> 564741.45 | Q15: =ROUND($O15*R15,2) -> 451793.16 | R15: 0.15 | S15: =ROUND($O15*T15,2) -> 112948.29 | T15: 0.0375 | U15: =IF($F15&"/Día"=W$9,SUM($G15:$H15),"") -> 47817 | V15: =IF(U15<>"",$O15,"") -> 3011954.4 | W15: =IF($F15&"/Día"=W$9,ROUND(U15/$W$1,1),"") -> 1707.8 | X15: =IF(U15=0,0,IF($F15&"/Día"=W$9,ROUND(V15/U15,4),"")) -> 62.9892 | Y15: =IF(U15=0,0,IF($F15&"/Día"=W$9,ROUND(Z15/U15,4),"")) -> 11.8105 | Z15: =IF(U15<>"",$P15,"") -> 564741.45 | AA15: =IF($F15&"/Día"=AC$9,SUM($G15:$H15),"") | AB15: =IF(AA15<>"",$O15,"") | AC15: =IF($F15&"/Día"=AC$9,ROUND(AA15/$W$1,1),"") | AD15: =IF(AA15=0,0,IF($F15&"/Día"=AC$9,ROUND(AB15/AA15,4),"")) | AE15: =IF(AA15=0,0,IF($F15&"/Día"=AC$9,ROUND(AF15/AA15,4),"")) | AF15: =IF(AA15<>"",$P15,"")
A16: - | B16: V | C16: Servicios | D16: Mes | E16: F1 | F16: Bls | H16: 2270 | J16: 63.0188 | N16: 1454.5 | O16: =ROUND(G16*I16,2)+ROUND(H16*J16,2)-K16-L16-M16-N16 -> 141598.18 | P16: =ROUND(18.75%*O16,2) -> 26549.66 | Q16: =ROUND($O16*R16,2) -> 21239.73 | R16: 0.15 | S16: =ROUND($O16*T16,2) -> 5309.93 | T16: 0.0375 | U16: =IF($F16&"/Día"=W$9,SUM($G16:$H16),"") -> 2270 | V16: =IF(U16<>"",$O16,"") -> 141598.18 | W16: =IF($F16&"/Día"=W$9,ROUND(U16/$W$1,1),"") -> 81.1 | X16: =IF(U16=0,0,IF($F16&"/Día"=W$9,ROUND(V16/U16,4),"")) -> 62.3781 | Y16: =IF(U16=0,0,IF($F16&"/Día"=W$9,ROUND(Z16/U16,4),"")) -> 11.6959 | Z16: =IF(U16<>"",$P16,"") -> 26549.66 | AA16: =IF($F16&"/Día"=AC$9,SUM($G16:$H16),"") | AB16: =IF(AA16<>"",$O16,"") | AC16: =IF($F16&"/Día"=AC$9,ROUND(AA16/$W$1,1),"") | AD16: =IF(AA16=0,0,IF($F16&"/Día"=AC$9,ROUND(AB16/AA16,4),"")) | AE16: =IF(AA16=0,0,IF($F16&"/Día"=AC$9,ROUND(AF16/AA16,4),"")) | AF16: =IF(AA16<>"",$P16,"")
A17: - | B17: VII/VI | C17: Licencia | D17: Quincena | E17: F2 | F17: Bls | G17: 55352 | H17: 55652 | I17: 62.3098 | J17: 62.6873 | N17: 2172.48 | O17: =ROUND(G17*I17,2)+ROUND(H17*J17,2)-K17-L17-M17-N17 -> 6935473.2 | P17: =ROUND(18.75%*O17,2) -> 1300401.2 | Q17: =ROUND($O17*R17,2) -> 1040321 | R17: 0.15 | S17: =ROUND($O17*T17,2) -> 260080.24 | T17: 0.0375 | U17: =IF($F17&"/Día"=W$9,SUM($G17:$H17),"") -> 111004 | V17: =IF(U17<>"",$O17,"") -> 6935473.2 | W17: =IF($F17&"/Día"=W$9,ROUND(U17/$W$1,1),"") -> 3964.4 | X17: =IF(U17=0,0,IF($F17&"/Día"=W$9,ROUND(V17/U17,4),"")) -> 62.4795 | Y17: =IF(U17=0,0,IF($F17&"/Día"=W$9,ROUND(Z17/U17,4),"")) -> 11.7149 | Z17: =IF(U17<>"",$P17,"") -> 1300401.2 | AA17: =IF($F17&"/Día"=AC$9,SUM($G17:$H17),"") | AB17: =IF(AA17<>"",$O17,"") | AC17: =IF($F17&"/Día"=AC$9,ROUND(AA17/$W$1,1),"") | AD17: =IF(AA17=0,0,IF($F17&"/Día"=AC$9,ROUND(AB17/AA17,4),"")) | AE17: =IF(AA17=0,0,IF($F17&"/Día"=AC$9,ROUND(AF17/AA17,4),"")) | AF17: =IF(AA17<>"",$P17,"")
A18: - | B18: VII | C18: Servicios | D18: Mes | E18: F1 | F18: Bls | O18: =ROUND(G18*I18,2)+ROUND(H18*J18,2)-K18-L18-M18-N18 -> 0 | P18: =ROUND(18.75%*O18,2) -> 0 | Q18: =ROUND($O18*R18,2) -> 0 | R18: 0.15 | S18: =ROUND($O18*T18,2) -> 0 | T18: 0.0375 | U18: =IF($F18&"/Día"=W$9,SUM($G18:$H18),"") -> 0 | V18: =IF(U18<>"",$O18,"") -> 0 | W18: =IF($F18&"/Día"=W$9,ROUND(U18/$W$1,1),"") -> 0 | X18: =IF(U18=0,0,IF($F18&"/Día"=W$9,ROUND(V18/U18,4),"")) -> 0 | Y18: =IF(U18=0,0,IF($F18&"/Día"=W$9,ROUND(Z18/U18,4),"")) -> 0 | Z18: =IF(U18<>"",$P18,"") -> 0 | AA18: =IF($F18&"/Día"=AC$9,SUM($G18:$H18),"") | AB18: =IF(AA18<>"",$O18,"") | AC18: =IF($F18&"/Día"=AC$9,ROUND(AA18/$W$1,1),"") | AD18: =IF(AA18=0,0,IF($F18&"/Día"=AC$9,ROUND(AB18/AA18,4),"")) | AE18: =IF(AA18=0,0,IF($F18&"/Día"=AC$9,ROUND(AF18/AA18,4),"")) | AF18: =IF(AA18<>"",$P18,"")
A19: - | B19: VII/VI-GAS | C19: Licencia | D19: Quincena | E19: F2 | F19: MM BTU | G19: 58427.63 | H19: 50453.55 | I19: 2.2141 | J19: 2.2141 | N19: 2074.48 | O19: =ROUND(G19*I19,2)+ROUND(H19*J19,2)-K19-L19-M19-N19 -> 238999.35 | P19: =ROUND(18.75%*O19,2) -> 44812.38 | Q19: =ROUND($O19*R19,2) -> 35849.9 | R19: 0.15 | S19: =ROUND($O19*T19,2) -> 8962.48 | T19: 0.0375 | U19: =IF($F19&"/Día"=W$9,SUM($G19:$H19),"") | V19: =IF(U19<>"",$O19,"") | W19: =IF($F19&"/Día"=W$9,ROUND(U19/$W$1,1),"") | X19: =IF(U19=0,0,IF($F19&"/Día"=W$9,ROUND(V19/U19,4),"")) | Y19: =IF(U19=0,0,IF($F19&"/Día"=W$9,ROUND(Z19/U19,4),"")) | Z19: =IF(U19<>"",$P19,"") | AA19: =IF($F19&"/Día"=AC$9,SUM($G19:$H19),"") -> 108881.18 | AB19: =IF(AA19<>"",$O19,"") -> 238999.35 | AC19: =IF($F19&"/Día"=AC$9,ROUND(AA19/$W$1,1),"") -> 3888.6 | AD19: =IF(AA19=0,0,IF($F19&"/Día"=AC$9,ROUND(AB19/AA19,4),"")) -> 2.195 | AE19: =IF(AA19=0,0,IF($F19&"/Día"=AC$9,ROUND(AF19/AA19,4),"")) -> 0.4116 | AF19: =IF(AA19<>"",$P19,"") -> 44812.38
A20: - | B20: IX | C20: Licencia | D20: Quincena | E20: F2 | F20: Bls | G20: 2061 | H20: 2919 | I20: 62.8598 | J20: 63.2373 | N20: 721.38 | O20: =ROUND(G20*I20,2)+ROUND(H20*J20,2)-K20-L20-M20-N20 -> 313422.35 | P20: =ROUND(18.75%*O20,2) -> 58766.69 | Q20: =ROUND($O20*R20,2) -> 47013.35 | R20: 0.15 | S20: =ROUND($O20*T20,2) -> 11753.34 | T20: 0.0375 | U20: =IF($F20&"/Día"=W$9,SUM($G20:$H20),"") -> 4980 | V20: =IF(U20<>"",$O20,"") -> 313422.35 | W20: =IF($F20&"/Día"=W$9,ROUND(U20/$W$1,1),"") -> 177.9 | X20: =IF(U20=0,0,IF($F20&"/Día"=W$9,ROUND(V20/U20,4),"")) -> 62.9362 | Y20: =IF(U20=0,0,IF($F20&"/Día"=W$9,ROUND(Z20/U20,4),"")) -> 11.8005 | Z20: =IF(U20<>"",$P20,"") -> 58766.69 | AA20: =IF($F20&"/Día"=AC$9,SUM($G20:$H20),"") | AB20: =IF(AA20<>"",$O20,"") | AC20: =IF($F20&"/Día"=AC$9,ROUND(AA20/$W$1,1),"") | AD20: =IF(AA20=0,0,IF($F20&"/Día"=AC$9,ROUND(AB20/AA20,4),"")) | AE20: =IF(AA20=0,0,IF($F20&"/Día"=AC$9,ROUND(AF20/AA20,4),"")) | AF20: =IF(AA20<>"",$P20,"")
A21: - | B21: X | C21: Licencia | D21: Quincena | E21: F2 | F21: Bls | G21: 194807 | H21: 167968 | I21: 62.8598 | J21: 63.2373 | N21: 4237.82 | O21: =ROUND(G21*I21,2)+ROUND(H21*J21,2)-K21-L21-M21-N21 -> 22863134 | P21: =ROUND(18.75%*O21,2) -> 4286837.6 | Q21: =ROUND($O21*R21,2) -> 3429470.1 | R21: 0.15 | S21: =ROUND($O21*T21,2) -> 857367.53 | T21: 0.0375 | U21: =IF($F21&"/Día"=W$9,SUM($G21:$H21),"") -> 362775 | V21: =IF(U21<>"",$O21,"") -> 22863134 | W21: =IF($F21&"/Día"=W$9,ROUND(U21/$W$1,1),"") -> 12956.3 | X21: =IF(U21=0,0,IF($F21&"/Día"=W$9,ROUND(V21/U21,4),"")) -> 63.0229 | Y21: =IF(U21=0,0,IF($F21&"/Día"=W$9,ROUND(Z21/U21,4),"")) -> 11.8168 | Z21: =IF(U21<>"",$P21,"") -> 4286837.6 | AA21: =IF($F21&"/Día"=AC$9,SUM($G21:$H21),"") | AB21: =IF(AA21<>"",$O21,"") | AC21: =IF($F21&"/Día"=AC$9,ROUND(AA21/$W$1,1),"") | AD21: =IF(AA21=0,0,IF($F21&"/Día"=AC$9,ROUND(AB21/AA21,4),"")) | AE21: =IF(AA21=0,0,IF($F21&"/Día"=AC$9,ROUND(AF21/AA21,4),"")) | AF21: =IF(AA21<>"",$P21,"")
A22: - | B22: X-GAS | C22: Licencia | D22: Mes | E22: F2 | F22: MM BTU | G22: 247038.94 | H22: 210769.83 | I22: 1.7948 | J22: 1.7948 | N22: 2185.46 | O22: =ROUND(G22*I22,2)+ROUND(H22*J22,2)-K22-L22-M22-N22 -> 819489.72 | P22: =ROUND(18.75%*O22,2) -> 153654.32 | Q22: =ROUND($O22*R22,2) -> 122923.46 | R22: 0.15 | S22: =ROUND($O22*T22,2) -> 30730.86 | T22: 0.0375 | U22: =IF($F22&"/Día"=W$9,SUM($G22:$H22),"") | V22: =IF(U22<>"",$O22,"") | W22: =IF($F22&"/Día"=W$9,ROUND(U22/$W$1,1),"") | X22: =IF(U22=0,0,IF($F22&"/Día"=W$9,ROUND(V22/U22,4),"")) | Y22: =IF(U22=0,0,IF($F22&"/Día"=W$9,ROUND(Z22/U22,4),"")) | Z22: =IF(U22<>"",$P22,"") | AA22: =IF($F22&"/Día"=AC$9,SUM($G22:$H22),"") -> 457808.77 | AB22: =IF(AA22<>"",$O22,"") -> 819489.72 | AC22: =IF($F22&"/Día"=AC$9,ROUND(AA22/$W$1,1),"") -> 16350.3 | AD22: =IF(AA22=0,0,IF($F22&"/Día"=AC$9,ROUND(AB22/AA22,4),"")) -> 1.79 | AE22: =IF(AA22=0,0,IF($F22&"/Día"=AC$9,ROUND(AF22/AA22,4),"")) -> 0.3356 | AF22: =IF(AA22<>"",$P22,"") -> 153654.32
A23: - | B23: XIV | C23: Licencia | D23: Mes | E23: F2 | F23: Bls | O23: =ROUND(G23*I23,2)+ROUND(H23*J23,2)-K23-L23-M23-N23 -> 0 | P23: =ROUND(18.75%*O23,2) -> 0 | Q23: =ROUND($O23*R23,2) -> 0 | R23: 0.15 | S23: =ROUND($O23*T23,2) -> 0 | T23: 0.0375 | U23: =IF($F23&"/Día"=W$9,SUM($G23:$H23),"") -> 0 | V23: =IF(U23<>"",$O23,"") -> 0 | W23: =IF($F23&"/Día"=W$9,ROUND(U23/$W$1,1),"") -> 0 | X23: =IF(U23=0,0,IF($F23&"/Día"=W$9,ROUND(V23/U23,4),"")) -> 0 | Y23: =IF(U23=0,0,IF($F23&"/Día"=W$9,ROUND(Z23/U23,4),"")) -> 0 | Z23: =IF(U23<>"",$P23,"") -> 0 | AA23: =IF($F23&"/Día"=AC$9,SUM($G23:$H23),"") | AB23: =IF(AA23<>"",$O23,"") | AC23: =IF($F23&"/Día"=AC$9,ROUND(AA23/$W$1,1),"") | AD23: =IF(AA23=0,0,IF($F23&"/Día"=AC$9,ROUND(AB23/AA23,4),"")) | AE23: =IF(AA23=0,0,IF($F23&"/Día"=AC$9,ROUND(AF23/AA23,4),"")) | AF23: =IF(AA23<>"",$P23,"")
A24: - | B24: XV | C24: Licencia | D24: Quincena | E24: F2 | F24: Bls | G24: 565 | H24: 574 | I24: 63.8679 | J24: 64.3152 | N24: 784.43 | O24: =ROUND(G24*I24,2)+ROUND(H24*J24,2)-K24-L24-M24-N24 -> 72217.85 | P24: =ROUND(18.75%*O24,2) -> 13540.85 | Q24: =ROUND($O24*R24,2) -> 10832.68 | R24: 0.15 | S24: =ROUND($O24*T24,2) -> 2708.17 | T24: 0.0375 | U24: =IF($F24&"/Día"=W$9,SUM($G24:$H24),"") -> 1139 | V24: =IF(U24<>"",$O24,"") -> 72217.85 | W24: =IF($F24&"/Día"=W$9,ROUND(U24/$W$1,1),"") -> 40.7 | X24: =IF(U24=0,0,IF($F24&"/Día"=W$9,ROUND(V24/U24,4),"")) -> 63.4046 | Y24: =IF(U24=0,0,IF($F24&"/Día"=W$9,ROUND(Z24/U24,4),"")) -> 11.8884 | Z24: =IF(U24<>"",$P24,"") -> 13540.85 | AA24: =IF($F24&"/Día"=AC$9,SUM($G24:$H24),"") | AB24: =IF(AA24<>"",$O24,"") | AC24: =IF($F24&"/Día"=AC$9,ROUND(AA24/$W$1,1),"") | AD24: =IF(AA24=0,0,IF($F24&"/Día"=AC$9,ROUND(AB24/AA24,4),"")) | AE24: =IF(AA24=0,0,IF($F24&"/Día"=AC$9,ROUND(AF24/AA24,4),"")) | AF24: =IF(AA24<>"",$P24,"")
A25: - | B25: XIII Crudo | C25: Licencia | D25: Quincena | E25: F2 | F25: Bls | G25: 29918 | H25: 27066 | I25: 62.8598 | J25: 63.2373 | N25: 1496.45 | O25: =ROUND(G25*I25,2)+ROUND(H25*J25,2)-K25-L25-M25-N25 -> 3590723.8 | P25: =ROUND(18.75%*O25,2) -> 673260.71 | Q25: =ROUND($O25*R25,2) -> 538608.57 | R25: 0.15 | S25: =ROUND($O25*T25,2) -> 134652.14 | T25: 0.0375 | U25: =IF($F25&"/Día"=W$9,SUM($G25:$H25),"") -> 56984 | V25: =IF(U25<>"",$O25,"") -> 3590723.8 | W25: =IF($F25&"/Día"=W$9,ROUND(U25/$W$1,1),"") -> 2035.1 | X25: =IF(U25=0,0,IF($F25&"/Día"=W$9,ROUND(V25/U25,4),"")) -> 63.0128 | Y25: =IF(U25=0,0,IF($F25&"/Día"=W$9,ROUND(Z25/U25,4),"")) -> 11.8149 | Z25: =IF(U25<>"",$P25,"") -> 673260.71 | AA25: =IF($F25&"/Día"=AC$9,SUM($G25:$H25),"") | AB25: =IF(AA25<>"",$O25,"") | AC25: =IF($F25&"/Día"=AC$9,ROUND(AA25/$W$1,1),"") | AD25: =IF(AA25=0,0,IF($F25&"/Día"=AC$9,ROUND(AB25/AA25,4),"")) | AE25: =IF(AA25=0,0,IF($F25&"/Día"=AC$9,ROUND(AF25/AA25,4),"")) | AF25: =IF(AA25<>"",$P25,"")
A26: - | B26: XIII COND | C26: Licencia | D26: Quincena | E26: F2 | F26: Bls | O26: =ROUND(G26*I26,2)+ROUND(H26*J26,2)-K26-L26-M26-N26 -> 0 | P26: =ROUND(18.75%*O26,2) -> 0 | Q26: =ROUND($O26*R26,2) -> 0 | R26: 0.15 | S26: =ROUND($O26*T26,2) -> 0 | T26: 0.0375 | U26: =IF($F26&"/Día"=W$9,SUM($G26:$H26),"") -> 0 | V26: =IF(U26<>"",$O26,"") -> 0 | W26: =IF($F26&"/Día"=W$9,ROUND(U26/$W$1,1),"") -> 0 | X26: =IF(U26=0,0,IF($F26&"/Día"=W$9,ROUND(V26/U26,4),"")) -> 0 | Y26: =IF(U26=0,0,IF($F26&"/Día"=W$9,ROUND(Z26/U26,4),"")) -> 0 | Z26: =IF(U26<>"",$P26,"") -> 0 | AA26: =IF($F26&"/Día"=AC$9,SUM($G26:$H26),"") | AB26: =IF(AA26<>"",$O26,"") | AC26: =IF($F26&"/Día"=AC$9,ROUND(AA26/$W$1,1),"") | AD26: =IF(AA26=0,0,IF($F26&"/Día"=AC$9,ROUND(AB26/AA26,4),"")) | AE26: =IF(AA26=0,0,IF($F26&"/Día"=AC$9,ROUND(AF26/AA26,4),"")) | AF26: =IF(AA26<>"",$P26,"")
A27: - | B27: XIII Gas | C27: Licencia | D27: Quincena | E27: F2 | F27: MM BTU | G27: =80755.7378+108003.1931 -> 188758.93 | H27: =93892.9507+84259.4053 -> 178152.36 | I27: 2.5834234 | J27: 2.6983454 | N27: 3092.96 | O27: =ROUND(G27*I27,2)+ROUND(H27*J27,2)-K27-L27-M27-N27 -> 965267.86 | P27: =ROUND(18.75%*O27,2) -> 180987.72 | Q27: =ROUND($O27*R27,2) -> 144790.18 | R27: 0.15 | S27: =ROUND($O27*T27,2) -> 36197.54 | T27: 0.0375 | U27: =IF($F27&"/Día"=W$9,SUM($G27:$H27),"") | V27: =IF(U27<>"",$O27,"") | W27: =IF($F27&"/Día"=W$9,ROUND(U27/$W$1,1),"") | X27: =IF(U27=0,0,IF($F27&"/Día"=W$9,ROUND(V27/U27,4),"")) | Y27: =IF(U27=0,0,IF($F27&"/Día"=W$9,ROUND(Z27/U27,4),"")) | Z27: =IF(U27<>"",$P27,"") | AA27: =IF($F27&"/Día"=AC$9,SUM($G27:$H27),"") -> 366911.29 | AB27: =IF(AA27<>"",$O27,"") -> 965267.86 | AC27: =IF($F27&"/Día"=AC$9,ROUND(AA27/$W$1,1),"") -> 13104 | AD27: =IF(AA27=0,0,IF($F27&"/Día"=AC$9,ROUND(AB27/AA27,4),"")) -> 2.6308 | AE27: =IF(AA27=0,0,IF($F27&"/Día"=AC$9,ROUND(AF27/AA27,4),"")) -> 0.4933 | AF27: =IF(AA27<>"",$P27,"") -> 180987.72
A28: - | B28: Z-2B | C28: Servicios | D28: Mes | E28: F1 | F28: Bls | H28: =34290+180024 -> 214314 | J28: 60.9661 | N28: 2391.37 | O28: =ROUND(G28*I28,2)+ROUND(H28*J28,2)-K28-L28-M28-N28 -> 13063497 | P28: =ROUND(18.75%*O28,2) -> 2449405.8 | Q28: =ROUND($O28*R28,2) -> 1959524.6 | R28: 0.15 | S28: =ROUND($O28*T28,2) -> 489881.15 | T28: 0.0375 | U28: =IF($F28&"/Día"=W$9,SUM($G28:$H28),"") -> 214314 | V28: =IF(U28<>"",$O28,"") -> 13063497 | W28: =IF($F28&"/Día"=W$9,ROUND(U28/$W$1,1),"") -> 7654.1 | X28: =IF(U28=0,0,IF($F28&"/Día"=W$9,ROUND(V28/U28,4),"")) -> 60.9549 | Y28: =IF(U28=0,0,IF($F28&"/Día"=W$9,ROUND(Z28/U28,4),"")) -> 11.4291 | Z28: =IF(U28<>"",$P28,"") -> 2449405.8 | AA28: =IF($F28&"/Día"=AC$9,SUM($G28:$H28),"") | AB28: =IF(AA28<>"",$O28,"") | AC28: =IF($F28&"/Día"=AC$9,ROUND(AA28/$W$1,1),"") | AD28: =IF(AA28=0,0,IF($F28&"/Día"=AC$9,ROUND(AB28/AA28,4),"")) | AE28: =IF(AA28=0,0,IF($F28&"/Día"=AC$9,ROUND(AF28/AA28,4),"")) | AF28: =IF(AA28<>"",$P28,"")
A29: - | B29: Z-2B GAS | C29: Servicios | D29: Mes | E29: F1 | F29: MM BTU | H29: =177687.13+1019.28+32825.88 -> 211532.29 | J29: 5.2921608 | N29: 2108.8 | O29: =ROUND(G29*I29,2)+ROUND(H29*J29,2)-K29-L29-M29-N29 -> 1117354.1 | P29: =ROUND(18.75%*O29,2) -> 209503.89 | Q29: =ROUND($O29*R29,2) -> 167603.12 | R29: 0.15 | S29: =ROUND($O29*T29,2) -> 41900.78 | T29: 0.0375 | U29: =IF($F29&"/Día"=W$9,SUM($G29:$H29),"") | V29: =IF(U29<>"",$O29,"") | W29: =IF($F29&"/Día"=W$9,ROUND(U29/$W$1,1),"") | X29: =IF(U29=0,0,IF($F29&"/Día"=W$9,ROUND(V29/U29,4),"")) | Y29: =IF(U29=0,0,IF($F29&"/Día"=W$9,ROUND(Z29/U29,4),"")) | Z29: =IF(U29<>"",$P29,"") | AA29: =IF($F29&"/Día"=AC$9,SUM($G29:$H29),"") -> 211532.29 | AB29: =IF(AA29<>"",$O29,"") -> 1117354.1 | AC29: =IF($F29&"/Día"=AC$9,ROUND(AA29/$W$1,1),"") -> 7554.7 | AD29: =IF(AA29=0,0,IF($F29&"/Día"=AC$9,ROUND(AB29/AA29,4),"")) -> 5.2822 | AE29: =IF(AA29=0,0,IF($F29&"/Día"=AC$9,ROUND(AF29/AA29,4),"")) -> 0.9904 | AF29: =IF(AA29<>"",$P29,"") -> 209503.89
A30: - | B30: XX | C30: Licencia | D30: Quincena | E30: F2 | F30: Bls | G30: 326 | H30: 229 | I30: 62.8598 | J30: 63.2373 | N30: 460.72 | O30: =ROUND(G30*I30,2)+ROUND(H30*J30,2)-K30-L30-M30-N30 -> 34512.91 | P30: =ROUND(18.75%*O30,2) -> 6471.17 | Q30: =ROUND($O30*R30,2) -> 1294.23 | R30: 0.0375 | S30: =ROUND($O30*T30,2) -> 5176.94 | T30: 0.15 | U30: =IF($F30&"/Día"=W$9,SUM($G30:$H30),"") -> 555 | V30: =IF(U30<>"",$O30,"") -> 34512.91 | W30: =IF($F30&"/Día"=W$9,ROUND(U30/$W$1,1),"") -> 19.8 | X30: =IF(U30=0,0,IF($F30&"/Día"=W$9,ROUND(V30/U30,4),"")) -> 62.1854 | Y30: =IF(U30=0,0,IF($F30&"/Día"=W$9,ROUND(Z30/U30,4),"")) -> 11.6598 | Z30: =IF(U30<>"",$P30,"") -> 6471.17 | AA30: =IF($F30&"/Día"=AC$9,SUM($G30:$H30),"") | AB30: =IF(AA30<>"",$O30,"") | AC30: =IF($F30&"/Día"=AC$9,ROUND(AA30/$W$1,1),"") | AD30: =IF(AA30=0,0,IF($F30&"/Día"=AC$9,ROUND(AB30/AA30,4),"")) | AE30: =IF(AA30=0,0,IF($F30&"/Día"=AC$9,ROUND(AF30/AA30,4),"")) | AF30: =IF(AA30<>"",$P30,"")
A31: - | B31: Z1 Crudo | C31: Licencia | D31: Quincena | E31: F2 | F31: Bls | G31: 78469 | I31: 62.8598 | N31: 1418.72 | O31: =ROUND(G31*I31,2)+ROUND(H31*J31,2)-K31-L31-M31-N31 -> 4931126.9 | P31: =ROUND(18.75%*O31,2) -> 924586.3 | Q31: =ROUND($O31*R31,2) -> 184917.26 | R31: 0.0375 | S31: =ROUND($O31*T31,2) -> 739669.04 | T31: 0.15 | U31: =IF($F31&"/Día"=W$9,SUM($G31:$H31),"") -> 78469 | V31: =IF(U31<>"",$O31,"") -> 4931126.9 | W31: =IF($F31&"/Día"=W$9,ROUND(U31/$W$1,1),"") -> 2802.5 | X31: =IF(U31=0,0,IF($F31&"/Día"=W$9,ROUND(V31/U31,4),"")) -> 62.8417 | Y31: =IF(U31=0,0,IF($F31&"/Día"=W$9,ROUND(Z31/U31,4),"")) -> 11.7828 | Z31: =IF(U31<>"",$P31,"") -> 924586.3 | AA31: =IF($F31&"/Día"=AC$9,SUM($G31:$H31),"") | AB31: =IF(AA31<>"",$O31,"") | AC31: =IF($F31&"/Día"=AC$9,ROUND(AA31/$W$1,1),"") | AD31: =IF(AA31=0,0,IF($F31&"/Día"=AC$9,ROUND(AB31/AA31,4),"")) | AE31: =IF(AA31=0,0,IF($F31&"/Día"=AC$9,ROUND(AF31/AA31,4),"")) | AF31: =IF(AA31<>"",$P31,"")
A32: - | B32: Z1 Gas | C32: Licencia | D32: Quincena | E32: F2 | F32: MM BTU | O32: =ROUND(G32*I32,2)+ROUND(H32*J32,2)-K32-L32-M32-N32 -> 0 | P32: =ROUND(18.75%*O32,2) -> 0 | Q32: =ROUND($O32*R32,2) -> 0 | R32: 0.0375 | S32: =ROUND($O32*T32,2) -> 0 | T32: 0.15 | U32: =IF($F32&"/Día"=W$9,SUM($G32:$H32),"") | V32: =IF(U32<>"",$O32,"") | W32: =IF($F32&"/Día"=W$9,ROUND(U32/$W$1,1),"") | X32: =IF(U32=0,0,IF($F32&"/Día"=W$9,ROUND(V32/U32,4),"")) | Y32: =IF(U32=0,0,IF($F32&"/Día"=W$9,ROUND(Z32/U32,4),"")) | Z32: =IF(U32<>"",$P32,"") | AA32: =IF($F32&"/Día"=AC$9,SUM($G32:$H32),"") -> 0 | AB32: =IF(AA32<>"",$O32,"") -> 0 | AC32: =IF($F32&"/Día"=AC$9,ROUND(AA32/$W$1,1),"") -> 0 | AD32: =IF(AA32=0,0,IF($F32&"/Día"=AC$9,ROUND(AB32/AA32,4),"")) -> 0 | AE32: =IF(AA32=0,0,IF($F32&"/Día"=AC$9,ROUND(AF32/AA32,4),"")) -> 0 | AF32: =IF(AA32<>"",$P32,"") -> 0
A33: - | B33: Z-2B - LGN | C33: Servicios | D33: Mes | E33: F1 | F33: Bls | H33: =4658+24454 -> 29112 | J33: 56.8538 | N33: 2297.09 | O33: =ROUND(G33*I33,2)+ROUND(H33*J33,2)-K33-L33-M33-N33 -> 1652830.7 | P33: =ROUND(18.75%*O33,2) -> 309905.76 | Q33: =ROUND($O33*R33,2) -> 247924.61 | R33: 0.15 | S33: =ROUND($O33*T33,2) -> 61981.15 | T33: 0.0375 | U33: =IF($F33&"/Día"=W$9,SUM($G33:$H33),"") -> 29112 | V33: =IF(U33<>"",$O33,"") -> 1652830.7 | W33: =IF($F33&"/Día"=W$9,ROUND(U33/$W$1,1),"") -> 1039.7 | X33: =IF(U33=0,0,IF($F33&"/Día"=W$9,ROUND(V33/U33,4),"")) -> 56.7749 | Y33: =IF(U33=0,0,IF($F33&"/Día"=W$9,ROUND(Z33/U33,4),"")) -> 10.6453 | Z33: =IF(U33<>"",$P33,"") -> 309905.76 | AA33: =IF($F33&"/Día"=AC$9,SUM($G33:$H33),"") | AB33: =IF(AA33<>"",$O33,"") | AC33: =IF($F33&"/Día"=AC$9,ROUND(AA33/$W$1,1),"") | AD33: =IF(AA33=0,0,IF($F33&"/Día"=AC$9,ROUND(AB33/AA33,4),"")) | AE33: =IF(AA33=0,0,IF($F33&"/Día"=AC$9,ROUND(AF33/AA33,4),"")) | AF33: =IF(AA33<>"",$P33,"")
A34: - | B34: Z-6 | C34: Licencia | D34: Quincena | E34: F2 | F34: MM BTU | O34: =ROUND(G34*I34,2)+ROUND(H34*J34,2)-K34-L34-M34-N34 -> 0 | P34: =ROUND(18.75%*O34,2) -> 0 | Q34: =ROUND($O34*R34,2) -> 0 | R34: 0.15 | S34: =ROUND($O34*T34,2) -> 0 | T34: 0.0375
A35: - | B35: Ajustes meses anteriores (1) | O35: =+O211 -> -23589.88 | P35: =+P211 -> -4423.1 | Q35: =+Q211 -> -3538.48 | S35: =+S211 -> -884.62 | U35: =IF($F35&"/Día"=W$9,SUM($G35:$H35),"") | V35: =IF(U35<>"",$O35,"") | W35: =IF($F35&"/Día"=W$9,ROUND(U35/$W$1,1),"") | X35: =IF(U35=0,0,IF($F35&"/Día"=W$9,ROUND(V35/U35,4),"")) | Y35: =IF(U35=0,0,IF($F35&"/Día"=W$9,ROUND(Z35/U35,4),"")) | Z35: =IF(U35<>"",$P35,"") | AA35: =IF($F35&"/Día"=AC$9,SUM($G35:$H35),"") | AB35: =IF(AA35<>"",$O35,"") | AC35: =IF($F35&"/Día"=AC$9,ROUND(AA35/$W$1,1),"") | AD35: =IF(AA35=0,0,IF($F35&"/Día"=AC$9,ROUND(AB35/AA35,4),"")) | AE35: =IF(AA35=0,0,IF($F35&"/Día"=AC$9,ROUND(AF35/AA35,4),"")) | AF35: =IF(AA35<>"",$P35,"")
B36: Subtotal | C36: =TEXT(A$9,)&" US$" -> Piura / Tumbes US$ | O36: =SUM(O10:O35) -> 63879786 | P36: =SUM(P10:P35) -> 11977460 | Q36: =SUM(Q10:Q35) -> 9023333.4 | S36: =SUM(S10:S35) -> 2954126.4 | U36: =SUM(U10:U35) -> 961590 | V36: =SUM(V10:V35) -> 59884279 | W36: =SUM(W10:W35) -> 34342.6 | X36: =ROUND(V36/U36,4) -> 62.2763 | Y36: =ROUND(Z36/U36,4) -> 11.6768 | Z36: =SUM(Z10:Z35) -> 11228302 | AA36: =SUM(AA10:AA35) -> 1441097.1 | AB36: =SUM(AB10:AB35) -> 4019095.9 | AC36: =SUM(AC10:AC35) -> 51467.8 | AD36: =ROUND(AB36/AA36,4) -> 2.7889 | AE36: =ROUND(AF36/AA36,4) -> 0.5229 | AF36: =SUM(AF10:AF35) -> 753580.47 | AG36: =P36-Z36-AF36 -> -4423.1
C37: =TEXT(A$9,)&" S/." -> Piura / Tumbes S/. | P37: =ROUND($F$1*P36,2) -> 0 | Q37: =ROUND($F$1*Q36,2) -> 0 | S37: =ROUND($F$1*S36,2) -> 0
A38: Provincia Puerto Inca Huanuco | Q38: Puerto Inca
A39: - | B39: 31-D | C39: Licencia | D39: Quincena | E39: F2 | F39: Bls | G39: 454 | I39: 64.2445 | N39: 1087.7 | O39: =ROUND(G39*I39,2)+ROUND(H39*J39,2)-K39-L39-M39-N39 -> 28079.3 | P39: =ROUND(15%*O39,2) -> 4211.9 | Q39: =ROUND($O39*R39,2) -> 4211.9 | R39: 0.15 | U39: =IF($F39&"/Día"=W$9,SUM($G39:$H39),"") -> 454 | V39: =IF(U39<>"",$O39,"") -> 28079.3 | W39: =IF($F39&"/Día"=W$9,ROUND(U39/$W$1,1),"") -> 16.2 | X39: =IF(U39=0,0,IF($F39&"/Día"=W$9,ROUND(V39/U39,4),"")) -> 61.8487 | Y39: =IF(U39=0,0,IF($F39&"/Día"=W$9,ROUND(Z39/U39,4),"")) -> 9.2773 | Z39: =IF(U39<>"",$P39,"") -> 4211.9 | AA39: =IF($F39&"/Día"=AC$9,SUM($G39:$H39),"") | AB39: =IF(AA39<>"",$O39,"") | AC39: =IF($F39&"/Día"=AC$9,ROUND(AA39/$W$1,1),"") | AD39: =IF(AA39=0,0,IF($F39&"/Día"=AC$9,ROUND(AB39/AA39,4),"")) | AE39: =IF(AA39=0,0,IF($F39&"/Día"=AC$9,ROUND(AF39/AA39,4),"")) | AF39: =IF(AA39<>"",$P39,"")
A40: - | B40: 131 | C40: Licencia | D40: Quincena | E40: F2 | F40: Bls | G40: 41216 | H40: 37648 | I40: 60.8419 | J40: 61.4912 | N40: 9234.9 | O40: =ROUND(G40*I40,2)+ROUND(H40*J40,2)-K40-L40-M40-N40 -> 4813445.5 | P40: =ROUND(15%*O40,2) -> 722016.83 | Q40: =ROUND($O40*R40,2) -> 722016.83 | R40: 0.15 | U40: =IF($F40&"/Día"=W$9,SUM($G40:$H40),"") -> 78864 | V40: =IF(U40<>"",$O40,"") -> 4813445.5 | W40: =IF($F40&"/Día"=W$9,ROUND(U40/$W$1,1),"") -> 2816.6 | X40: =IF(U40=0,0,IF($F40&"/Día"=W$9,ROUND(V40/U40,4),"")) -> 61.0348 | Y40: =IF(U40=0,0,IF($F40&"/Día"=W$9,ROUND(Z40/U40,4),"")) -> 9.1552 | Z40: =IF(U40<>"",$P40,"") -> 722016.83 | AA40: =IF($F40&"/Día"=AC$9,SUM($G40:$H40),"") | AB40: =IF(AA40<>"",$O40,"") | AC40: =IF($F40&"/Día"=AC$9,ROUND(AA40/$W$1,1),"") | AD40: =IF(AA40=0,0,IF($F40&"/Día"=AC$9,ROUND(AB40/AA40,4),"")) | AE40: =IF(AA40=0,0,IF($F40&"/Día"=AC$9,ROUND(AF40/AA40,4),"")) | AF40: =IF(AA40<>"",$P40,"")
A41: - | B41: Ajustes meses anteriores (2) | O41: =+O214 -> 0 | P41: =+P214 -> -166.87 | Q41: =+Q214 -> -166.87 | U41: =IF($F41&"/Día"=W$9,SUM($G41:$H41),"") | V41: =IF(U41<>"",$O41,"") | W41: =IF($F41&"/Día"=W$9,ROUND(U41/$W$1,1),"") | X41: =IF(U41=0,0,IF($F41&"/Día"=W$9,ROUND(V41/U41,4),"")) | Y41: =IF(U41=0,0,IF($F41&"/Día"=W$9,ROUND(Z41/U41,4),"")) | Z41: =IF(U41<>"",$P41,"") | AA41: =IF($F41&"/Día"=AC$9,SUM($G41:$H41),"") | AB41: =IF(AA41<>"",$O41,"") | AC41: =IF($F41&"/Día"=AC$9,ROUND(AA41/$W$1,1),"") | AD41: =IF(AA41=0,0,IF($F41&"/Día"=AC$9,ROUND(AB41/AA41,4),"")) | AE41: =IF(AA41=0,0,IF($F41&"/Día"=AC$9,ROUND(AF41/AA41,4),"")) | AF41: =IF(AA41<>"",$P41,"")
B42: Subtotal | C42: =TEXT(A$38,)&" US$" -> Provincia Puerto Inca Huanuco US$ | O42: =SUM(O39:O41) -> 4841524.8 | P42: =SUM(P39:P41) -> 726061.86 | Q42: =SUM(Q39:Q41) -> 726061.86 | S42: =SUM(S39:S41) -> 0 | U42: =SUM(U39:U41) -> 79318 | V42: =SUM(V39:V41) -> 4841524.8 | W42: =SUM(W39:W41) -> 2832.8 | X42: =ROUND(V42/U42,4) -> 61.0394 | Y42: =ROUND(Z42/U42,4) -> 9.1559 | Z42: =SUM(Z39:Z41) -> 726228.73 | AA42: =SUM(AA39:AA41) -> 0 | AB42: =SUM(AB39:AB41) -> 0 | AC42: =SUM(AC39:AC41) -> 0 | AD42: =IF(AA42=0,0,ROUND(AB42/AA42,4)) -> 0 | AE42: =IF(AA42=0,0,ROUND(AF42/AA42,4)) -> 0 | AF42: =SUM(AF39:AF41) -> 0 | AG42: =P42-Z42-AF42 -> -166.87
C43: =TEXT(A$38,)&" S/." -> Provincia Puerto Inca Huanuco S/. | P43: =ROUND($F$1*P42,2) -> 0 | Q43: =ROUND($F$1*Q42,2) -> 0 | S43: =ROUND($F$1*S42,2) -> 0
A44: Loreto / Ucayali | Q44: Loreto | S44: Ucayali
A45: - | B45: 31-E | C45: Licencia | D45: Mes | E45: F2 | F45: Bls | N45: 502.28 | O45: =ROUND(G45*I45,2)+ROUND(H45*J45,2)-K45-L45-M45-N45 -> -502.28 | P45: =ROUND(18.75%*O45,2) -> -94.18 | Q45: =ROUND($O45*R45,2) -> -75.34 | R45: 0.15 | S45: =ROUND($O45*T45,2) -> -18.84 | T45: 0.0375 | U45: =IF($F45&"/Día"=W$9,SUM($G45:$H45),"") -> 0 | V45: =IF(U45<>"",$O45,"") -> -502.28 | W45: =IF($F45&"/Día"=W$9,ROUND(U45/$W$1,1),"") -> 0 | X45: =IF(U45=0,0,IF($F45&"/Día"=W$9,ROUND(V45/U45,4),"")) -> 0 | Y45: =IF(U45=0,0,IF($F45&"/Día"=W$9,ROUND(Z45/U45,4),"")) -> 0 | Z45: =IF(U45<>"",$P45,"") -> -94.18 | AA45: =IF($F45&"/Día"=AC$9,SUM($G45:$H45),"") | AB45: =IF(AA45<>"",$O45,"") | AC45: =IF($F45&"/Día"=AC$9,ROUND(AA45/$W$1,1),"") | AD45: =IF(AA45=0,0,IF($F45&"/Día"=AC$9,ROUND(AB45/AA45,4),"")) | AE45: =IF(AA45=0,0,IF($F45&"/Día"=AC$9,ROUND(AF45/AA45,4),"")) | AF45: =IF(AA45<>"",$P45,"")
A46: - | B46: 192 | C46: Servicios | D46: Mes | E46: F1 | F46: Bls | H46: 223464 | J46: 48.7722 | N46: 10390.98 | O46: =ROUND(G46*I46,2)+ROUND(H46*J46,2)-K46-L46-M46-N46 -> 10888440 | P46: =ROUND(18.75%*O46,2) -> 2041582.5 | Q46: =ROUND($O46*R46,2) -> 1633266 | R46: 0.15 | S46: =ROUND($O46*T46,2) -> 408316.5 | T46: 0.0375 | U46: =IF($F46&"/Día"=W$9,SUM($G46:$H46),"") -> 223464 | V46: =IF(U46<>"",$O46,"") -> 10888440 | W46: =IF($F46&"/Día"=W$9,ROUND(U46/$W$1,1),"") -> 7980.9 | X46: =IF(U46=0,0,IF($F46&"/Día"=W$9,ROUND(V46/U46,4),"")) -> 48.7257 | Y46: =IF(U46=0,0,IF($F46&"/Día"=W$9,ROUND(Z46/U46,4),"")) -> 9.1361 | Z46: =IF(U46<>"",$P46,"") -> 2041582.5 | AA46: =IF($F46&"/Día"=AC$9,SUM($G46:$H46),"") | AB46: =IF(AA46<>"",$O46,"") | AC46: =IF($F46&"/Día"=AC$9,ROUND(AA46/$W$1,1),"") | AD46: =IF(AA46=0,0,IF($F46&"/Día"=AC$9,ROUND(AB46/AA46,4),"")) | AE46: =IF(AA46=0,0,IF($F46&"/Día"=AC$9,ROUND(AF46/AA46,4),"")) | AF46: =IF(AA46<>"",$P46,"")
A47: - | B47: 8 | C47: Licencia | D47: Quincena | E47: F2 | F47: Bls | G47: 62584 | H47: 67041 | I47: 48.6986 | J47: 48.7839 | N47: 12372.89 | O47: =ROUND(G47*I47,2)+ROUND(H47*J47,2)-K47-L47-M47-N47 -> 6305901.7 | P47: =ROUND(18.75%*O47,2) -> 1182356.6 | Q47: =ROUND($O47*R47,2) -> 945885.26 | R47: 0.15 | S47: =ROUND($O47*T47,2) -> 236471.31 | T47: 0.0375 | U47: =IF($F47&"/Día"=W$9,SUM($G47:$H47),"") -> 129625 | V47: =IF(U47<>"",$O47,"") -> 6305901.7 | W47: =IF($F47&"/Día"=W$9,ROUND(U47/$W$1,1),"") -> 4629.5 | X47: =IF(U47=0,0,IF($F47&"/Día"=W$9,ROUND(V47/U47,4),"")) -> 48.6473 | Y47: =IF(U47=0,0,IF($F47&"/Día"=W$9,ROUND(Z47/U47,4),"")) -> 9.1214 | Z47: =IF(U47<>"",$P47,"") -> 1182356.6 | AA47: =IF($F47&"/Día"=AC$9,SUM($G47:$H47),"") | AB47: =IF(AA47<>"",$O47,"") | AC47: =IF($F47&"/Día"=AC$9,ROUND(AA47/$W$1,1),"") | AD47: =IF(AA47=0,0,IF($F47&"/Día"=AC$9,ROUND(AB47/AA47,4),"")) | AE47: =IF(AA47=0,0,IF($F47&"/Día"=AC$9,ROUND(AF47/AA47,4),"")) | AF47: =IF(AA47<>"",$P47,"")
A48: - | B48: 31-B | C48: Licencia | D48: Quincena | E48: F2 | F48: Bls | N48: 642.46 | O48: =ROUND(G48*I48,2)+ROUND(H48*J48,2)-K48-L48-M48-N48 -> -642.46 | P48: =ROUND(18.75%*O48,2) -> -120.46 | Q48: =ROUND($O48*R48,2) -> -96.37 | R48: 0.15 | S48: =ROUND($O48*T48,2) -> -24.09 | T48: 0.0375 | U48: =IF($F48&"/Día"=W$9,SUM($G48:$H48),"") -> 0 | V48: =IF(U48<>"",$O48,"") -> -642.46 | W48: =IF($F48&"/Día"=W$9,ROUND(U48/$W$1,1),"") -> 0 | X48: =IF(U48=0,0,IF($F48&"/Día"=W$9,ROUND(V48/U48,4),"")) -> 0 | Y48: =IF(U48=0,0,IF($F48&"/Día"=W$9,ROUND(Z48/U48,4),"")) -> 0 | Z48: =IF(U48<>"",$P48,"") -> -120.46 | AA48: =IF($F48&"/Día"=AC$9,SUM($G48:$H48),"") | AB48: =IF(AA48<>"",$O48,"") | AC48: =IF($F48&"/Día"=AC$9,ROUND(AA48/$W$1,1),"") | AD48: =IF(AA48=0,0,IF($F48&"/Día"=AC$9,ROUND(AB48/AA48,4),"")) | AE48: =IF(AA48=0,0,IF($F48&"/Día"=AC$9,ROUND(AF48/AA48,4),"")) | AF48: =IF(AA48<>"",$P48,"")
A49: - | B49: 31-C GAS | C49: Licencia | D49: Quincena | E49: F2 | F49: MM BTU | G49: 385285.92 | H49: 173838.08 | I49: 3.7415 | J49: 3.7417 | N49: 1157.93 | O49: =ROUND(G49*I49,2)+ROUND(H49*J49,2)-K49-L49-M49-N49 -> 2090839.3 | P49: =ROUND(18.75%*O49,2) -> 392032.37 | Q49: =ROUND($O49*R49,2) -> 78406.47 | R49: 0.0375 | S49: =ROUND($O49*T49,2) -> 313625.89 | T49: 0.15 | U49: =IF($F49&"/Día"=W$9,SUM($G49:$H49),"") | V49: =IF(U49<>"",$O49,"") | W49: =IF($F49&"/Día"=W$9,ROUND(U49/$W$1,1),"") | X49: =IF(U49=0,0,IF($F49&"/Día"=W$9,ROUND(V49/U49,4),"")) | Y49: =IF(U49=0,0,IF($F49&"/Día"=W$9,ROUND(Z49/U49,4),"")) | Z49: =IF(U49<>"",$P49,"") | AA49: =IF($F49&"/Día"=AC$9,SUM($G49:$H49),"") -> 559124 | AB49: =IF(AA49<>"",$O49,"") -> 2090839.3 | AC49: =IF($F49&"/Día"=AC$9,ROUND(AA49/$W$1,1),"") -> 19968.7 | AD49: =IF(AA49=0,0,IF($F49&"/Día"=AC$9,ROUND(AB49/AA49,4),"")) -> 3.7395 | AE49: =IF(AA49=0,0,IF($F49&"/Día"=AC$9,ROUND(AF49/AA49,4),"")) -> 0.7012 | AF49: =IF(AA49<>"",$P49,"") -> 392032.37
A50: - | B50: 31-C LGN (*) | C50: Licencia | D50: Quincena | E50: F3 | F50: Bls | G50: 18828 | H50: 17369 | I50: 54.4709 | J50: 54.3539 | N50: 5240.42 | O50: =ROUND(G50*I50,2)+ROUND(H50*J50,2)-K50-L50-M50-N50 -> 1964410.6 | P50: =ROUND(18.75%*O50,2) -> 368326.98 | Q50: =ROUND($O50*R50,2) -> 73665.4 | R50: 0.0375 | S50: =ROUND($O50*T50,2) -> 294661.59 | T50: 0.15 | U50: =IF($F50&"/Día"=W$9,SUM($G50:$H50),"") -> 36197 | V50: =IF(U50<>"",$O50,"") -> 1964410.6 | W50: =IF($F50&"/Día"=W$9,ROUND(U50/$W$1,1),"") -> 1292.8 | X50: =IF(U50=0,0,IF($F50&"/Día"=W$9,ROUND(V50/U50,4),"")) -> 54.27 | Y50: =IF(U50=0,0,IF($F50&"/Día"=W$9,ROUND(Z50/U50,4),"")) -> 10.1756 | Z50: =IF(U50<>"",$P50,"") -> 368326.98 | AA50: =IF($F50&"/Día"=AC$9,SUM($G50:$H50),"") | AB50: =IF(AA50<>"",$O50,"") | AC50: =IF($F50&"/Día"=AC$9,ROUND(AA50/$W$1,1),"") | AD50: =IF(AA50=0,0,IF($F50&"/Día"=AC$9,ROUND(AB50/AA50,4),"")) | AE50: =IF(AA50=0,0,IF($F50&"/Día"=AC$9,ROUND(AF50/AA50,4),"")) | AF50: =IF(AA50<>"",$P50,"")
A51: - | B51: 31-C COND | C51: Licencia | D51: Quincena | E51: F2 | F51: Bls | O51: =ROUND(G51*I51,2)+ROUND(H51*J51,2)-K51-L51-M51-N51 -> 0 | P51: =ROUND(18.75%*O51,2) -> 0 | Q51: =ROUND($O51*R51,2) -> 0 | R51: 0.0375 | S51: =ROUND($O51*T51,2) -> 0 | T51: 0.15 | U51: =IF($F51&"/Día"=W$9,SUM($G51:$H51),"") -> 0 | V51: =IF(U51<>"",$O51,"") -> 0 | W51: =IF($F51&"/Día"=W$9,ROUND(U51/$W$1,1),"") -> 0 | X51: =IF(U51=0,0,IF($F51&"/Día"=W$9,ROUND(V51/U51,4),"")) -> 0 | Y51: =IF(U51=0,0,IF($F51&"/Día"=W$9,ROUND(Z51/U51,4),"")) -> 0 | Z51: =IF(U51<>"",$P51,"") -> 0 | AA51: =IF($F51&"/Día"=AC$9,SUM($G51:$H51),"") | AB51: =IF(AA51<>"",$O51,"") | AC51: =IF($F51&"/Día"=AC$9,ROUND(AA51/$W$1,1),"") | AD51: =IF(AA51=0,0,IF($F51&"/Día"=AC$9,ROUND(AB51/AA51,4),"")) | AE51: =IF(AA51=0,0,IF($F51&"/Día"=AC$9,ROUND(AF51/AA51,4),"")) | AF51: =IF(AA51<>"",$P51,"")
A52: - | B52: 102 | C52: Licencia | D52: Quincena | E52: F2 | F52: Bls | O52: =ROUND(G52*I52,2)+ROUND(H52*J52,2)-K52-L52-M52-N52 -> 0 | P52: =ROUND(18.75%*O52,2) -> 0 | Q52: =P52-S52 -> 0 | R52: 0.15 | S52: =ROUND($O52*T52,2) -> 0 | T52: 0.0375 | U52: =IF($F52&"/Día"=W$9,SUM($G52:$H52),"") -> 0 | V52: =IF(U52<>"",$O52,"") -> 0 | W52: =IF($F52&"/Día"=W$9,ROUND(U52/$W$1,1),"") -> 0 | X52: =IF(U52=0,0,IF($F52&"/Día"=W$9,ROUND(V52/U52,4),"")) -> 0 | Y52: =IF(U52=0,0,IF($F52&"/Día"=W$9,ROUND(Z52/U52,4),"")) -> 0 | Z52: =IF(U52<>"",$P52,"") -> 0 | AA52: =IF($F52&"/Día"=AC$9,SUM($G52:$H52),"") | AB52: =IF(AA52<>"",$O52,"") | AC52: =IF($F52&"/Día"=AC$9,ROUND(AA52/$W$1,1),"") | AD52: =IF(AA52=0,0,IF($F52&"/Día"=AC$9,ROUND(AB52/AA52,4),"")) | AE52: =IF(AA52=0,0,IF($F52&"/Día"=AC$9,ROUND(AF52/AA52,4),"")) | AF52: =IF(AA52<>"",$P52,"")
A53: - | B53: 95 | C53: Licencia | D53: Quincena | E53: F2 | F53: Bls | O53: =ROUND(G53*I53,2)+ROUND(H53*J53,2)-K53-L53-M53-N53 -> 0 | P53: =ROUND(18.75%*O53,2) -> 0 | Q53: =P53-S53 -> 0 | R53: 0.15 | S53: =ROUND($O53*T53,2) -> 0 | T53: 0.0375 | U53: =IF($F53&"/Día"=W$9,SUM($G53:$H53),"") -> 0 | V53: =IF(U53<>"",$O53,"") -> 0 | W53: =IF($F53&"/Día"=W$9,ROUND(U53/$W$1,1),"") -> 0 | X53: =IF(U53=0,0,IF($F53&"/Día"=W$9,ROUND(V53/U53,4),"")) -> 0 | Y53: =IF(U53=0,0,IF($F53&"/Día"=W$9,ROUND(Z53/U53,4),"")) -> 0 | Z53: =IF(U53<>"",$P53,"") -> 0 | AA53: =IF($F53&"/Día"=AC$9,SUM($G53:$H53),"") | AB53: =IF(AA53<>"",$O53,"") | AC53: =IF($F53&"/Día"=AC$9,ROUND(AA53/$W$1,1),"") | AD53: =IF(AA53=0,0,IF($F53&"/Día"=AC$9,ROUND(AB53/AA53,4),"")) | AE53: =IF(AA53=0,0,IF($F53&"/Día"=AC$9,ROUND(AF53/AA53,4),"")) | AF53: =IF(AA53<>"",$P53,"")
A54: - | B54: 67 | C54: Licencia | D54: Quincena | E54: F2 | F54: Bls | O54: =ROUND(G54*I54,2)+ROUND(H54*J54,2)-K54-L54-M54-N54 -> 0 | P54: =ROUND(18.75%*O54,2) -> 0 | Q54: =P54-S54 -> 0 | R54: 0.15 | S54: =ROUND($O54*T54,2) -> 0 | T54: 0.0375 | U54: =IF($F54&"/Día"=W$9,SUM($G54:$H54),"") -> 0 | V54: =IF(U54<>"",$O54,"") -> 0 | W54: =IF($F54&"/Día"=W$9,ROUND(U54/$W$1,1),"") -> 0 | X54: =IF(U54=0,0,IF($F54&"/Día"=W$9,ROUND(V54/U54,4),"")) -> 0 | Y54: =IF(U54=0,0,IF($F54&"/Día"=W$9,ROUND(Z54/U54,4),"")) -> 0 | Z54: =IF(U54<>"",$P54,"") -> 0 | AA54: =IF($F54&"/Día"=AC$9,SUM($G54:$H54),"") | AB54: =IF(AA54<>"",$O54,"") | AC54: =IF($F54&"/Día"=AC$9,ROUND(AA54/$W$1,1),"") | AD54: =IF(AA54=0,0,IF($F54&"/Día"=AC$9,ROUND(AB54/AA54,4),"")) | AE54: =IF(AA54=0,0,IF($F54&"/Día"=AC$9,ROUND(AF54/AA54,4),"")) | AF54: =IF(AA54<>"",$P54,"")
A55: - | B55: Ajustes meses anteriores (3) | O55: =+O220 -> -1476468.5 | P55: =+P220 -> -277057.39 | Q55: =+Q220 -> -221645.92 | S55: =+S220 -> -55411.46 | U55: =IF($F55&"/Día"=W$9,SUM($G55:$H55),"") | V55: =IF(U55<>"",$O55,"") | W55: =IF($F55&"/Día"=W$9,ROUND(U55/$W$1,1),"") | X55: =IF(U55=0,0,IF($F55&"/Día"=W$9,ROUND(V55/U55,4),"")) | Y55: =IF(U55=0,0,IF($F55&"/Día"=W$9,ROUND(Z55/U55,4),"")) | Z55: =IF(U55<>"",$P55,"") | AA55: =IF($F55&"/Día"=AC$9,SUM($G55:$H55),"") | AB55: =IF(AA55<>"",$O55,"") | AC55: =IF($F55&"/Día"=AC$9,ROUND(AA55/$W$1,1),"") | AD55: =IF(AA55=0,0,IF($F55&"/Día"=AC$9,ROUND(AB55/AA55,4),"")) | AE55: =IF(AA55=0,0,IF($F55&"/Día"=AC$9,ROUND(AF55/AA55,4),"")) | AF55: =IF(AA55<>"",$P55,"")
B56: Subtotal | C56: =TEXT(A$44,)&" US$" -> Loreto / Ucayali US$ | O56: =SUM(O45:O55) -> 19771978 | P56: =SUM(P45:P55) -> 3707026.4 | Q56: =SUM(Q45:Q55) -> 2509405.5 | S56: =SUM(S45:S55) -> 1197620.9 | U56: =SUM(U45:U55) -> 389286 | V56: =SUM(V45:V55) -> 19157607 | W56: =SUM(W45:W55) -> 13903.2 | X56: =ROUND(V56/U56,4) -> 49.2122 | Y56: =ROUND(Z56/U56,4) -> 9.2273 | Z56: =SUM(Z45:Z55) -> 3592051.4 | AA56: =SUM(AA45:AA55) -> 559124 | AB56: =SUM(AB45:AB55) -> 2090839.3 | AC56: =SUM(AC45:AC55) -> 19968.7 | AD56: =ROUND(AB56/AA56,4) -> 3.7395 | AE56: =ROUND(AF56/AA56,4) -> 0.7012 | AF56: =SUM(AF45:AF55) -> 392032.37 | AG56: =P56-Z56-AF56 -> -277057.39
C57: =TEXT(A$44,)&" S/." -> Loreto / Ucayali S/. | P57: =ROUND($F$1*P56,2) -> 0 | Q57: =ROUND($F$1*Q56,2) -> 0 | S57: =ROUND($F$1*S56,2) -> 0
A58: Cusco | P58: V. Regalías | Q58: Cusco
A59: - | B59: 88 LGN | C59: Licencia | D59: Quincena | E59: F4 | F59: Bls | G59: 154527 | H59: 648045 | I59: 39.4053 | J59: 40.8881 | O59: =G59*I59+H59*J59 -> 32586512 | P59: =ROUND(37.24%*(G59*I59+H59*J59),2) -> 12135217 | Q59: =ROUND(R59*P59,2) -> 6067608.5 | R59: 0.5 | U59: =IF($F59&"/Día"=W$9,SUM($G59:$H59),"") -> 802572 | V59: =IF(U59<>"",$O59,"") -> 32586512 | W59: =IF($F59&"/Día"=W$9,ROUND(U59/$W$1,1),"") -> 28663.3 | X59: =IF(U59=0,0,IF($F59&"/Día"=W$9,ROUND(V59/U59,4),"")) -> 40.6026 | Y59: =IF(U59=0,0,IF($F59&"/Día"=W$9,ROUND(Z59/U59,4),"")) -> 7.5602 | Z59: =IF(U59<>"",$Q59,"") -> 6067608.5 | AA59: =IF($F59&"/Día"=AC$9,SUM($G59:$H59),"") | AB59: =IF(AA59<>"",$O59,"") | AC59: =IF($F59&"/Día"=AC$9,ROUND(AA59/$W$1,1),"") | AD59: =IF(AA59=0,0,IF($F59&"/Día"=AC$9,ROUND(AB59/AA59,4),"")) | AE59: =IF(AA59=0,0,IF($F59&"/Día"=AC$9,ROUND(AF59/AA59,4),"")) | AF59: =IF(AA59<>"",$Q59,"")
A60: - | B60: 88 GAS | C60: Licencia | D60: Quincena | E60: F4 | F60: MM BTU | G60: 6714461.6 | H60: 6354405.1 | I60: 2.1094 | J60: 2.1094 | O60: =G60*I60+H60*J60 -> 27567467 | P60: =ROUND(37.24%*(G60*I60+H60*J60),2) -> 10266125 | Q60: =ROUND(R60*P60,2) -> 5133062.4 | R60: 0.5 | U60: =IF($F60&"/Día"=W$9,SUM($G60:$H60),"") | V60: =IF(U60<>"",$O60,"") | W60: =IF($F60&"/Día"=W$9,ROUND(U60/$W$1,1),"") | X60: =IF(U60=0,0,IF($F60&"/Día"=W$9,ROUND(V60/U60,4),"")) | Y60: =IF(U60=0,0,IF($F60&"/Día"=W$9,ROUND(Z60/U60,4),"")) | Z60: =IF(U60<>"",$Q60,"") | AA60: =IF($F60&"/Día"=AC$9,SUM($G60:$H60),"") -> 13068867 | AB60: =IF(AA60<>"",$O60,"") -> 27567467 | AC60: =IF($F60&"/Día"=AC$9,ROUND(AA60/$W$1,1),"") -> 466745.2 | AD60: =IF(AA60=0,0,IF($F60&"/Día"=AC$9,ROUND(AB60/AA60,4),"")) -> 2.1094 | AE60: =IF(AA60=0,0,IF($F60&"/Día"=AC$9,ROUND(AF60/AA60,4),"")) -> 0.3928 | AF60: =IF(AA60<>"",$Q60,"") -> 5133062.4
A61: - | B61: 88 GAS -Mlocal | C61: Licencia | D61: Quincena | E61: F4 | F61: MM BTU | G61: 5329.8662 | H61: 20568.602 | I61: 2.8783 | J61: 2.8783 | O61: =G61*I61+H61*J61 -> 74543.561 | P61: =ROUND(37.24%*O61,2) -> 27760.02 | Q61: =ROUND(R61*P61,2) -> 13880.01 | R61: 0.5 | U61: =IF($F61&"/Día"=W$9,SUM($G61:$H61),"") | V61: =IF(U61<>"",$O61,"") | W61: =IF($F61&"/Día"=W$9,ROUND(U61/$W$1,1),"") | X61: =IF(U61=0,0,IF($F61&"/Día"=W$9,ROUND(V61/U61,4),"")) | Y61: =IF(U61=0,0,IF($F61&"/Día"=W$9,ROUND(Z61/U61,4),"")) | Z61: =IF(U61<>"",$Q61,"") | AA61: =IF($F61&"/Día"=AC$9,SUM($G61:$H61),"") -> 25898.468 | AB61: =IF(AA61<>"",$O61,"") -> 74543.561 | AC61: =IF($F61&"/Día"=AC$9,ROUND(AA61/$W$1,1),"") -> 924.9 | AD61: =IF(AA61=0,0,IF($F61&"/Día"=AC$9,ROUND(AB61/AA61,4),"")) -> 2.8783 | AE61: =IF(AA61=0,0,IF($F61&"/Día"=AC$9,ROUND(AF61/AA61,4),"")) -> 0.5359 | AF61: =IF(AA61<>"",$Q61,"") -> 13880.01
A62: - | B62: 88 GAS -PM | C62: Licencia | D62: Quincena | E62: F4 | F62: MM BTU | G62: 361206.1 | H62: 865614.38 | I62: 1.747 | J62: 2.472 | O62: =G62*I62+H62*J62 -> 2770825.8 | P62: =ROUND(38%*G62*I62,2)+ROUND(38%*H62*J62,2) -> 1052913.8 | Q62: =ROUND(R62*P62,2) -> 526456.9 | R62: 0.5 | U62: =IF($F62&"/Día"=W$9,SUM($G62:$H62),"") | V62: =IF(U62<>"",$O62,"") | W62: =IF($F62&"/Día"=W$9,ROUND(U62/$W$1,1),"") | X62: =IF(U62=0,0,IF($F62&"/Día"=W$9,ROUND(V62/U62,4),"")) | Y62: =IF(U62=0,0,IF($F62&"/Día"=W$9,ROUND(Z62/U62,4),"")) | Z62: =IF(U62<>"",$Q62,"") | AA62: =IF($F62&"/Día"=AC$9,SUM($G62:$H62),"") -> 1226820.5 | AB62: =IF(AA62<>"",$O62,"") -> 2770825.8 | AC62: =IF($F62&"/Día"=AC$9,ROUND(AA62/$W$1,1),"") -> 43815 | AD62: =IF(AA62=0,0,IF($F62&"/Día"=AC$9,ROUND(AB62/AA62,4),"")) -> 2.2585 | AE62: =IF(AA62=0,0,IF($F62&"/Día"=AC$9,ROUND(AF62/AA62,4),"")) -> 0.4291 | AF62: =IF(AA62<>"",$Q62,"") -> 526456.9
A63: - | B63: 56 LGN | C63: Licencia | D63: Quincena | E63: F4 | F63: Bls | G63: 83164 | H63: 314254 | I63: 39.4063 | J63: 40.8617 | O63: =G63*I63+H63*J63 -> 16118138 | P63: =ROUND(40%*G63*I63,2)+ROUND(40%*H63*J63,2) -> 6447255.3 | Q63: =ROUND(R63*P63,2) -> 3223627.6 | R63: 0.5 | U63: =IF($F63&"/Día"=W$9,SUM($G63:$H63),"") -> 397418 | V63: =IF(U63<>"",$O63,"") -> 16118138 | W63: =IF($F63&"/Día"=W$9,ROUND(U63/$W$1,1),"") -> 14193.5 | X63: =IF(U63=0,0,IF($F63&"/Día"=W$9,ROUND(V63/U63,4),"")) -> 40.5571 | Y63: =IF(U63=0,0,IF($F63&"/Día"=W$9,ROUND(Z63/U63,4),"")) -> 8.1114 | Z63: =IF(U63<>"",$Q63,"") -> 3223627.6 | AA63: =IF($F63&"/Día"=AC$9,SUM($G63:$H63),"") | AB63: =IF(AA63<>"",$O63,"") | AC63: =IF($F63&"/Día"=AC$9,ROUND(AA63/$W$1,1),"") | AD63: =IF(AA63=0,0,IF($F63&"/Día"=AC$9,ROUND(AB63/AA63,4),"")) | AE63: =IF(AA63=0,0,IF($F63&"/Día"=AC$9,ROUND(AF63/AA63,4),"")) | AF63: =IF(AA63<>"",$Q63,"")
A64: - | B64: 56 GAS | C64: Licencia | D64: Quincena | E64: F4 | F64: MM BTU | G64: 1254262.5 | H64: 4808502.6 | I64: 1.747 | J64: 2.472 | O64: =G64*I64+H64*J64 -> 14077815 | P64: =ROUND(38%*G64*I64,2)+ROUND(38%*H64*J64,2) -> 5349569.7 | Q64: =ROUND(R64*P64,2) -> 2674784.9 | R64: 0.5 | U64: =IF($F64&"/Día"=W$9,SUM($G64:$H64),"") | V64: =IF(U64<>"",$O64,"") | W64: =IF($F64&"/Día"=W$9,ROUND(U64/$W$1,1),"") | X64: =IF(U64=0,0,IF($F64&"/Día"=W$9,ROUND(V64/U64,4),"")) | Y64: =IF(U64=0,0,IF($F64&"/Día"=W$9,ROUND(Z64/U64,4),"")) | Z64: =IF(U64<>"",$Q64,"") | AA64: =IF($F64&"/Día"=AC$9,SUM($G64:$H64),"") -> 6062765.1 | AB64: =IF(AA64<>"",$O64,"") -> 14077815 | AC64: =IF($F64&"/Día"=AC$9,ROUND(AA64/$W$1,1),"") -> 216527.3 | AD64: =IF(AA64=0,0,IF($F64&"/Día"=AC$9,ROUND(AB64/AA64,4),"")) -> 2.322 | AE64: =IF(AA64=0,0,IF($F64&"/Día"=AC$9,ROUND(AF64/AA64,4),"")) -> 0.4412 | AF64: =IF(AA64<>"",$Q64,"") -> 2674784.9
A65: - | B65: 56 GAS-Mlocal | C65: Licencia | D65: Quincena | E65: F4 | F65: MM BTU | G65: 49070.685 | H65: 185183.87 | I65: 1.8275 | J65: 1.8275 | O65: =G65*I65+H65*J65 -> 428100.2 | P65: =ROUND(37.24%*(G65*I65+H65*J65),2) -> 159424.51 | Q65: =ROUND(R65*P65,2) -> 79712.26 | R65: 0.5 | U65: =IF($F65&"/Día"=W$9,SUM($G65:$H65),"") | V65: =IF(U65<>"",$O65,"") | W65: =IF($F65&"/Día"=W$9,ROUND(U65/$W$1,1),"") | X65: =IF(U65=0,0,IF($F65&"/Día"=W$9,ROUND(V65/U65,4),"")) | Y65: =IF(U65=0,0,IF($F65&"/Día"=W$9,ROUND(Z65/U65,4),"")) | Z65: =IF(U65<>"",$Q65,"") | AA65: =IF($F65&"/Día"=AC$9,SUM($G65:$H65),"") -> 234254.55 | AB65: =IF(AA65<>"",$O65,"") -> 428100.2 | AC65: =IF($F65&"/Día"=AC$9,ROUND(AA65/$W$1,1),"") -> 8366.2 | AD65: =IF(AA65=0,0,IF($F65&"/Día"=AC$9,ROUND(AB65/AA65,4),"")) -> 1.8275 | AE65: =IF(AA65=0,0,IF($F65&"/Día"=AC$9,ROUND(AF65/AA65,4),"")) -> 0.3403 | AF65: =IF(AA65<>"",$Q65,"") -> 79712.26
A66: - | B66: 57 LGN | C66: Licencia | D66: Quincena | E66: F4 | F66: Bls | G66: 32150 | H66: 142646 | I66: 34.9534 | J66: 36.4404 | O66: =G66*I66+H66*J66 -> 6321829.1 | P66: =ROUND(G66*I66,2)*5.9%+ROUND(H66*J66,2)*6.09% -> 382864.26 | Q66: =ROUND(R66*P66,2) -> 191432.13 | R66: 0.5 | U66: =IF($F66&"/Día"=W$9,SUM($G66:$H66),"") -> 174796 | V66: =IF(U66<>"",$O66,"") -> 6321829.1 | W66: =IF($F66&"/Día"=W$9,ROUND(U66/$W$1,1),"") -> 6242.7 | X66: =IF(U66=0,0,IF($F66&"/Día"=W$9,ROUND(V66/U66,4),"")) -> 36.1669 | Y66: =IF(U66=0,0,IF($F66&"/Día"=W$9,ROUND(Z66/U66,4),"")) -> 1.0952 | Z66: =IF(U66<>"",$Q66,"") -> 191432.13 | AA66: =IF($F66&"/Día"=AC$9,SUM($G66:$H66),"") | AB66: =IF(AA66<>"",$O66,"") | AC66: =IF($F66&"/Día"=AC$9,ROUND(AA66/$W$1,1),"") | AD66: =IF(AA66=0,0,IF($F66&"/Día"=AC$9,ROUND(AB66/AA66,4),"")) | AE66: =IF(AA66=0,0,IF($F66&"/Día"=AC$9,ROUND(AF66/AA66,4),"")) | AF66: =IF(AA66<>"",$Q66,"")
A67: - | B67: 57 GAS | C67: Licencia | D67: Quincena | E67: F4 | F67: MM BTU | G67: 524216.32 | H67: 2239481.4 | I67: 2.701 | J67: 2.701 | O67: =G67*I67+H67*J67 -> 7464747.6 | P67: =ROUND(G67*I67,2)*8.81%+ROUND(H67*J67,2)*9.12% -> 676395.66 | Q67: =ROUND(R67*P67,2) -> 338197.83 | R67: 0.5 | U67: =IF($F67&"/Día"=W$9,SUM($G67:$H67),"") | V67: =IF(U67<>"",$O67,"") | W67: =IF($F67&"/Día"=W$9,ROUND(U67/$W$1,1),"") | X67: =IF(U67=0,0,IF($F67&"/Día"=W$9,ROUND(V67/U67,4),"")) | Y67: =IF(U67=0,0,IF($F67&"/Día"=W$9,ROUND(Z67/U67,4),"")) | Z67: =IF(U67<>"",$Q67,"") | AA67: =IF($F67&"/Día"=AC$9,SUM($G67:$H67),"") -> 2763697.7 | AB67: =IF(AA67<>"",$O67,"") -> 7464747.6 | AC67: =IF($F67&"/Día"=AC$9,ROUND(AA67/$W$1,1),"") -> 98703.5 | AD67: =IF(AA67=0,0,IF($F67&"/Día"=AC$9,ROUND(AB67/AA67,4),"")) -> 2.701 | AE67: =IF(AA67=0,0,IF($F67&"/Día"=AC$9,ROUND(AF67/AA67,4),"")) -> 0.1224 | AF67: =IF(AA67<>"",$Q67,"") -> 338197.83
A68: - | B68: Ajustes meses anteriores (4) | O68: =+O226 -> -299010.02 | P68: =+P226 -> 602092.67 | Q68: =+Q226 -> 301046.33 | U68: =IF($F68&"/Día"=W$9,SUM($G68:$H68),"") | V68: =IF(U68<>"",$O68,"") | W68: =IF($F68&"/Día"=W$9,ROUND(U68/$W$1,1),"") | X68: =IF(U68=0,0,IF($F68&"/Día"=W$9,ROUND(V68/U68,4),"")) | Y68: =IF(U68=0,0,IF($F68&"/Día"=W$9,ROUND(Z68/U68,4),"")) | Z68: =IF(U68<>"",$Q68,"") | AA68: =IF($F68&"/Día"=AC$9,SUM($G68:$H68),"") | AB68: =IF(AA68<>"",$O68,"") | AC68: =IF($F68&"/Día"=AC$9,ROUND(AA68/$W$1,1),"") | AD68: =IF(AA68=0,0,IF($F68&"/Día"=AC$9,ROUND(AB68/AA68,4),"")) | AE68: =IF(AA68=0,0,IF($F68&"/Día"=AC$9,ROUND(AF68/AA68,4),"")) | AF68: =IF(AA68<>"",$Q68,"")
B69: Subtotal | C69: =TEXT(A$58,)&" US$" -> Cusco US$ | G69: =SUM(G64:G65) -> 1303333.1 | H69: =SUM(H64:H65) -> 4993686.5 | O69: =SUM(O59:O68) -> 1.0711097e+08 | P69: =SUM(P59:P68) -> 37099618 | Q69: =SUM(Q59:Q68) -> 18549809 | U69: =SUM(U59:U68) -> 1374786 | V69: =SUM(V59:V68) -> 55026479 | W69: =SUM(W59:W68) -> 49099.5 | X69: =ROUND(V69/U69,4) -> 40.0255 | Y69: =ROUND(Z69/U69,4) -> 6.8976 | Z69: =SUM(Z59:Z68) -> 9482668.2 | AA69: =SUM(AA59:AA68) -> 23382303 | AB69: =SUM(AB59:AB68) -> 52383499 | AC69: =SUM(AC59:AC68) -> 835082.1 | AD69: =ROUND(AB69/AA69,4) -> 2.2403 | AE69: =ROUND(AF69/AA69,4) -> 0.3749 | AF69: =SUM(AF59:AF68) -> 8766094.3 | AG69: =Q69-Z69-AF69 -> 301046.33
C70: =TEXT(A$58,)&" S/." -> Cusco S/. | G70: =SUMPRODUCT(I64:I65,G64:G65)/SUM(G64:G65) -> 1.7500308 | H70: =SUMPRODUCT(J64:J65,H64:H65)/SUM(H64:H65) -> 2.4480996 | Q70: =Q69*F1 -> 0
A71: Total General | G71: =G69*G70 -> 2280873.2 | H71: =H69*H70 -> 12225042 | I71: =H71+G71 -> 14505915 | J71: =O64+O65 -> 14505915 | K71: =I71-J71 -> 0 | N71: =SUM(N10:N67) -> 78038.71 | O71: =O36+O42+O56+O69 -> 1.9560426e+08 | P71: =+Q69+P56+P42+P36 -> 34960357 | Q71: =Q70+P57+P43+P37 -> 0 | U71: =U36+U42+U56+U69 -> 2804980 | V71: =V36+V42+V56+V69 -> 1.3890989e+08 | W71: =W36+W42+W56+W69 -> 100178.1 | X71: =ROUND(V71/U71,4) -> 49.5226 | Y71: =ROUND(Z71/U71,4) -> 8.9231 | Z71: =Z36+Z42+Z56+Z69 -> 25029251 | AA71: =AA36+AA42+AA56+AA69 -> 25382524 | AB71: =AB36+AB42+AB56+AB69 -> 58493435 | AC71: =AC36+AC42+AC56+AC69 -> 906518.6 | AD71: =ROUND(AB71/AA71,4) -> 2.3045 | AE71: =ROUND(AF71/AA71,4) -> 0.3905 | AF71: =AF36+AF42+AF56+AF69 -> 9911707.1 | AG71: =P71-Z71-AF71 -> 19398.97
A73: (*) | B73: Determinación de Canasta de los Líquidos de Gas Natural (VLGNF) | H73: = ( VC * %P + (PB - TF - TT) * (1 - %P)) | O73: =63427404.04+0.44+105176870.48-0.83+2529.92-1581.05+0.01-78038.71+28876141.03-1801351.67+2283.22 -> 1.9560426e+08 | U73: Regalía 1Q | V73: =6329295.84-V79 -> 6356192.6 | W73: =+P36 -> 11977460 | X73: Piura / Tumbes
B74: Simbolo | C74: Descripcion | E74: 1ra. Q | F74: 2da. Q | H74: 1ra. Q | U74: Regalía 2Q | V74: =5078159.27-V82 -> 4644050.7 | W74: =+P56 -> 3707026.4 | X74: Loreto / Ucayali
B75: VC | C75: Canasta de Petróleo | H75: ="= ("&TEXT(E75,"0.0000")&" * "&TEXT(E78,"0.00%")&" + ("&TEXT(E76,"0.0000")&" - "&TEXT(E77,"0.0000")&" - "&TEXT(E80,"0.0000")&") * (1 - "&TEXT(E78,"0.00%")&"))" -> = (0.0000 * 0.00% + (0.0000 - 0.0000 - 0.0000) * (1 - 0.00%)) | O75: =+O73-O71 -> -0.0084449053 | U75: Servicios | V75: 5410304.7 | W75: =+P42 -> 726061.86 | X75: Huanuco
B76: PB | C76: Precio del GLP | H76: =((85.98%*E75+4.4221)*E78+(E76-E77-E80)*(1-E78)) -> 0 | V76: =SUM(V73:V75) -> 16410548 | W76: =SUM(W73:W75) -> 16410548 | X76: =+V76-W76 -> 0.079999998
B77: TF | C77: Tarifa de Fraccionam. | U77: Lote 56 1Q | V77: 1088541.6
B78: %P | C78: % Contenido Pentanos | H78: 2da. Q | O78: Maple | P78: 2283.22 | U78: Lote 88 1Q | V78: 4317183.7 | AB78: 281480.49
B79: QLGNF | C79: Volumen de LGN | H79: ="= ("&TEXT(F75,"0.0000")&" * "&TEXT(F78,"0.00%")&" + ("&TEXT(F76,"0.0000")&" - "&TEXT(F77,"0.0000")&" - "&TEXT(F80,"0.0000")&") * (1 - "&TEXT(F78,"0.00%")&"))" -> = (0.0000 * 0.00% + (0.0000 - 0.0000 - 0.0000) * (1 - 0.00%)) | U79: Lote 57 1Q | V79: -26896.8
B80: TT | C80: Tarifa de Transporte | H80: =((85.98%*F75+4.4221)*F78+(F76-F77-F80)*(1-F78)) -> 0 | U80: Lote 56 2Q | V80: 4889662.5
U81: Lote 88 2Q | V81: 7847209.4
A82: (*) Se incluye ND 001-90 por US$ 30,498.50 facturado el 01.02.18 a Enap por la exportacion de crudo Loreto de enero, del Lote 192. En febrero no considerar la ND | U82: Lote 57 2Q | V82: 434108.54
A83: ="AJUSTES PARA "&UPPER(TEXT(E1,"MMMMMMM YYYY")) -> AJUSTES PARA FEBRERO 2018 | V83: =SUM(V77:V82) -> 18549809 | W83: =Q69 -> 18549809 | X83: =V83-W83 -> 0.080000002
A85: (4) | B85: Ajuste correspondiente de Enero 2018 (Reporte de Regalía 1ra. Quincena de Febrero 2018) - Liq. 1193 | V85: =+V73+V77+V78+V79 -> 11735021
A86: Cusco | D86: Período | E86: Fórmula | F86: Unidades | G86: 1ra. Q | H86: 2da. Q / Mes | I86: 1ra. Q | J86: 2da. Q / Mes | K86: Flete Marítimo | L86: Comercialización | M86: Oleoducto | N86: Fiscalización | O86: Valor Producción | P86: V. Regalías | Q86: Cuzco | V86: =+V74+V80+V81+V82 -> 17815031
A87: - | B87: 56 GAS-Mlocal | C87: Licencia | D87: Calculo Efectuado | F87: MM BTU | G87: 191112.54 | H87: 282162.15 | I87: 1.8266 | J87: 1.8266 | O87: =G87*I87+H87*J87 -> 864483.55 | P87: =ROUND(37.24%*(G87*I87+H87*J87),2) -> 321933.67 | Q87: =ROUND(R87*P87,2) -> 160966.84 | R87: 0.5 | V87: =+V75 -> 5410304.7
A88: - | B88: =B87 -> 56 GAS-Mlocal | C88: Licencia | D88: Modificación | F88: =F87 -> MM BTU | G88: =+G87 -> 191112.54 | H88: =+H87 -> 282162.15 | I88: 1.8275 | J88: 1.8275 | O88: =G88*I88+H88*J88 -> 864909.5 | P88: =ROUND(37.24%*(G88*I88+H88*J88),2) -> 322092.3 | Q88: =ROUND(R88*P88,2) -> 161046.15 | R88: 0.5 | V88: =SUM(V85:V87) -> 34960357 | X88: =+V88-P71 -> 0.16
B89: Ajuste | G89: =G88-G87 -> 0 | H89: =H88-H87 -> 0 | I89: =I88-I87 -> 0.0009 | J89: =J88-J87 -> 0.0009 | K89: =K88-K87 -> 0 | L89: =L88-L87 -> 0 | M89: =M88-M87 -> 0 | N89: =N88-N87 -> 0 | ... Q89: =Q88-Q87 -> 79.31 | S89: ok
B91: Ajuste correspondiente de Enero 2018 (Reporte de Regalía 1ra. Quincena de Febrero 2018) - Liq. 1193
A92: Cusco | D92: Período | E92: Fórmula | F92: Unidades | G92: 1ra. Q | H92: 2da. Q / Mes | I92: 1ra. Q | J92: 2da. Q / Mes | K92: Flete Marítimo | L92: Comercialización | M92: Oleoducto | N92: Fiscalización | O92: Valor Producción | P92: V. Regalías | Q92: Cuzco
A93: - | B93: 57 GAS | C93: Licencia | D93: Quincena | E93: F4 | F93: MM BTU | G93: 2377392.5 | H93: 3455909.8 | I93: 3.118 | J93: 3.118 | O93: =G93*I93+H93*J93 -> 18188237 | P93: =ROUND(G93*I93,2)*9.42%+ROUND(H93*J93,2)*9.89% -> 1763976.9 | Q93: =ROUND(R93*P93,2) -> 881988.44 | R93: 0.5
A94: - | B94: =B93 -> 57 GAS | C94: Licencia | D94: Modificación | F94: =F93 -> MM BTU | G94: =+G93 -> 2377392.5 | H94: =+H93 -> 3455909.8 | I94: 2.701 | J94: 2.701 | O94: =G94*I94+H94*J94 -> 15755750 | P94: =ROUND(G94*I94,2)*9.42%+ROUND(H94*J94,2)*9.89% -> 1528063.4 | Q94: =ROUND(R94*P94,2) -> 764031.68 | R94: 0.5
B95: Ajuste | G95: =G94-G93 -> 0 | H95: =H94-H93 -> 0 | I95: =I94-I93 -> -0.417 | J95: =J94-J93 -> -0.417 | K95: =K94-K93 -> 0 | L95: =L94-L93 -> 0 | M95: =M94-M93 -> 0 | N95: =N94-N93 -> 0 | ... Q95: =Q94-Q93 -> -117956.76 | S95: ok
B97: Ajuste correspondiente de Diciembre 2017 (Reporte de Regalía 1ra. Quincena de Febrero 2018) - Liq. 1193
A98: Cusco | D98: Período | E98: Fórmula | F98: Unidades | G98: 1ra. Q | H98: 2da. Q / Mes | I98: 1ra. Q | J98: 2da. Q / Mes | K98: Flete Marítimo | L98: Comercialización | M98: Oleoducto | N98: Fiscalización | O98: Valor Producción | P98: V. Regalías | Q98: Cuzco
A99: - | B99: 88 GAS | C99: Licencia | D99: Quincena | E99: F4 | F99: MM BTU | G99: 10073303 | H99: 9746635 | I99: 1.9641 | J99: 1.9641 | O99: =G99*I99+H99*J99 -> 38928340 | P99: =ROUND(37.24%*(G99*I99+H99*J99),2) -> 14496914 | Q99: =ROUND(R99*P99,2) -> 7248456.8 | R99: 0.5 | X99: 5975668.6 | Y99: 4298512.9
A100: - | B100: =B99 -> 88 GAS | C100: Licencia | D100: Modificación | F100: =F99 -> MM BTU | G100: =+G99 -> 10073303 | H100: =+H99 -> 9746635 | I100: 1.9588 | J100: 1.9588 | O100: =G100*I100+H100*J100 -> 38823294 | P100: =ROUND(37.24%*(G100*I100+H100*J100),2) -> 14457795 | Q100: =ROUND(R100*P100,2) -> 7228897.3 | R100: 0.5 | X100: 380524.01 | Y100: 345537.84
B101: Ajuste | G101: =G100-G99 -> 0 | H101: =H100-H99 -> 0 | I101: =I100-I99 -> -0.0053 | J101: =J100-J99 -> -0.0053 | K101: =K100-K99 -> 0 | L101: =L100-L99 -> 0 | M101: =M100-M99 -> 0 | N101: =N100-N99 -> 0 | ... Q101: =Q100-Q99 -> -19559.5 | S101: ok | X101: =SUM(X99:X100) -> 6356192.6 | Y101: =SUM(Y99:Y100) -> 4644050.7
W102: 5975668.6
B103: Ajuste correspondiente de Enero 2018 (Reporte de Regalía 1ra. Quincena de Febrero 2018) - Liq. 1193 | W103: 380524.01
A104: Cusco | D104: Período | E104: Fórmula | F104: Unidades | G104: 1ra. Q | H104: 2da. Q / Mes | I104: 1ra. Q | J104: 2da. Q / Mes | K104: Flete Marítimo | L104: Comercialización | M104: Oleoducto | N104: Fiscalización | O104: Valor Producción | P104: V. Regalías | Q104: Cuzco | W104: =SUM(W102:W103) -> 6356192.6
A105: - | B105: 88 GAS | C105: Licencia | D105: Quincena | E105: F4 | F105: MM BTU | G105: 7816183.7 | H105: 8555912.2 | I105: 1.9641 | J105: 1.9641 | O105: =G105*I105+H105*J105 -> 32156434 | P105: =ROUND(37.24%*(G105*I105+H105*J105),2) -> 11975056 | Q105: =ROUND(R105*P105,2) -> 5987527.9 | R105: 0.5
...

Sheet Abr (2)
A1: Período de Cálculo: | E1: 43191 | U1: Días en el mes | W1: =DATE(YEAR(E1),MONTH(E1)+1,1)-DATE(YEAR(E1),MONTH(E1),1) -> 30
A2: PERUPETRO S.A.
A3: DETERMINACION DEL CANON, SOBRECANON y PARTICIPACION (US$)
A4: ="Correspondiente a "&TEXT(E1,"MMMMMMM YYYY") -> Correspondiente a abril 2018
A5: ="Tipo de Cambio= "&TEXT(F1,"0.000") -> Tipo de Cambio= 0.000
A7: Localidad | C7: Modalidad de Contrato | D7: Calculo del Canon | F7: Volumen Producción / Venta | I7: Canasta o Valor Venta (US$/Unidad) | K7: Deducción de Gastos para determinación de valor de producción en Punto de Fiscalización (US$) | O7: Valor de la Producción (US$) | P7: Canon y Sobrecanon / Participación (US$) | U7: Resumen por Petróleo y Condensados | AA7: Resumen por Gas Natural | AG7: Control
A8: - Lote | D8: Período | E8: Fórmula | F8: Unidades | G8: 1ra. Q | H8: 2da. Q / Mes | I8: 1ra. Q | J8: 2da. Q / Mes | K8: Flete Marítimo | L8: Comercialización | M8: Oleoducto | N8: Fiscalización | P8: Total | Q8: Localidad 1 | S8: Localidad 2 | U8: Producción / Venta | X8: Valor Prod | Y8: Valor Canon | AA8: Producción / Venta | AD8: Valor Prod | AE8: Valor Canon | AG8: Total
A9: Piura / Tumbes | Q9: Piura | S9: Tumbes | U9: Bls/Mes | V9: V P (US$) | W9: Bls/Día | X9: US$/Bl | Y9: US$/Bl | Z9: US$ | AA9: MM BTU/Mes | AB9: V P (US$) | AC9: MM BTU/Día | AD9: US$/MM BTU | AE9: US$/MM BTU | AF9: US$ | AG9: Canon
A10: - | B10: I | C10: Servicios | D10: Mes | E10: F1 | F10: Bls | H10: 21812 | J10: 69.0374 | N10: 675.6 | O10: =ROUND(G10*I10,2)+ROUND(H10*J10,2)-K10-L10-M10-N10 -> 1505168.2 | P10: =ROUND(18.75%*O10,2) -> 282219.03 | Q10: =ROUND($O10*R10,2) -> 225775.23 | R10: 0.15 | S10: =ROUND($O10*T10,2) -> 56443.81 | T10: 0.0375 | U10: =IF($F10&"/Día"=W$9,SUM($G10:$H10),"") -> 21812 | V10: =IF(U10<>"",$O10,"") -> 1505168.2 | W10: =IF($F10&"/Día"=W$9,ROUND(U10/$W$1,1),"") -> 727.1 | X10: =IF(U10=0,0,IF($F10&"/Día"=W$9,ROUND(V10/U10,4),"")) -> 69.0064 | Y10: =IF(U10=0,0,IF($F10&"/Día"=W$9,ROUND(Z10/U10,4),"")) -> 12.9387 | Z10: =IF(U10<>"",$P10,"") -> 282219.03 | AA10: =IF($F10&"/Día"=AC$9,SUM($G10:$H10),"") | AB10: =IF(AA10<>"",$O10,"") | AC10: =IF($F10&"/Día"=AC$9,ROUND(AA10/$W$1,1),"") | AD10: =IF(AA10=0,0,IF($F10&"/Día"=AC$9,ROUND(AB10/AA10,4),"")) | AE10: =IF(AA10=0,0,IF($F10&"/Día"=AC$9,ROUND(AF10/AA10,4),"")) | AF10: =IF(AA10<>"",$P10,"")
A11: - | B11: I GAS | C11: Servicios | D11: Mes | E11: F1 | F11: MM BTU | H11: 207427.64 | J11: 2.934 | N11: 1891.7 | O11: =ROUND(G11*I11,2)+ROUND(H11*J11,2)-K11-L11-M11-N11 -> 606701 | P11: =ROUND(18.75%*O11,2) -> 113756.44 | Q11: =ROUND($O11*R11,2) -> 91005.15 | R11: 0.15 | S11: =ROUND($O11*T11,2) -> 22751.29 | T11: 0.0375 | U11: =IF($F11&"/Día"=W$9,SUM($G11:$H11),"") | V11: =IF(U11<>"",$O11,"") | W11: =IF($F11&"/Día"=W$9,ROUND(U11/$W$1,1),"") | X11: =IF(U11=0,0,IF($F11&"/Día"=W$9,ROUND(V11/U11,4),"")) | Y11: =IF(U11=0,0,IF($F11&"/Día"=W$9,ROUND(Z11/U11,4),"")) | Z11: =IF(U11<>"",$P11,"") | AA11: =IF($F11&"/Día"=AC$9,SUM($G11:$H11),"") -> 207427.64 | AB11: =IF(AA11<>"",$O11,"") -> 606701 | AC11: =IF($F11&"/Día"=AC$9,ROUND(AA11/$W$1,1),"") -> 6914.3 | AD11: =IF(AA11=0,0,IF($F11&"/Día"=AC$9,ROUND(AB11/AA11,4),"")) -> 2.9249 | AE11: =IF(AA11=0,0,IF($F11&"/Día"=AC$9,ROUND(AF11/AA11,4),"")) -> 0.5484 | AF11: =IF(AA11<>"",$P11,"") -> 113756.44
A12: - | B12: II | C12: Licencia | D12: Quincena | E12: F2 | F12: Bls | G12: 4240 | H12: 4760 | I12: 65.1052 | J12: 68.4188 | N12: 1744.22 | O12: =ROUND(G12*I12,2)+ROUND(H12*J12,2)-K12-L12-M12-N12 -> 599975.32 | P12: =ROUND(18.75%*O12,2) -> 112495.37 | Q12: =ROUND($O12*R12,2) -> 89996.3 | R12: 0.15 | S12: =ROUND($O12*T12,2) -> 22499.07 | T12: 0.0375 | U12: =IF($F12&"/Día"=W$9,SUM($G12:$H12),"") -> 9000 | V12: =IF(U12<>"",$O12,"") -> 599975.32 | W12: =IF($F12&"/Día"=W$9,ROUND(U12/$W$1,1),"") -> 300 | X12: =IF(U12=0,0,IF($F12&"/Día"=W$9,ROUND(V12/U12,4),"")) -> 66.6639 | Y12: =IF(U12=0,0,IF($F12&"/Día"=W$9,ROUND(Z12/U12,4),"")) -> 12.4995 | Z12: =IF(U12<>"",$P12,"") -> 112495.37 | AA12: =IF($F12&"/Día"=AC$9,SUM($G12:$H12),"") | AB12: =IF(AA12<>"",$O12,"") | AC12: =IF($F12&"/Día"=AC$9,ROUND(AA12/$W$1,1),"") | AD12: =IF(AA12=0,0,IF($F12&"/Día"=AC$9,ROUND(AB12/AA12,4),"")) | AE12: =IF(AA12=0,0,IF($F12&"/Día"=AC$9,ROUND(AF12/AA12,4),"")) | AF12: =IF(AA12<>"",$P12,"")
A13: - | B13: II-GAS | C13: Servicios | D13: Mes | E13: F1 | F13: MM BTU | G13: 38460.027 | H13: 37277.294 | I13: 2.1591 | J13: 2.1609 | N13: 1862.53 | O13: =ROUND(G13*I13,2)+ROUND(H13*J13,2)-K13-L13-M13-N13 -> 161729.01 | P13: =ROUND(18.75%*O13,2) -> 30324.19 | Q13: =ROUND($P13*R13/(R13+T13),2) -> 24259.35 | R13: 0.15 | S13: =P13-Q13 -> 6064.84 | T13: 0.0375 | U13: =IF($F13&"/Día"=W$9,SUM($G13:$H13),"") | V13: =IF(U13<>"",$O13,"") | W13: =IF($F13&"/Día"=W$9,ROUND(U13/$W$1,1),"") | X13: =IF(U13=0,0,IF($F13&"/Día"=W$9,ROUND(V13/U13,4),"")) | Y13: =IF(U13=0,0,IF($F13&"/Día"=W$9,ROUND(Z13/U13,4),"")) | Z13: =IF(U13<>"",$P13,"") | AA13: =IF($F13&"/Día"=AC$9,SUM($G13:$H13),"") -> 75737.321 | AB13: =IF(AA13<>"",$O13,"") -> 161729.01 | AC13: =IF($F13&"/Día"=AC$9,ROUND(AA13/$W$1,1),"") -> 2524.6 | AD13: =IF(AA13=0,0,IF($F13&"/Día"=AC$9,ROUND(AB13/AA13,4),"")) -> 2.1354 | AE13: =IF(AA13=0,0,IF($F13&"/Día"=AC$9,ROUND(AF13/AA13,4),"")) -> 0.4004 | AF13: =IF(AA13<>"",$P13,"") -> 30324.19
A14: - | B14: III | C14: Licencia | D14: Quincena | E14: F2 | F14: Bls | G14: 11055 | H14: 11288 | I14: 66.8811 | J14: 70.8015 | N14: 1242.63 | O14: =ROUND(G14*I14,2)+ROUND(H14*J14,2)-K14-L14-M14-N14 -> 1537335.3 | P14: =ROUND(18.75%*O14,2) -> 288250.36 | Q14: =ROUND($O14*R14,2) -> 230600.29 | R14: 0.15 | S14: =ROUND($O14*T14,2) -> 57650.07 | T14: 0.0375 | U14: =IF($F14&"/Día"=W$9,SUM($G14:$H14),"") -> 22343 | V14: =IF(U14<>"",$O14,"") -> 1537335.3 | W14: =IF($F14&"/Día"=W$9,ROUND(U14/$W$1,1),"") -> 744.8 | X14: =IF(U14=0,0,IF($F14&"/Día"=W$9,ROUND(V14/U14,4),"")) -> 68.8061 | Y14: =IF(U14=0,0,IF($F14&"/Día"=W$9,ROUND(Z14/U14,4),"")) -> 12.9011 | Z14: =IF(U14<>"",$P14,"") -> 288250.36 | AA14: =IF($F14&"/Día"=AC$9,SUM($G14:$H14),"") | AB14: =IF(AA14<>"",$O14,"") | AC14: =IF($F14&"/Día"=AC$9,ROUND(AA14/$W$1,1),"") | AD14: =IF(AA14=0,0,IF($F14&"/Día"=AC$9,ROUND(AB14/AA14,4),"")) | AE14: =IF(AA14=0,0,IF($F14&"/Día"=AC$9,ROUND(AF14/AA14,4),"")) | AF14: =IF(AA14<>"",$P14,"")
A15: - | B15: IV | C15: Licencia | D15: Quincena | E15: F2 | F15: Bls | G15: 30621 | H15: 31021 | I15: 66.8811 | J15: 70.8015 | N15: 3209.33 | O15: =ROUND(G15*I15,2)+ROUND(H15*J15,2)-K15-L15-M15-N15 -> 4241090.2 | P15: =ROUND(18.75%*O15,2) -> 795204.41 | Q15: =ROUND($O15*R15,2) -> 636163.52 | R15: 0.15 | S15: =ROUND($O15*T15,2) -> 159040.88 | T15: 0.0375 | U15: =IF($F15&"/Día"=W$9,SUM($G15:$H15),"") -> 61642 | V15: =IF(U15<>"",$O15,"") -> 4241090.2 | W15: =IF($F15&"/Día"=W$9,ROUND(U15/$W$1,1),"") -> 2054.7 | X15: =IF(U15=0,0,IF($F15&"/Día"=W$9,ROUND(V15/U15,4),"")) -> 68.802 | Y15: =IF(U15=0,0,IF($F15&"/Día"=W$9,ROUND(Z15/U15,4),"")) -> 12.9004 | Z15: =IF(U15<>"",$P15,"") -> 795204.41 | AA15: =IF($F15&"/Día"=AC$9,SUM($G15:$H15),"") | AB15: =IF(AA15<>"",$O15,"") | AC15: =IF($F15&"/Día"=AC$9,ROUND(AA15/$W$1,1),"") | AD15: =IF(AA15=0,0,IF($F15&"/Día"=AC$9,ROUND(AB15/AA15,4),"")) | AE15: =IF(AA15=0,0,IF($F15&"/Día"=AC$9,ROUND(AF15/AA15,4),"")) | AF15: =IF(AA15<>"",$P15,"")
A16: - | B16: V | C16: Servicios | D16: Mes | E16: F1 | F16: Bls | H16: 4328 | J16: 69.0374 | N16: 1470.21 | O16: =ROUND(G16*I16,2)+ROUND(H16*J16,2)-K16-L16-M16-N16 -> 297323.66 | P16: =ROUND(18.75%*O16,2) -> 55748.19 | Q16: =ROUND($O16*R16,2) -> 44598.55 | R16: 0.15 | S16: =ROUND($O16*T16,2) -> 11149.64 | T16: 0.0375 | U16: =IF($F16&"/Día"=W$9,SUM($G16:$H16),"") -> 4328 | V16: =IF(U16<>"",$O16,"") -> 297323.66 | W16: =IF($F16&"/Día"=W$9,ROUND(U16/$W$1,1),"") -> 144.3 | X16: =IF(U16=0,0,IF($F16&"/Día"=W$9,ROUND(V16/U16,4),"")) -> 68.6977 | Y16: =IF(U16=0,0,IF($F16&"/Día"=W$9,ROUND(Z16/U16,4),"")) -> 12.8808 | Z16: =IF(U16<>"",$P16,"") -> 55748.19 | AA16: =IF($F16&"/Día"=AC$9,SUM($G16:$H16),"") | AB16: =IF(AA16<>"",$O16,"") | AC16: =IF($F16&"/Día"=AC$9,ROUND(AA16/$W$1,1),"") | AD16: =IF(AA16=0,0,IF($F16&"/Día"=AC$9,ROUND(AB16/AA16,4),"")) | AE16: =IF(AA16=0,0,IF($F16&"/Día"=AC$9,ROUND(AF16/AA16,4),"")) | AF16: =IF(AA16<>"",$P16,"")
A17: - | B17: VII/VI | C17: Licencia | D17: Quincena | E17: F2 | F17: Bls | G17: 53887 | H17: 57472 | I17: 66.3311 | J17: 70.2515 | N17: 2195.94 | O17: =ROUND(G17*I17,2)+ROUND(H17*J17,2)-K17-L17-M17-N17 -> 7609682.3 | P17: =ROUND(18.75%*O17,2) -> 1426815.4 | Q17: =ROUND($O17*R17,2) -> 1141452.3 | R17: 0.15 | S17: =ROUND($O17*T17,2) -> 285363.08 | T17: 0.0375 | U17: =IF($F17&"/Día"=W$9,SUM($G17:$H17),"") -> 111359 | V17: =IF(U17<>"",$O17,"") -> 7609682.3 | W17: =IF($F17&"/Día"=W$9,ROUND(U17/$W$1,1),"") -> 3712 | X17: =IF(U17=0,0,IF($F17&"/Día"=W$9,ROUND(V17/U17,4),"")) -> 68.3347 | Y17: =IF(U17=0,0,IF($F17&"/Día"=W$9,ROUND(Z17/U17,4),"")) -> 12.8128 | Z17: =IF(U17<>"",$P17,"") -> 1426815.4 | AA17: =IF($F17&"/Día"=AC$9,SUM($G17:$H17),"") | AB17: =IF(AA17<>"",$O17,"") | AC17: =IF($F17&"/Día"=AC$9,ROUND(AA17/$W$1,1),"") | AD17: =IF(AA17=0,0,IF($F17&"/Día"=AC$9,ROUND(AB17/AA17,4),"")) | AE17: =IF(AA17=0,0,IF($F17&"/Día"=AC$9,ROUND(AF17/AA17,4),"")) | AF17: =IF(AA17<>"",$P17,"")
A18: - | B18: VII | C18: Servicios | D18: Mes | E18: F1 | F18: Bls | O18: =ROUND(G18*I18,2)+ROUND(H18*J18,2)-K18-L18-M18-N18 -> 0 | P18: =ROUND(18.75%*O18,2) -> 0 | Q18: =ROUND($O18*R18,2) -> 0 | R18: 0.15 | S18: =ROUND($O18*T18,2) -> 0 | T18: 0.0375 | U18: =IF($F18&"/Día"=W$9,SUM($G18:$H18),"") -> 0 | V18: =IF(U18<>"",$O18,"") -> 0 | W18: =IF($F18&"/Día"=W$9,ROUND(U18/$W$1,1),"") -> 0 | X18: =IF(U18=0,0,IF($F18&"/Día"=W$9,ROUND(V18/U18,4),"")) -> 0 | Y18: =IF(U18=0,0,IF($F18&"/Día"=W$9,ROUND(Z18/U18,4),"")) -> 0 | Z18: =IF(U18<>"",$P18,"") -> 0 | AA18: =IF($F18&"/Día"=AC$9,SUM($G18:$H18),"") | AB18: =IF(AA18<>"",$O18,"") | AC18: =IF($F18&"/Día"=AC$9,ROUND(AA18/$W$1,1),"") | AD18: =IF(AA18=0,0,IF($F18&"/Día"=AC$9,ROUND(AB18/AA18,4),"")) | AE18: =IF(AA18=0,0,IF($F18&"/Día"=AC$9,ROUND(AF18/AA18,4),"")) | AF18: =IF(AA18<>"",$P18,"")
A19: - | B19: VII/VI-GAS | C19: Licencia | D19: Quincena | E19: F2 | F19: MM BTU | G19: 57333.39 | H19: 47484.57 | I19: 0.8 | J19: 0.8 | N19: 2096.88 | O19: =ROUND(G19*I19,2)+ROUND(H19*J19,2)-K19-L19-M19-N19 -> 81757.49 | P19: =ROUND(18.75%*O19,2) -> 15329.53 | Q19: =ROUND($O19*R19,2) -> 12263.62 | R19: 0.15 | S19: =ROUND($O19*T19,2) -> 3065.91 | T19: 0.0375 | U19: =IF($F19&"/Día"=W$9,SUM($G19:$H19),"") | V19: =IF(U19<>"",$O19,"") | W19: =IF($F19&"/Día"=W$9,ROUND(U19/$W$1,1),"") | X19: =IF(U19=0,0,IF($F19&"/Día"=W$9,ROUND(V19/U19,4),"")) | Y19: =IF(U19=0,0,IF($F19&"/Día"=W$9,ROUND(Z19/U19,4),"")) | Z19: =IF(U19<>"",$P19,"") | AA19: =IF($F19&"/Día"=AC$9,SUM($G19:$H19),"") -> 104817.96 | AB19: =IF(AA19<>"",$O19,"") -> 81757.49 | AC19: =IF($F19&"/Día"=AC$9,ROUND(AA19/$W$1,1),"") -> 3493.9 | AD19: =IF(AA19=0,0,IF($F19&"/Día"=AC$9,ROUND(AB19/AA19,4),"")) -> 0.78 | AE19: =IF(AA19=0,0,IF($F19&"/Día"=AC$9,ROUND(AF19/AA19,4),"")) -> 0.1462 | AF19: =IF(AA19<>"",$P19,"") -> 15329.53
A20: - | B20: IX | C20: Licencia | D20: Quincena | E20: F2 | F20: Bls | G20: 2124 | H20: 3038 | I20: 66.8811 | J20: 70.8015 | N20: 729.17 | O20: =ROUND(G20*I20,2)+ROUND(H20*J20,2)-K20-L20-M20-N20 -> 356421.25 | P20: =ROUND(18.75%*O20,2) -> 66828.98 | Q20: =ROUND($O20*R20,2) -> 53463.19 | R20: 0.15 | S20: =ROUND($O20*T20,2) -> 13365.8 | T20: 0.0375 | U20: =IF($F20&"/Día"=W$9,SUM($G20:$H20),"") -> 5162 | V20: =IF(U20<>"",$O20,"") -> 356421.25 | W20: =IF($F20&"/Día"=W$9,ROUND(U20/$W$1,1),"") -> 172.1 | X20: =IF(U20=0,0,IF($F20&"/Día"=W$9,ROUND(V20/U20,4),"")) -> 69.0471 | Y20: =IF(U20=0,0,IF($F20&"/Día"=W$9,ROUND(Z20/U20,4),"")) -> 12.9463 | Z20: =IF(U20<>"",$P20,"") -> 66828.98 | AA20: =IF($F20&"/Día"=AC$9,SUM($G20:$H20),"") | AB20: =IF(AA20<>"",$O20,"") | AC20: =IF($F20&"/Día"=AC$9,ROUND(AA20/$W$1,1),"") | AD20: =IF(AA20=0,0,IF($F20&"/Día"=AC$9,ROUND(AB20/AA20,4),"")) | AE20: =IF(AA20=0,0,IF($F20&"/Día"=AC$9,ROUND(AF20/AA20,4),"")) | AF20: =IF(AA20<>"",$P20,"")
A21: - | B21: X | C21: Licencia | D21: Quincena | E21: F2 | F21: Bls | G21: 192441 | H21: 192657 | I21: 66.8811 | J21: 70.8015 | N21: 4283.58 | O21: =ROUND(G21*I21,2)+ROUND(H21*J21,2)-K21-L21-M21-N21 -> 26506787 | P21: =ROUND(18.75%*O21,2) -> 4970022.5 | Q21: =ROUND($O21*R21,2) -> 3976018 | R21: 0.15 | S21: =ROUND($O21*T21,2) -> 994004.5 | T21: 0.0375 | U21: =IF($F21&"/Día"=W$9,SUM($G21:$H21),"") -> 385098 | V21: =IF(U21<>"",$O21,"") -> 26506787 | W21: =IF($F21&"/Día"=W$9,ROUND(U21/$W$1,1),"") -> 12836.6 | X21: =IF(U21=0,0,IF($F21&"/Día"=W$9,ROUND(V21/U21,4),"")) -> 68.8313 | Y21: =IF(U21=0,0,IF($F21&"/Día"=W$9,ROUND(Z21/U21,4),"")) -> 12.9059 | Z21: =IF(U21<>"",$P21,"") -> 4970022.5 | AA21: =IF($F21&"/Día"=AC$9,SUM($G21:$H21),"") | AB21: =IF(AA21<>"",$O21,"") | AC21: =IF($F21&"/Día"=AC$9,ROUND(AA21/$W$1,1),"") | AD21: =IF(AA21=0,0,IF($F21&"/Día"=AC$9,ROUND(AB21/AA21,4),"")) | AE21: =IF(AA21=0,0,IF($F21&"/Día"=AC$9,ROUND(AF21/AA21,4),"")) | AF21: =IF(AA21<>"",$P21,"")
A22: - | B22: X-GAS | C22: Licencia | D22: Mes | E22: F2 | F22: MM BTU | G22: 245652.84 | H22: 253188.98 | I22: 1.7112 | J22: 1.7112 | N22: 2209.07 | O22: =ROUND(G22*I22,2)+ROUND(H22*J22,2)-K22-L22-M22-N22 -> 851409.05 | P22: =ROUND(18.75%*O22,2) -> 159639.2 | Q22: =ROUND($O22*R22,2) -> 127711.36 | R22: 0.15 | S22: =ROUND($O22*T22,2) -> 31927.84 | T22: 0.0375 | U22: =IF($F22&"/Día"=W$9,SUM($G22:$H22),"") | V22: =IF(U22<>"",$O22,"") | W22: =IF($F22&"/Día"=W$9,ROUND(U22/$W$1,1),"") | X22: =IF(U22=0,0,IF($F22&"/Día"=W$9,ROUND(V22/U22,4),"")) | Y22: =IF(U22=0,0,IF($F22&"/Día"=W$9,ROUND(Z22/U22,4),"")) | Z22: =IF(U22<>"",$P22,"") | AA22: =IF($F22&"/Día"=AC$9,SUM($G22:$H22),"") -> 498841.82 | AB22: =IF(AA22<>"",$O22,"") -> 851409.05 | AC22: =IF($F22&"/Día"=AC$9,ROUND(AA22/$W$1,1),"") -> 16628.1 | AD22: =IF(AA22=0,0,IF($F22&"/Día"=AC$9,ROUND(AB22/AA22,4),"")) -> 1.7068 | AE22: =IF(AA22=0,0,IF($F22&"/Día"=AC$9,ROUND(AF22/AA22,4),"")) -> 0.32 | AF22: =IF(AA22<>"",$P22,"") -> 159639.2
A23: - | B23: XIV | C23: Licencia | D23: Mes | E23: F2 | F23: Bls | O23: =ROUND(G23*I23,2)+ROUND(H23*J23,2)-K23-L23-M23-N23 -> 0 | P23: =ROUND(18.75%*O23,2) -> 0 | Q23: =ROUND($O23*R23,2) -> 0 | R23: 0.15 | S23: =ROUND($O23*T23,2) -> 0 | T23: 0.0375 | U23: =IF($F23&"/Día"=W$9,SUM($G23:$H23),"") -> 0 | V23: =IF(U23<>"",$O23,"") -> 0 | W23: =IF($F23&"/Día"=W$9,ROUND(U23/$W$1,1),"") -> 0 | X23: =IF(U23=0,0,IF($F23&"/Día"=W$9,ROUND(V23/U23,4),"")) -> 0 | Y23: =IF(U23=0,0,IF($F23&"/Día"=W$9,ROUND(Z23/U23,4),"")) -> 0 | Z23: =IF(U23<>"",$P23,"") -> 0 | AA23: =IF($F23&"/Día"=AC$9,SUM($G23:$H23),"") | AB23: =IF(AA23<>"",$O23,"") | AC23: =IF($F23&"/Día"=AC$9,ROUND(AA23/$W$1,1),"") | AD23: =IF(AA23=0,0,IF($F23&"/Día"=AC$9,ROUND(AB23/AA23,4),"")) | AE23: =IF(AA23=0,0,IF($F23&"/Día"=AC$9,ROUND(AF23/AA23,4),"")) | AF23: =IF(AA23<>"",$P23,"")
A24: - | B24: XV | C24: Licencia | D24: Quincena | E24: F2 | F24: Bls | G24: 557 | H24: 544 | I24: 67.6937 | J24: 70.8609 | N24: 792.9 | O24: =ROUND(G24*I24,2)+ROUND(H24*J24,2)-K24-L24-M24-N24 -> 75460.82 | P24: =ROUND(18.75%*O24,2) -> 14148.9 | Q24: =ROUND($O24*R24,2) -> 11319.12 | R24: 0.15 | S24: =ROUND($O24*T24,2) -> 2829.78 | T24: 0.0375 | U24: =IF($F24&"/Día"=W$9,SUM($G24:$H24),"") -> 1101 | V24: =IF(U24<>"",$O24,"") -> 75460.82 | W24: =IF($F24&"/Día"=W$9,ROUND(U24/$W$1,1),"") -> 36.7 | X24: =IF(U24=0,0,IF($F24&"/Día"=W$9,ROUND(V24/U24,4),"")) -> 68.5384 | Y24: =IF(U24=0,0,IF($F24&"/Día"=W$9,ROUND(Z24/U24,4),"")) -> 12.851 | Z24: =IF(U24<>"",$P24,"") -> 14148.9 | AA24: =IF($F24&"/Día"=AC$9,SUM($G24:$H24),"") | AB24: =IF(AA24<>"",$O24,"") | AC24: =IF($F24&"/Día"=AC$9,ROUND(AA24/$W$1,1),"") | AD24: =IF(AA24=0,0,IF($F24&"/Día"=AC$9,ROUND(AB24/AA24,4),"")) | AE24: =IF(AA24=0,0,IF($F24&"/Día"=AC$9,ROUND(AF24/AA24,4),"")) | AF24: =IF(AA24<>"",$P24,"")
A25: - | B25: XIII Crudo | C25: Licencia | D25: Quincena | E25: F2 | F25: Bls | G25: 25730 | H25: 31508 | I25: 66.8811 | J25: 70.8015 | N25: 1512.61 | O25: =ROUND(G25*I25,2)+ROUND(H25*J25,2)-K25-L25-M25-N25 -> 3950151.8 | P25: =ROUND(18.75%*O25,2) -> 740653.45 | Q25: =ROUND($O25*R25,2) -> 592522.76 | R25: 0.15 | S25: =ROUND($O25*T25,2) -> 148130.69 | T25: 0.0375 | U25: =IF($F25&"/Día"=W$9,SUM($G25:$H25),"") -> 57238 | V25: =IF(U25<>"",$O25,"") -> 3950151.8 | W25: =IF($F25&"/Día"=W$9,ROUND(U25/$W$1,1),"") -> 1907.9 | X25: =IF(U25=0,0,IF($F25&"/Día"=W$9,ROUND(V25/U25,4),"")) -> 69.0127 | Y25: =IF(U25=0,0,IF($F25&"/Día"=W$9,ROUND(Z25/U25,4),"")) -> 12.9399 | Z25: =IF(U25<>"",$P25,"") -> 740653.45 | AA25: =IF($F25&"/Día"=AC$9,SUM($G25:$H25),"") | AB25: =IF(AA25<>"",$O25,"") | AC25: =IF($F25&"/Día"=AC$9,ROUND(AA25/$W$1,1),"") | AD25: =IF(AA25=0,0,IF($F25&"/Día"=AC$9,ROUND(AB25/AA25,4),"")) | AE25: =IF(AA25=0,0,IF($F25&"/Día"=AC$9,ROUND(AF25/AA25,4),"")) | AF25: =IF(AA25<>"",$P25,"")
A26: - | B26: XIII COND | C26: Licencia | D26: Quincena | E26: F2 | F26: Bls | O26: =ROUND(G26*I26,2)+ROUND(H26*J26,2)-K26-L26-M26-N26 -> 0 | P26: =ROUND(18.75%*O26,2) -> 0 | Q26: =ROUND($O26*R26,2) -> 0 | R26: 0.15 | S26: =ROUND($O26*T26,2) -> 0 | T26: 0.0375 | U26: =IF($F26&"/Día"=W$9,SUM($G26:$H26),"") -> 0 | V26: =IF(U26<>"",$O26,"") -> 0 | W26: =IF($F26&"/Día"=W$9,ROUND(U26/$W$1,1),"") -> 0 | X26: =IF(U26=0,0,IF($F26&"/Día"=W$9,ROUND(V26/U26,4),"")) -> 0 | Y26: =IF(U26=0,0,IF($F26&"/Día"=W$9,ROUND(Z26/U26,4),"")) -> 0 | Z26: =IF(U26<>"",$P26,"") -> 0 | AA26: =IF($F26&"/Día"=AC$9,SUM($G26:$H26),"") | AB26: =IF(AA26<>"",$O26,"") | AC26: =IF($F26&"/Día"=AC$9,ROUND(AA26/$W$1,1),"") | AD26: =IF(AA26=0,0,IF($F26&"/Día"=AC$9,ROUND(AB26/AA26,4),"")) | AE26: =IF(AA26=0,0,IF($F26&"/Día"=AC$9,ROUND(AF26/AA26,4),"")) | AF26: =IF(AA26<>"",$P26,"")
A27: - | B27: XIII Gas | C27: Licencia | D27: Quincena | E27: F2 | F27: MM BTU | G27: =104778.0799+72373.8704 -> 177151.95 | H27: =107745.4041+80578.4653 -> 188323.87 | I27: 2.5397374 | J27: 2.5926134 | N27: 3126.36 | O27: =ROUND(G27*I27,2)+ROUND(H27*J27,2)-K27-L27-M27-N27 -> 935044.05 | P27: =ROUND(18.75%*O27,2) -> 175320.76 | Q27: =ROUND($O27*R27,2) -> 140256.61 | R27: 0.15 | S27: =ROUND($O27*T27,2) -> 35064.15 | T27: 0.0375 | U27: =IF($F27&"/Día"=W$9,SUM($G27:$H27),"") | V27: =IF(U27<>"",$O27,"") | W27: =IF($F27&"/Día"=W$9,ROUND(U27/$W$1,1),"") | X27: =IF(U27=0,0,IF($F27&"/Día"=W$9,ROUND(V27/U27,4),"")) | Y27: =IF(U27=0,0,IF($F27&"/Día"=W$9,ROUND(Z27/U27,4),"")) | Z27: =IF(U27<>"",$P27,"") | AA27: =IF($F27&"/Día"=AC$9,SUM($G27:$H27),"") -> 365475.82 | AB27: =IF(AA27<>"",$O27,"") -> 935044.05 | AC27: =IF($F27&"/Día"=AC$9,ROUND(AA27/$W$1,1),"") -> 12182.5 | AD27: =IF(AA27=0,0,IF($F27&"/Día"=AC$9,ROUND(AB27/AA27,4),"")) -> 2.5584 | AE27: =IF(AA27=0,0,IF($F27&"/Día"=AC$9,ROUND(AF27/AA27,4),"")) -> 0.4797 | AF27: =IF(AA27<>"",$P27,"") -> 175320.76
A28: - | B28: Z-2B | C28: Servicios | D28: Mes | E28: F1 | F28: Bls | G28: =41580+38551+37557+37373+40740+39453+34290 -> 269544 | H28: =38140+200235 -> 238375 | I28: 3.0405943 | J28: 66.808616 | N28: 2417.19 | O28: =ROUND(G28*I28,2)+ROUND(H28*J28,2)-K28-L28-M28-N28 -> 16742661 | P28: =ROUND(18.75%*O28,2) -> 3139248.9 | Q28: =ROUND($O28*R28,2) -> 2511399.1 | R28: 0.15 | S28: =ROUND($O28*T28,2) -> 627849.77 | T28: 0.0375 | U28: =IF($F28&"/Día"=W$9,SUM($G28:$H28),"") -> 507919 | V28: =IF(U28<>"",$O28,"") -> 16742661 | W28: =IF($F28&"/Día"=W$9,ROUND(U28/$W$1,1),"") -> 16930.6 | X28: =IF(U28=0,0,IF($F28&"/Día"=W$9,ROUND(V28/U28,4),"")) -> 32.9632 | Y28: =IF(U28=0,0,IF($F28&"/Día"=W$9,ROUND(Z28/U28,4),"")) -> 6.1806 | Z28: =IF(U28<>"",$P28,"") -> 3139248.9 | AA28: =IF($F28&"/Día"=AC$9,SUM($G28:$H28),"") | AB28: =IF(AA28<>"",$O28,"") | AC28: =IF($F28&"/Día"=AC$9,ROUND(AA28/$W$1,1),"") | AD28: =IF(AA28=0,0,IF($F28&"/Día"=AC$9,ROUND(AB28/AA28,4),"")) | AE28: =IF(AA28=0,0,IF($F28&"/Día"=AC$9,ROUND(AF28/AA28,4),"")) | AF28: =IF(AA28<>"",$P28,"")
A29: - | B29: Z-2B GAS | C29: Servicios | D29: Mes | E29: F1 | F29: MM BTU | H29: =1153.36+20956.56+116077.1 -> 138187.02 | J29: 5.5796026 | N29: 2131.57 | O29: =ROUND(G29*I29,2)+ROUND(H29*J29,2)-K29-L29-M29-N29 -> 768897.09 | P29: =ROUND(18.75%*O29,2) -> 144168.2 | Q29: =ROUND($O29*R29,2) -> 115334.56 | R29: 0.15 | S29: =ROUND($O29*T29,2) -> 28833.64 | T29: 0.0375 | U29: =IF($F29&"/Día"=W$9,SUM($G29:$H29),"") | V29: =IF(U29<>"",$O29,"") | W29: =IF($F29&"/Día"=W$9,ROUND(U29/$W$1,1),"") | X29: =IF(U29=0,0,IF($F29&"/Día"=W$9,ROUND(V29/U29,4),"")) | Y29: =IF(U29=0,0,IF($F29&"/Día"=W$9,ROUND(Z29/U29,4),"")) | Z29: =IF(U29<>"",$P29,"") | AA29: =IF($F29&"/Día"=AC$9,SUM($G29:$H29),"") -> 138187.02 | AB29: =IF(AA29<>"",$O29,"") -> 768897.09 | AC29: =IF($F29&"/Día"=AC$9,ROUND(AA29/$W$1,1),"") -> 4606.2 | AD29: =IF(AA29=0,0,IF($F29&"/Día"=AC$9,ROUND(AB29/AA29,4),"")) -> 5.5642 | AE29: =IF(AA29=0,0,IF($F29&"/Día"=AC$9,ROUND(AF29/AA29,4),"")) -> 1.0433 | AF29: =IF(AA29<>"",$P29,"") -> 144168.2
A30: - | B30: XX | C30: Licencia | D30: Quincena | E30: F2 | F30: Bls | G30: 329 | H30: 329 | I30: 66.8811 | J30: 70.8015 | N30: 465.7 | O30: =ROUND(G30*I30,2)+ROUND(H30*J30,2)-K30-L30-M30-N30 -> 44831.87 | P30: =ROUND(18.75%*O30,2) -> 8405.98 | Q30: =ROUND($O30*R30,2) -> 1681.2 | R30: 0.0375 | S30: =ROUND($O30*T30,2) -> 6724.78 | T30: 0.15 | U30: =IF($F30&"/Día"=W$9,SUM($G30:$H30),"") -> 658 | V30: =IF(U30<>"",$O30,"") -> 44831.87 | W30: =IF($F30&"/Día"=W$9,ROUND(U30/$W$1,1),"") -> 21.9 | X30: =IF(U30=0,0,IF($F30&"/Día"=W$9,ROUND(V30/U30,4),"")) -> 68.1335 | Y30: =IF(U30=0,0,IF($F30&"/Día"=W$9,ROUND(Z30/U30,4),"")) -> 12.775 | Z30: =IF(U30<>"",$P30,"") -> 8405.98 | AA30: =IF($F30&"/Día"=AC$9,SUM($G30:$H30),"") | AB30: =IF(AA30<>"",$O30,"") | AC30: =IF($F30&"/Día"=AC$9,ROUND(AA30/$W$1,1),"") | AD30: =IF(AA30=0,0,IF($F30&"/Día"=AC$9,ROUND(AB30/AA30,4),"")) | AE30: =IF(AA30=0,0,IF($F30&"/Día"=AC$9,ROUND(AF30/AA30,4),"")) | AF30: =IF(AA30<>"",$P30,"")
A31: - | B31: Z1 Crudo | C31: Licencia | D31: Quincena | E31: F2 | F31: Bls | N31: 1434.04 | O31: =ROUND(G31*I31,2)+ROUND(H31*J31,2)-K31-L31-M31-N31 -> -1434.04 | P31: =ROUND(18.75%*O31,2) -> -268.88 | Q31: =ROUND($O31*R31,2) -> -53.78 | R31: 0.0375 | S31: =ROUND($O31*T31,2) -> -215.11 | T31: 0.15 | U31: =IF($F31&"/Día"=W$9,SUM($G31:$H31),"") -> 0 | V31: =IF(U31<>"",$O31,"") -> -1434.04 | W31: =IF($F31&"/Día"=W$9,ROUND(U31/$W$1,1),"") -> 0 | X31: =IF(U31=0,0,IF($F31&"/Día"=W$9,ROUND(V31/U31,4),"")) -> 0 | Y31: =IF(U31=0,0,IF($F31&"/Día"=W$9,ROUND(Z31/U31,4),"")) -> 0 | Z31: =IF(U31<>"",$P31,"") -> -268.88 | AA31: =IF($F31&"/Día"=AC$9,SUM($G31:$H31),"") | AB31: =IF(AA31<>"",$O31,"") | AC31: =IF($F31&"/Día"=AC$9,ROUND(AA31/$W$1,1),"") | AD31: =IF(AA31=0,0,IF($F31&"/Día"=AC$9,ROUND(AB31/AA31,4),"")) | AE31: =IF(AA31=0,0,IF($F31&"/Día"=AC$9,ROUND(AF31/AA31,4),"")) | AF31: =IF(AA31<>"",$P31,"")
A32: - | B32: Z1 Gas | C32: Licencia | D32: Quincena | E32: F2 | F32: MM BTU | O32: =ROUND(G32*I32,2)+ROUND(H32*J32,2)-K32-L32-M32-N32 -> 0 | P32: =ROUND(18.75%*O32,2) -> 0 | Q32: =ROUND($O32*R32,2) -> 0 | R32: 0.0375 | S32: =ROUND($O32*T32,2) -> 0 | T32: 0.15 | U32: =IF($F32&"/Día"=W$9,SUM($G32:$H32),"") | V32: =IF(U32<>"",$O32,"") | W32: =IF($F32&"/Día"=W$9,ROUND(U32/$W$1,1),"") | X32: =IF(U32=0,0,IF($F32&"/Día"=W$9,ROUND(V32/U32,4),"")) | Y32: =IF(U32=0,0,IF($F32&"/Día"=W$9,ROUND(Z32/U32,4),"")) | Z32: =IF(U32<>"",$P32,"") | AA32: =IF($F32&"/Día"=AC$9,SUM($G32:$H32),"") -> 0 | AB32: =IF(AA32<>"",$O32,"") -> 0 | AC32: =IF($F32&"/Día"=AC$9,ROUND(AA32/$W$1,1),"") -> 0 | AD32: =IF(AA32=0,0,IF($F32&"/Día"=AC$9,ROUND(AB32/AA32,4),"")) -> 0 | AE32: =IF(AA32=0,0,IF($F32&"/Día"=AC$9,ROUND(AF32/AA32,4),"")) -> 0 | AF32: =IF(AA32<>"",$P32,"") -> 0
A33: - | B33: Z-2B - LGN | C33: Servicios | D33: Mes | E33: F1 | F33: Bls | H33: =27634+5264 -> 32898 | J33: 54.9433 | N33: 2321.9 | O33: =ROUND(G33*I33,2)+ROUND(H33*J33,2)-K33-L33-M33-N33 -> 1805202.8 | P33: =ROUND(18.75%*O33,2) -> 338475.52 | Q33: =ROUND($O33*R33,2) -> 270780.42 | R33: 0.15 | S33: =ROUND($O33*T33,2) -> 67695.1 | T33: 0.0375 | U33: =IF($F33&"/Día"=W$9,SUM($G33:$H33),"") -> 32898 | V33: =IF(U33<>"",$O33,"") -> 1805202.8 | W33: =IF($F33&"/Día"=W$9,ROUND(U33/$W$1,1),"") -> 1096.6 | X33: =IF(U33=0,0,IF($F33&"/Día"=W$9,ROUND(V33/U33,4),"")) -> 54.8727 | Y33: =IF(U33=0,0,IF($F33&"/Día"=W$9,ROUND(Z33/U33,4),"")) -> 10.2886 | Z33: =IF(U33<>"",$P33,"") -> 338475.52 | AA33: =IF($F33&"/Día"=AC$9,SUM($G33:$H33),"") | AB33: =IF(AA33<>"",$O33,"") | AC33: =IF($F33&"/Día"=AC$9,ROUND(AA33/$W$1,1),"") | AD33: =IF(AA33=0,0,IF($F33&"/Día"=AC$9,ROUND(AB33/AA33,4),"")) | AE33: =IF(AA33=0,0,IF($F33&"/Día"=AC$9,ROUND(AF33/AA33,4),"")) | AF33: =IF(AA33<>"",$P33,"")
A34: - | B34: Z-6 | C34: Licencia | D34: Quincena | E34: F2 | F34: MM BTU | O34: =ROUND(G34*I34,2)+ROUND(H34*J34,2)-K34-L34-M34-N34 -> 0 | P34: =ROUND(18.75%*O34,2) -> 0 | Q34: =ROUND($O34*R34,2) -> 0 | R34: 0.15 | S34: =ROUND($O34*T34,2) -> 0 | T34: 0.0375
A35: - | B35: Ajustes meses anteriores (1) | O35: =O440 -> -23593.12 | P35: =P440 -> -4423.71 | Q35: =Q440 -> -3538.97 | S35: =S440 -> -884.74 | U35: =IF($F35&"/Día"=W$9,SUM($G35:$H35),"") | V35: =IF(U35<>"",$O35,"") | W35: =IF($F35&"/Día"=W$9,ROUND(U35/$W$1,1),"") | X35: =IF(U35=0,0,IF($F35&"/Día"=W$9,ROUND(V35/U35,4),"")) | Y35: =IF(U35=0,0,IF($F35&"/Día"=W$9,ROUND(Z35/U35,4),"")) | Z35: =IF(U35<>"",$P35,"") | AA35: =IF($F35&"/Día"=AC$9,SUM($G35:$H35),"") | AB35: =IF(AA35<>"",$O35,"") | AC35: =IF($F35&"/Día"=AC$9,ROUND(AA35/$W$1,1),"") | AD35: =IF(AA35=0,0,IF($F35&"/Día"=AC$9,ROUND(AB35/AA35,4),"")) | AE35: =IF(AA35=0,0,IF($F35&"/Día"=AC$9,ROUND(AF35/AA35,4),"")) | AF35: =IF(AA35<>"",$P35,"")
B36: Subtotal | C36: =TEXT(A$9,)&" US$" -> Piura / Tumbes US$ | O36: =SUM(O10:O35) -> 68652601 | P36: =SUM(P10:P35) -> 12872363 | Q36: =SUM(Q10:Q35) -> 10293008 | S36: =SUM(S10:S35) -> 2579354.8 | U36: =SUM(U10:U35) -> 1220558 | V36: =SUM(V10:V35) -> 65270657 | W36: =SUM(W10:W35) -> 40685.3 | X36: =ROUND(V36/U36,4) -> 53.4761 | Y36: =ROUND(Z36/U36,4) -> 10.0268 | Z36: =SUM(Z10:Z35) -> 12238248 | AA36: =SUM(AA10:AA35) -> 1390487.6 | AB36: =SUM(AB10:AB35) -> 3405537.7 | AC36: =SUM(AC10:AC35) -> 46349.6 | AD36: =ROUND(AB36/AA36,4) -> 2.4492 | AE36: =ROUND(AF36/AA36,4) -> 0.4592 | AF36: =SUM(AF10:AF35) -> 638538.32 | AG36: =P36-Z36-AF36 -> -4423.71
C37: =TEXT(A$9,)&" S/." -> Piura / Tumbes S/. | P37: =ROUND($F$1*P36,2) -> 0 | Q37: =ROUND($F$1*Q36,2) -> 0 | S37: =ROUND($F$1*S36,2) -> 0
A38: Provincia Puerto Inca Huanuco | Q38: Puerto Inca
A39: - | B39: 31-D | C39: Licencia | D39: Quincena | E39: F2 | F39: Bls | N39: 1099.45 | O39: =ROUND(G39*I39,2)+ROUND(H39*J39,2)-K39-L39-M39-N39 -> -1099.45 | P39: =ROUND(15%*O39,2) -> -164.92 | Q39: =ROUND($O39*R39,2) -> -164.92 | R39: 0.15 | U39: =IF($F39&"/Día"=W$9,SUM($G39:$H39),"") -> 0 | V39: =IF(U39<>"",$O39,"") -> -1099.45 | W39: =IF($F39&"/Día"=W$9,ROUND(U39/$W$1,1),"") -> 0 | X39: =IF(U39=0,0,IF($F39&"/Día"=W$9,ROUND(V39/U39,4),"")) -> 0 | Y39: =IF(U39=0,0,IF($F39&"/Día"=W$9,ROUND(Z39/U39,4),"")) -> 0 | Z39: =IF(U39<>"",$P39,"") -> -164.92 | AA39: =IF($F39&"/Día"=AC$9,SUM($G39:$H39),"") | AB39: =IF(AA39<>"",$O39,"") | AC39: =IF($F39&"/Día"=AC$9,ROUND(AA39/$W$1,1),"") | AD39: =IF(AA39=0,0,IF($F39&"/Día"=AC$9,ROUND(AB39/AA39,4),"")) | AE39: =IF(AA39=0,0,IF($F39&"/Día"=AC$9,ROUND(AF39/AA39,4),"")) | AF39: =IF(AA39<>"",$P39,"")
A40: - | B40: 131 | C40: Licencia | D40: Quincena | E40: F2 | F40: Bls | G40: 44053 | H40: 44299 | I40: 65.1058 | J40: 68.7299 | N40: 9334.62 | O40: =ROUND(G40*I40,2)+ROUND(H40*J40,2)-K40-L40-M40-N40 -> 5903437 | P40: =ROUND(15%*O40,2) -> 885515.55 | Q40: =ROUND($O40*R40,2) -> 885515.55 | R40: 0.15 | U40: =IF($F40&"/Día"=W$9,SUM($G40:$H40),"") -> 88352 | V40: =IF(U40<>"",$O40,"") -> 5903437 | W40: =IF($F40&"/Día"=W$9,ROUND(U40/$W$1,1),"") -> 2945.1 | X40: =IF(U40=0,0,IF($F40&"/Día"=W$9,ROUND(V40/U40,4),"")) -> 66.8172 | Y40: =IF(U40=0,0,IF($F40&"/Día"=W$9,ROUND(Z40/U40,4),"")) -> 10.0226 | Z40: =IF(U40<>"",$P40,"") -> 885515.55 | AA40: =IF($F40&"/Día"=AC$9,SUM($G40:$H40),"") | AB40: =IF(AA40<>"",$O40,"") | AC40: =IF($F40&"/Día"=AC$9,ROUND(AA40/$W$1,1),"") | AD40: =IF(AA40=0,0,IF($F40&"/Día"=AC$9,ROUND(AB40/AA40,4),"")) | AE40: =IF(AA40=0,0,IF($F40&"/Día"=AC$9,ROUND(AF40/AA40,4),"")) | AF40: =IF(AA40<>"",$P40,"")
A41: - | B41: Ajustes meses anteriores (2) | O41: =O442 -> 147042.22 | P41: =P442 -> 22056.33 | Q41: =Q442 -> 22056.33 | U41: =IF($F41&"/Día"=W$9,SUM($G41:$H41),"") | V41: =IF(U41<>"",$O41,"") | W41: =IF($F41&"/Día"=W$9,ROUND(U41/$W$1,1),"") | X41: =IF(U41=0,0,IF($F41&"/Día"=W$9,ROUND(V41/U41,4),"")) | Y41: =IF(U41=0,0,IF($F41&"/Día"=W$9,ROUND(Z41/U41,4),"")) | Z41: =IF(U41<>"",$P41,"") | AA41: =IF($F41&"/Día"=AC$9,SUM($G41:$H41),"") | AB41: =IF(AA41<>"",$O41,"") | AC41: =IF($F41&"/Día"=AC$9,ROUND(AA41/$W$1,1),"") | AD41: =IF(AA41=0,0,IF($F41&"/Día"=AC$9,ROUND(AB41/AA41,4),"")) | AE41: =IF(AA41=0,0,IF($F41&"/Día"=AC$9,ROUND(AF41/AA41,4),"")) | AF41: =IF(AA41<>"",$P41,"")
B42: Subtotal | C42: =TEXT(A$38,)&" US$" -> Provincia Puerto Inca Huanuco US$ | O42: =SUM(O39:O41) -> 6049379.8 | P42: =SUM(P39:P41) -> 907406.96 | Q42: =SUM(Q39:Q41) -> 907406.96 | S42: =SUM(S39:S41) -> 0 | U42: =SUM(U39:U41) -> 88352 | V42: =SUM(V39:V41) -> 5902337.6 | W42: =SUM(W39:W41) -> 2945.1 | X42: =ROUND(V42/U42,4) -> 66.8048 | Y42: =ROUND(Z42/U42,4) -> 10.0207 | Z42: =SUM(Z39:Z41) -> 885350.63 | AA42: =SUM(AA39:AA41) -> 0 | AB42: =SUM(AB39:AB41) -> 0 | AC42: =SUM(AC39:AC41) -> 0 | AD42: =IF(AA42=0,0,ROUND(AB42/AA42,4)) -> 0 | AE42: =IF(AA42=0,0,ROUND(AF42/AA42,4)) -> 0 | AF42: =SUM(AF39:AF41) -> 0 | AG42: =P42-Z42-AF42 -> 22056.33
C43: =TEXT(A$38,)&" S/." -> Provincia Puerto Inca Huanuco S/. | P43: =ROUND($F$1*P42,2) -> 0 | Q43: =ROUND($F$1*Q42,2) -> 0 | S43: =ROUND($F$1*S42,2) -> 0
A44: Loreto / Ucayali | Q44: Loreto | S44: Ucayali
A45: - | B45: 31-E | C45: Licencia | D45: Mes | E45: F2 | F45: Bls | N45: 3.72 | O45: =ROUND(G45*I45,2)+ROUND(H45*J45,2)-K45-L45-M45-N45 -> -3.72 | P45: =ROUND(18.75%*O45,2) -> -0.7 | Q45: =ROUND($O45*R45,2) -> -0.56 | R45: 0.15 | S45: =ROUND($O45*T45,2) -> -0.14 | T45: 0.0375 | U45: =IF($F45&"/Día"=W$9,SUM($G45:$H45),"") -> 0 | V45: =IF(U45<>"",$O45,"") -> -3.72 | W45: =IF($F45&"/Día"=W$9,ROUND(U45/$W$1,1),"") -> 0 | X45: =IF(U45=0,0,IF($F45&"/Día"=W$9,ROUND(V45/U45,4),"")) -> 0 | Y45: =IF(U45=0,0,IF($F45&"/Día"=W$9,ROUND(Z45/U45,4),"")) -> 0 | Z45: =IF(U45<>"",$P45,"") -> -0.7 | AA45: =IF($F45&"/Día"=AC$9,SUM($G45:$H45),"") | AB45: =IF(AA45<>"",$O45,"") | AC45: =IF($F45&"/Día"=AC$9,ROUND(AA45/$W$1,1),"") | AD45: =IF(AA45=0,0,IF($F45&"/Día"=AC$9,ROUND(AB45/AA45,4),"")) | AE45: =IF(AA45=0,0,IF($F45&"/Día"=AC$9,ROUND(AF45/AA45,4),"")) | AF45: =IF(AA45<>"",$P45,"")
A46: - | B46: 192 | C46: Servicios | D46: Mes | E46: F1 | F46: Bls | H46: 258757 | J46: 56.3849 | M46: 11586.45 | N46: 10503.2 | O46: =ROUND(G46*I46,2)+ROUND(H46*J46,2)-K46-L46-M46-N46 -> 14567898 | P46: =ROUND(18.75%*O46,2) -> 2731480.9 | Q46: =ROUND($O46*R46,2) -> 2185184.7 | R46: 0.15 | S46: =ROUND($O46*T46,2) -> 546296.17 | T46: 0.0375 | U46: =IF($F46&"/Día"=W$9,SUM($G46:$H46),"") -> 258757 | V46: =IF(U46<>"",$O46,"") -> 14567898 | W46: =IF($F46&"/Día"=W$9,ROUND(U46/$W$1,1),"") -> 8625.2 | X46: =IF(U46=0,0,IF($F46&"/Día"=W$9,ROUND(V46/U46,4),"")) -> 56.2995 | Y46: =IF(U46=0,0,IF($F46&"/Día"=W$9,ROUND(Z46/U46,4),"")) -> 10.5562 | Z46: =IF(U46<>"",$P46,"") -> 2731480.9 | AA46: =IF($F46&"/Día"=AC$9,SUM($G46:$H46),"") | AB46: =IF(AA46<>"",$O46,"") | AC46: =IF($F46&"/Día"=AC$9,ROUND(AA46/$W$1,1),"") | AD46: =IF(AA46=0,0,IF($F46&"/Día"=AC$9,ROUND(AB46/AA46,4),"")) | AE46: =IF(AA46=0,0,IF($F46&"/Día"=AC$9,ROUND(AF46/AA46,4),"")) | AF46: =IF(AA46<>"",$P46,"")
A47: - | B47: 8 | C47: Licencia | D47: Quincena | E47: F2 | F47: Bls | G47: 87029 | H47: 95302 | I47: 51.5364 | J47: 55.1583 | N47: 12506.51 | O47: =ROUND(G47*I47,2)+ROUND(H47*J47,2)-K47-L47-M47-N47 -> 9729351.2 | P47: =ROUND(18.75%*O47,2) -> 1824253.3 | Q47: =ROUND($O47*R47,2) -> 1459402.7 | R47: 0.15 | S47: =ROUND($O47*T47,2) -> 364850.67 | T47: 0.0375 | U47: =IF($F47&"/Día"=W$9,SUM($G47:$H47),"") -> 182331 | V47: =IF(U47<>"",$O47,"") -> 9729351.2 | W47: =IF($F47&"/Día"=W$9,ROUND(U47/$W$1,1),"") -> 6077.7 | X47: =IF(U47=0,0,IF($F47&"/Día"=W$9,ROUND(V47/U47,4),"")) -> 53.3609 | Y47: =IF(U47=0,0,IF($F47&"/Día"=W$9,ROUND(Z47/U47,4),"")) -> 10.0052 | Z47: =IF(U47<>"",$P47,"") -> 1824253.3 | AA47: =IF($F47&"/Día"=AC$9,SUM($G47:$H47),"") | AB47: =IF(AA47<>"",$O47,"") | AC47: =IF($F47&"/Día"=AC$9,ROUND(AA47/$W$1,1),"") | AD47: =IF(AA47=0,0,IF($F47&"/Día"=AC$9,ROUND(AB47/AA47,4),"")) | AE47: =IF(AA47=0,0,IF($F47&"/Día"=AC$9,ROUND(AF47/AA47,4),"")) | AF47: =IF(AA47<>"",$P47,"")
A48: - | B48: 31-B | C48: Licencia | D48: Quincena | E48: F2 | F48: Bls | N48: 4.76 | O48: =ROUND(G48*I48,2)+ROUND(H48*J48,2)-K48-L48-M48-N48 -> -4.76 | P48: =ROUND(18.75%*O48,2) -> -0.89 | Q48: =ROUND($O48*R48,2) -> -0.71 | R48: 0.15 | S48: =ROUND($O48*T48,2) -> -0.18 | T48: 0.0375 | U48: =IF($F48&"/Día"=W$9,SUM($G48:$H48),"") -> 0 | V48: =IF(U48<>"",$O48,"") -> -4.76 | W48: =IF($F48&"/Día"=W$9,ROUND(U48/$W$1,1),"") -> 0 | X48: =IF(U48=0,0,IF($F48&"/Día"=W$9,ROUND(V48/U48,4),"")) -> 0 | Y48: =IF(U48=0,0,IF($F48&"/Día"=W$9,ROUND(Z48/U48,4),"")) -> 0 | Z48: =IF(U48<>"",$P48,"") -> -0.89 | AA48: =IF($F48&"/Día"=AC$9,SUM($G48:$H48),"") | AB48: =IF(AA48<>"",$O48,"") | AC48: =IF($F48&"/Día"=AC$9,ROUND(AA48/$W$1,1),"") | AD48: =IF(AA48=0,0,IF($F48&"/Día"=AC$9,ROUND(AB48/AA48,4),"")) | AE48: =IF(AA48=0,0,IF($F48&"/Día"=AC$9,ROUND(AF48/AA48,4),"")) | AF48: =IF(AA48<>"",$P48,"")
A49: - | B49: 31-C GAS | C49: Licencia | D49: Quincena | E49: F2 | F49: MM BTU | G49: 11653.68 | H49: 45676.72 | I49: 3.7418 | J49: 3.742 | N49: 1170.43 | O49: =ROUND(G49*I49,2)+ROUND(H49*J49,2)-K49-L49-M49-N49 -> 213357.6 | P49: =ROUND(18.75%*O49,2) -> 40004.55 | Q49: =ROUND($O49*R49,2) -> 8000.91 | R49: 0.0375 | S49: =ROUND($O49*T49,2) -> 32003.64 | T49: 0.15 | U49: =IF($F49&"/Día"=W$9,SUM($G49:$H49),"") | V49: =IF(U49<>"",$O49,"") | W49: =IF($F49&"/Día"=W$9,ROUND(U49/$W$1,1),"") | X49: =IF(U49=0,0,IF($F49&"/Día"=W$9,ROUND(V49/U49,4),"")) | Y49: =IF(U49=0,0,IF($F49&"/Día"=W$9,ROUND(Z49/U49,4),"")) | Z49: =IF(U49<>"",$P49,"") | AA49: =IF($F49&"/Día"=AC$9,SUM($G49:$H49),"") -> 57330.4 | AB49: =IF(AA49<>"",$O49,"") -> 213357.6 | AC49: =IF($F49&"/Día"=AC$9,ROUND(AA49/$W$1,1),"") -> 1911 | AD49: =IF(AA49=0,0,IF($F49&"/Día"=AC$9,ROUND(AB49/AA49,4),"")) -> 3.7215 | AE49: =IF(AA49=0,0,IF($F49&"/Día"=AC$9,ROUND(AF49/AA49,4),"")) -> 0.6978 | AF49: =IF(AA49<>"",$P49,"") -> 40004.55
A50: - | B50: 31-C LGN (*) | C50: Licencia | D50: Quincena | E50: F3 | F50: Bls | G50: 18290 | H50: 18612 | I50: 54.8279 | J50: 56.9789 | N50: 5297.01 | O50: =ROUND(G50*I50,2)+ROUND(H50*J50,2)-K50-L50-M50-N50 -> 2057996.6 | P50: =ROUND(18.75%*O50,2) -> 385874.36 | Q50: =ROUND($O50*R50,2) -> 77174.87 | R50: 0.0375 | S50: =ROUND($O50*T50,2) -> 308699.49 | T50: 0.15 | U50: =IF($F50&"/Día"=W$9,SUM($G50:$H50),"") -> 36902 | V50: =IF(U50<>"",$O50,"") -> 2057996.6 | W50: =IF($F50&"/Día"=W$9,ROUND(U50/$W$1,1),"") -> 1230.1 | X50: =IF(U50=0,0,IF($F50&"/Día"=W$9,ROUND(V50/U50,4),"")) -> 55.7692 | Y50: =IF(U50=0,0,IF($F50&"/Día"=W$9,ROUND(Z50/U50,4),"")) -> 10.4567 | Z50: =IF(U50<>"",$P50,"") -> 385874.36 | AA50: =IF($F50&"/Día"=AC$9,SUM($G50:$H50),"") | AB50: =IF(AA50<>"",$O50,"") | AC50: =IF($F50&"/Día"=AC$9,ROUND(AA50/$W$1,1),"") | AD50: =IF(AA50=0,0,IF($F50&"/Día"=AC$9,ROUND(AB50/AA50,4),"")) | AE50: =IF(AA50=0,0,IF($F50&"/Día"=AC$9,ROUND(AF50/AA50,4),"")) | AF50: =IF(AA50<>"",$P50,"")
A51: - | B51: 31-C COND | C51: Licencia | D51: Quincena | E51: F2 | F51: Bls | O51: =ROUND(G51*I51,2)+ROUND(H51*J51,2)-K51-L51-M51-N51 -> 0 | P51: =ROUND(18.75%*O51,2) -> 0 | Q51: =ROUND($O51*R51,2) -> 0 | R51: 0.0375 | S51: =ROUND($O51*T51,2) -> 0 | T51: 0.15 | U51: =IF($F51&"/Día"=W$9,SUM($G51:$H51),"") -> 0 | V51: =IF(U51<>"",$O51,"") -> 0 | W51: =IF($F51&"/Día"=W$9,ROUND(U51/$W$1,1),"") -> 0 | X51: =IF(U51=0,0,IF($F51&"/Día"=W$9,ROUND(V51/U51,4),"")) -> 0 | Y51: =IF(U51=0,0,IF($F51&"/Día"=W$9,ROUND(Z51/U51,4),"")) -> 0 | Z51: =IF(U51<>"",$P51,"") -> 0 | AA51: =IF($F51&"/Día"=AC$9,SUM($G51:$H51),"") | AB51: =IF(AA51<>"",$O51,"") | AC51: =IF($F51&"/Día"=AC$9,ROUND(AA51/$W$1,1),"") | AD51: =IF(AA51=0,0,IF($F51&"/Día"=AC$9,ROUND(AB51/AA51,4),"")) | AE51: =IF(AA51=0,0,IF($F51&"/Día"=AC$9,ROUND(AF51/AA51,4),"")) | AF51: =IF(AA51<>"",$P51,"")
A52: - | B52: 102 | C52: Licencia | D52: Quincena | E52: F2 | F52: Bls | O52: =ROUND(G52*I52,2)+ROUND(H52*J52,2)-K52-L52-M52-N52 -> 0 | P52: =ROUND(18.75%*O52,2) -> 0 | Q52: =P52-S52 -> 0 | R52: 0.15 | S52: =ROUND($O52*T52,2) -> 0 | T52: 0.0375 | U52: =IF($F52&"/Día"=W$9,SUM($G52:$H52),"") -> 0 | V52: =IF(U52<>"",$O52,"") -> 0 | W52: =IF($F52&"/Día"=W$9,ROUND(U52/$W$1,1),"") -> 0 | X52: =IF(U52=0,0,IF($F52&"/Día"=W$9,ROUND(V52/U52,4),"")) -> 0 | Y52: =IF(U52=0,0,IF($F52&"/Día"=W$9,ROUND(Z52/U52,4),"")) -> 0 | Z52: =IF(U52<>"",$P52,"") -> 0 | AA52: =IF($F52&"/Día"=AC$9,SUM($G52:$H52),"") | AB52: =IF(AA52<>"",$O52,"") | AC52: =IF($F52&"/Día"=AC$9,ROUND(AA52/$W$1,1),"") | AD52: =IF(AA52=0,0,IF($F52&"/Día"=AC$9,ROUND(AB52/AA52,4),"")) | AE52: =IF(AA52=0,0,IF($F52&"/Día"=AC$9,ROUND(AF52/AA52,4),"")) | AF52: =IF(AA52<>"",$P52,"")
A53: - | B53: 95 | C53: Licencia | D53: Quincena | E53: F2 | F53: Bls | O53: =ROUND(G53*I53,2)+ROUND(H53*J53,2)-K53-L53-M53-N53 -> 0 | P53: =ROUND(18.75%*O53,2) -> 0 | Q53: =P53-S53 -> 0 | R53: 0.15 | S53: =ROUND($O53*T53,2) -> 0 | T53: 0.0375 | U53: =IF($F53&"/Día"=W$9,SUM($G53:$H53),"") -> 0 | V53: =IF(U53<>"",$O53,"") -> 0 | W53: =IF($F53&"/Día"=W$9,ROUND(U53/$W$1,1),"") -> 0 | X53: =IF(U53=0,0,IF($F53&"/Día"=W$9,ROUND(V53/U53,4),"")) -> 0 | Y53: =IF(U53=0,0,IF($F53&"/Día"=W$9,ROUND(Z53/U53,4),"")) -> 0 | Z53: =IF(U53<>"",$P53,"") -> 0 | AA53: =IF($F53&"/Día"=AC$9,SUM($G53:$H53),"") | AB53: =IF(AA53<>"",$O53,"") | AC53: =IF($F53&"/Día"=AC$9,ROUND(AA53/$W$1,1),"") | AD53: =IF(AA53=0,0,IF($F53&"/Día"=AC$9,ROUND(AB53/AA53,4),"")) | AE53: =IF(AA53=0,0,IF($F53&"/Día"=AC$9,ROUND(AF53/AA53,4),"")) | AF53: =IF(AA53<>"",$P53,"")
A54: - | B54: 67 | C54: Licencia | D54: Quincena | E54: F2 | F54: Bls | O54: =ROUND(G54*I54,2)+ROUND(H54*J54,2)-K54-L54-M54-N54 -> 0 | P54: =ROUND(18.75%*O54,2) -> 0 | Q54: =P54-S54 -> 0 | R54: 0.15 | S54: =ROUND($O54*T54,2) -> 0 | T54: 0.0375 | U54: =IF($F54&"/Día"=W$9,SUM($G54:$H54),"") -> 0 | V54: =IF(U54<>"",$O54,"") -> 0 | W54: =IF($F54&"/Día"=W$9,ROUND(U54/$W$1,1),"") -> 0 | X54: =IF(U54=0,0,IF($F54&"/Día"=W$9,ROUND(V54/U54,4),"")) -> 0 | Y54: =IF(U54=0,0,IF($F54&"/Día"=W$9,ROUND(Z54/U54,4),"")) -> 0 | Z54: =IF(U54<>"",$P54,"") -> 0 | AA54: =IF($F54&"/Día"=AC$9,SUM($G54:$H54),"") | AB54: =IF(AA54<>"",$O54,"") | AC54: =IF($F54&"/Día"=AC$9,ROUND(AA54/$W$1,1),"") | AD54: =IF(AA54=0,0,IF($F54&"/Día"=AC$9,ROUND(AB54/AA54,4),"")) | AE54: =IF(AA54=0,0,IF($F54&"/Día"=AC$9,ROUND(AF54/AA54,4),"")) | AF54: =IF(AA54<>"",$P54,"")
A55: - | B55: Ajustes meses anteriores (3) | O55: =O447 -> 172254.86 | P55: =P447 -> 32297.79 | Q55: =Q447 -> 25838.23 | S55: =S447 -> 6459.56 | U55: =IF($F55&"/Día"=W$9,SUM($G55:$H55),"") | V55: =IF(U55<>"",$O55,"") | W55: =IF($F55&"/Día"=W$9,ROUND(U55/$W$1,1),"") | X55: =IF(U55=0,0,IF($F55&"/Día"=W$9,ROUND(V55/U55,4),"")) | Y55: =IF(U55=0,0,IF($F55&"/Día"=W$9,ROUND(Z55/U55,4),"")) | Z55: =IF(U55<>"",$P55,"") | AA55: =IF($F55&"/Día"=AC$9,SUM($G55:$H55),"") | AB55: =IF(AA55<>"",$O55,"") | AC55: =IF($F55&"/Día"=AC$9,ROUND(AA55/$W$1,1),"") | AD55: =IF(AA55=0,0,IF($F55&"/Día"=AC$9,ROUND(AB55/AA55,4),"")) | AE55: =IF(AA55=0,0,IF($F55&"/Día"=AC$9,ROUND(AF55/AA55,4),"")) | AF55: =IF(AA55<>"",$P55,"")
B56: Subtotal | C56: =TEXT(A$44,)&" US$" -> Loreto / Ucayali US$ | O56: =SUM(O45:O55) -> 26740850 | P56: =SUM(P45:P55) -> 5013909.3 | Q56: =SUM(Q45:Q55) -> 3755600.1 | S56: =SUM(S45:S55) -> 1258309.2 | U56: =SUM(U45:U55) -> 477990 | V56: =SUM(V45:V55) -> 26355237 | W56: =SUM(W45:W55) -> 15933 | X56: =ROUND(V56/U56,4) -> 55.1376 | Y56: =ROUND(Z56/U56,4) -> 10.3383 | Z56: =SUM(Z45:Z55) -> 4941607 | AA56: =SUM(AA45:AA55) -> 57330.4 | AB56: =SUM(AB45:AB55) -> 213357.6 | AC56: =SUM(AC45:AC55) -> 1911 | AD56: =ROUND(AB56/AA56,4) -> 3.7215 | AE56: =ROUND(AF56/AA56,4) -> 0.6978 | AF56: =SUM(AF45:AF55) -> 40004.55 | AG56: =P56-Z56-AF56 -> 32297.79
C57: =TEXT(A$44,)&" S/." -> Loreto / Ucayali S/. | P57: =ROUND($F$1*P56,2) -> 0 | Q57: =ROUND($F$1*Q56,2) -> 0 | S57: =ROUND($F$1*S56,2) -> 0
A58: Cusco | P58: V. Regalías | Q58: Cusco
A59: - | B59: 88 LGN | C59: Licencia | D59: Quincena | E59: F4 | F59: Bls | G59: 704947 | H59: 757358 | I59: 40.6421 | J59: 44.0333 | O59: =G59*I59+H59*J59 -> 61999498 | P59: =ROUND(37.24%*(G59*I59+H59*J59),2) -> 23088613 | Q59: =ROUND(R59*P59,2) -> 11544307 | R59: 0.5 | U59: =IF($F59&"/Día"=W$9,SUM($G59:$H59),"") -> 1462305 | V59: =IF(U59<>"",$O59,"") -> 61999498 | W59: =IF($F59&"/Día"=W$9,ROUND(U59/$W$1,1),"") -> 48743.5 | X59: =IF(U59=0,0,IF($F59&"/Día"=W$9,ROUND(V59/U59,4),"")) -> 42.3985 | Y59: =IF(U59=0,0,IF($F59&"/Día"=W$9,ROUND(Z59/U59,4),"")) -> 7.8946 | Z59: =IF(U59<>"",$Q59,"") -> 11544307 | AA59: =IF($F59&"/Día"=AC$9,SUM($G59:$H59),"") | AB59: =IF(AA59<>"",$O59,"") | AC59: =IF($F59&"/Día"=AC$9,ROUND(AA59/$W$1,1),"") | AD59: =IF(AA59=0,0,IF($F59&"/Día"=AC$9,ROUND(AB59/AA59,4),"")) | AE59: =IF(AA59=0,0,IF($F59&"/Día"=AC$9,ROUND(AF59/AA59,4),"")) | AF59: =IF(AA59<>"",$Q59,"")
A60: - | B60: 88 GAS | C60: Licencia | D60: Quincena | E60: F4 | F60: MM BTU | G60: 7520607 | H60: 8539048.7 | I60: 2.0621 | J60: 2.0621 | O60: =G60*I60+H60*J60 -> 33116616 | P60: =ROUND(37.24%*(G60*I60+H60*J60),2) -> 12332628 | Q60: =ROUND(R60*P60,2) -> 6166313.9 | R60: 0.5 | U60: =IF($F60&"/Día"=W$9,SUM($G60:$H60),"") | V60: =IF(U60<>"",$O60,"") | W60: =IF($F60&"/Día"=W$9,ROUND(U60/$W$1,1),"") | X60: =IF(U60=0,0,IF($F60&"/Día"=W$9,ROUND(V60/U60,4),"")) | Y60: =IF(U60=0,0,IF($F60&"/Día"=W$9,ROUND(Z60/U60,4),"")) | Z60: =IF(U60<>"",$Q60,"") | AA60: =IF($F60&"/Día"=AC$9,SUM($G60:$H60),"") -> 16059656 | AB60: =IF(AA60<>"",$O60,"") -> 33116616 | AC60: =IF($F60&"/Día"=AC$9,ROUND(AA60/$W$1,1),"") -> 535321.9 | AD60: =IF(AA60=0,0,IF($F60&"/Día"=AC$9,ROUND(AB60/AA60,4),"")) -> 2.0621 | AE60: =IF(AA60=0,0,IF($F60&"/Día"=AC$9,ROUND(AF60/AA60,4),"")) -> 0.384 | AF60: =IF(AA60<>"",$Q60,"") -> 6166313.9
A61: - | B61: 88 GAS -Mlocal | C61: Licencia | D61: Quincena | E61: F4 | F61: MM BTU | G61: 30736.478 | H61: 31362.119 | I61: 2.8684 | J61: 2.8684 | O61: =G61*I61+H61*J61 -> 178123.62 | P61: =ROUND(37.24%*O61,2) -> 66333.23 | Q61: =ROUND(R61*P61,2) -> 33166.62 | R61: 0.5 | U61: =IF($F61&"/Día"=W$9,SUM($G61:$H61),"") | V61: =IF(U61<>"",$O61,"") | W61: =IF($F61&"/Día"=W$9,ROUND(U61/$W$1,1),"") | X61: =IF(U61=0,0,IF($F61&"/Día"=W$9,ROUND(V61/U61,4),"")) | Y61: =IF(U61=0,0,IF($F61&"/Día"=W$9,ROUND(Z61/U61,4),"")) | Z61: =IF(U61<>"",$Q61,"") | AA61: =IF($F61&"/Día"=AC$9,SUM($G61:$H61),"") -> 62098.597 | AB61: =IF(AA61<>"",$O61,"") -> 178123.62 | AC61: =IF($F61&"/Día"=AC$9,ROUND(AA61/$W$1,1),"") -> 2070 | AD61: =IF(AA61=0,0,IF($F61&"/Día"=AC$9,ROUND(AB61/AA61,4),"")) -> 2.8684 | AE61: =IF(AA61=0,0,IF($F61&"/Día"=AC$9,ROUND(AF61/AA61,4),"")) -> 0.5341 | AF61: =IF(AA61<>"",$Q61,"") -> 33166.62
A62: - | B62: 88 GAS -PM | C62: Licencia | D62: Quincena | E62: F4 | F62: MM BTU | G62: 878493.54 | H62: 926493.38 | I62: 1.821 | J62: 2.218 | O62: =G62*I62+H62*J62 -> 3654699.1 | P62: =ROUND(38%*G62*I62,2)+ROUND(38%*H62*J62,2) -> 1388785.6 | Q62: =ROUND(R62*P62,2) -> 694392.82 | R62: 0.5 | U62: =IF($F62&"/Día"=W$9,SUM($G62:$H62),"") | V62: =IF(U62<>"",$O62,"") | W62: =IF($F62&"/Día"=W$9,ROUND(U62/$W$1,1),"") | X62: =IF(U62=0,0,IF($F62&"/Día"=W$9,ROUND(V62/U62,4),"")) | Y62: =IF(U62=0,0,IF($F62&"/Día"=W$9,ROUND(Z62/U62,4),"")) | Z62: =IF(U62<>"",$Q62,"") | AA62: =IF($F62&"/Día"=AC$9,SUM($G62:$H62),"") -> 1804986.9 | AB62: =IF(AA62<>"",$O62,"") -> 3654699.1 | AC62: =IF($F62&"/Día"=AC$9,ROUND(AA62/$W$1,1),"") -> 60166.2 | AD62: =IF(AA62=0,0,IF($F62&"/Día"=AC$9,ROUND(AB62/AA62,4),"")) -> 2.0248 | AE62: =IF(AA62=0,0,IF($F62&"/Día"=AC$9,ROUND(AF62/AA62,4),"")) -> 0.3847 | AF62: =IF(AA62<>"",$Q62,"") -> 694392.82
A63: - | B63: 56 LGN | C63: Licencia | D63: Quincena | E63: F4 | F63: Bls | G63: 419837 | H63: 448419 | I63: 40.6415 | J63: 44.0327 | O63: =G63*I63+H63*J63 -> 36807905 | P63: =ROUND(40%*G63*I63,2)+ROUND(40%*H63*J63,2) -> 14723162 | Q63: =ROUND(R63*P63,2) -> 7361581 | R63: 0.5 | U63: =IF($F63&"/Día"=W$9,SUM($G63:$H63),"") -> 868256 | V63: =IF(U63<>"",$O63,"") -> 36807905 | W63: =IF($F63&"/Día"=W$9,ROUND(U63/$W$1,1),"") -> 28941.9 | X63: =IF(U63=0,0,IF($F63&"/Día"=W$9,ROUND(V63/U63,4),"")) -> 42.3929 | Y63: =IF(U63=0,0,IF($F63&"/Día"=W$9,ROUND(Z63/U63,4),"")) -> 8.4786 | Z63: =IF(U63<>"",$Q63,"") -> 7361581 | AA63: =IF($F63&"/Día"=AC$9,SUM($G63:$H63),"") | AB63: =IF(AA63<>"",$O63,"") | AC63: =IF($F63&"/Día"=AC$9,ROUND(AA63/$W$1,1),"") | AD63: =IF(AA63=0,0,IF($F63&"/Día"=AC$9,ROUND(AB63/AA63,4),"")) | AE63: =IF(AA63=0,0,IF($F63&"/Día"=AC$9,ROUND(AF63/AA63,4),"")) | AF63: =IF(AA63<>"",$Q63,"")
A64: - | B64: 56 GAS | C64: Licencia | D64: Quincena | E64: F4 | F64: MM BTU | G64: 6224075.9 | H64: 6695796.4 | I64: 1.821 | J64: 2.218 | O64: =G64*I64+H64*J64 -> 26185319 | P64: =ROUND(38%*G64*I64,2)+ROUND(38%*H64*J64,2) -> 9950421.1 | Q64: =ROUND(R64*P64,2) -> 4975210.5 | R64: 0.5 | U64: =IF($F64&"/Día"=W$9,SUM($G64:$H64),"") | V64: =IF(U64<>"",$O64,"") | W64: =IF($F64&"/Día"=W$9,ROUND(U64/$W$1,1),"") | X64: =IF(U64=0,0,IF($F64&"/Día"=W$9,ROUND(V64/U64,4),"")) | Y64: =IF(U64=0,0,IF($F64&"/Día"=W$9,ROUND(Z64/U64,4),"")) | Z64: =IF(U64<>"",$Q64,"") | AA64: =IF($F64&"/Día"=AC$9,SUM($G64:$H64),"") -> 12919872 | AB64: =IF(AA64<>"",$O64,"") -> 26185319 | AC64: =IF($F64&"/Día"=AC$9,ROUND(AA64/$W$1,1),"") -> 430662.4 | AD64: =IF(AA64=0,0,IF($F64&"/Día"=AC$9,ROUND(AB64/AA64,4),"")) -> 2.0267 | AE64: =IF(AA64=0,0,IF($F64&"/Día"=AC$9,ROUND(AF64/AA64,4),"")) -> 0.3851 | AF64: =IF(AA64<>"",$Q64,"") -> 4975210.5
A65: - | B65: 56 GAS-Mlocal | C65: Licencia | D65: Quincena | E65: F4 | F65: MM BTU | G65: 249670.41 | H65: 262965.1 | I65: 1.8303 | J65: 1.8303 | O65: =G65*I65+H65*J65 -> 938276.78 | P65: =ROUND(37.24%*(G65*I65+H65*J65),2) -> 349414.27 | Q65: =ROUND(R65*P65,2) -> 174707.14 | R65: 0.5 | U65: =IF($F65&"/Día"=W$9,SUM($G65:$H65),"") | V65: =IF(U65<>"",$O65,"") | W65: =IF($F65&"/Día"=W$9,ROUND(U65/$W$1,1),"") | X65: =IF(U65=0,0,IF($F65&"/Día"=W$9,ROUND(V65/U65,4),"")) | Y65: =IF(U65=0,0,IF($F65&"/Día"=W$9,ROUND(Z65/U65,4),"")) | Z65: =IF(U65<>"",$Q65,"") | AA65: =IF($F65&"/Día"=AC$9,SUM($G65:$H65),"") -> 512635.51 | AB65: =IF(AA65<>"",$O65,"") -> 938276.78 | AC65: =IF($F65&"/Día"=AC$9,ROUND(AA65/$W$1,1),"") -> 17087.9 | AD65: =IF(AA65=0,0,IF($F65&"/Día"=AC$9,ROUND(AB65/AA65,4),"")) -> 1.8303 | AE65: =IF(AA65=0,0,IF($F65&"/Día"=AC$9,ROUND(AF65/AA65,4),"")) -> 0.3408 | AF65: =IF(AA65<>"",$Q65,"") -> 174707.14
A66: - | B66: 57 LGN | C66: Licencia | D66: Quincena | E66: F4 | F66: Bls | G66: 209845 | H66: 225889 | I66: 36.5524 | J66: 39.9458 | O66: =G66*I66+H66*J66 -> 16693655 | P66: =ROUND(G66*I66,2)*6.42%+ROUND(H66*J66,2)*6.59% -> 1087072.3 | Q66: =ROUND(R66*P66,2) -> 543536.15 | R66: 0.5 | U66: =IF($F66&"/Día"=W$9,SUM($G66:$H66),"") -> 435734 | V66: =IF(U66<>"",$O66,"") -> 16693655 | W66: =IF($F66&"/Día"=W$9,ROUND(U66/$W$1,1),"") -> 14524.5 | X66: =IF(U66=0,0,IF($F66&"/Día"=W$9,ROUND(V66/U66,4),"")) -> 38.3116 | Y66: =IF(U66=0,0,IF($F66&"/Día"=W$9,ROUND(Z66/U66,4),"")) -> 1.2474 | Z66: =IF(U66<>"",$Q66,"") -> 543536.15 | AA66: =IF($F66&"/Día"=AC$9,SUM($G66:$H66),"") | AB66: =IF(AA66<>"",$O66,"") | AC66: =IF($F66&"/Día"=AC$9,ROUND(AA66/$W$1,1),"") | AD66: =IF(AA66=0,0,IF($F66&"/Día"=AC$9,ROUND(AB66/AA66,4),"")) | AE66: =IF(AA66=0,0,IF($F66&"/Día"=AC$9,ROUND(AF66/AA66,4),"")) | AF66: =IF(AA66<>"",$Q66,"")
A67: - | B67: 57 GAS | C67: Licencia | D67: Quincena | E67: F4 | F67: MM BTU | G67: 2998626.1 | H67: 3222616.1 | I67: 2.504 | J67: 2.504 | O67: =G67*I67+H67*J67 -> 15577990 | P67: =ROUND(G67*I67,2)*9.47%+ROUND(H67*J67,2)*9.86% -> 1506706.5 | Q67: =ROUND(R67*P67,2) -> 753353.23 | R67: 0.5 | U67: =IF($F67&"/Día"=W$9,SUM($G67:$H67),"") | V67: =IF(U67<>"",$O67,"") | W67: =IF($F67&"/Día"=W$9,ROUND(U67/$W$1,1),"") | X67: =IF(U67=0,0,IF($F67&"/Día"=W$9,ROUND(V67/U67,4),"")) | Y67: =IF(U67=0,0,IF($F67&"/Día"=W$9,ROUND(Z67/U67,4),"")) | Z67: =IF(U67<>"",$Q67,"") | AA67: =IF($F67&"/Día"=AC$9,SUM($G67:$H67),"") -> 6221242.2 | AB67: =IF(AA67<>"",$O67,"") -> 15577990 | AC67: =IF($F67&"/Día"=AC$9,ROUND(AA67/$W$1,1),"") -> 207374.7 | AD67: =IF(AA67=0,0,IF($F67&"/Día"=AC$9,ROUND(AB67/AA67,4),"")) -> 2.504 | AE67: =IF(AA67=0,0,IF($F67&"/Día"=AC$9,ROUND(AF67/AA67,4),"")) -> 0.1211 | AF67: =IF(AA67<>"",$Q67,"") -> 753353.23
A68: - | B68: Ajustes meses anteriores (4) | O68: =O454 -> 2326688.6 | P68: =P454 -> -127757.11 | Q68: =Q454 -> -63878.55 | U68: =IF($F68&"/Día"=W$9,SUM($G68:$H68),"") | V68: =IF(U68<>"",$O68,"") | W68: =IF($F68&"/Día"=W$9,ROUND(U68/$W$1,1),"") | X68: =IF(U68=0,0,IF($F68&"/Día"=W$9,ROUND(V68/U68,4),"")) | Y68: =IF(U68=0,0,IF($F68&"/Día"=W$9,ROUND(Z68/U68,4),"")) | Z68: =IF(U68<>"",$Q68,"") | AA68: =IF($F68&"/Día"=AC$9,SUM($G68:$H68),"") | AB68: =IF(AA68<>"",$O68,"") | AC68: =IF($F68&"/Día"=AC$9,ROUND(AA68/$W$1,1),"") | AD68: =IF(AA68=0,0,IF($F68&"/Día"=AC$9,ROUND(AB68/AA68,4),"")) | AE68: =IF(AA68=0,0,IF($F68&"/Día"=AC$9,ROUND(AF68/AA68,4),"")) | AF68: =IF(AA68<>"",$Q68,"")
B69: Subtotal | C69: =TEXT(A$58,)&" US$" -> Cusco US$ | G69: =SUM(G64:G65) -> 6473746.3 | H69: =SUM(H64:H65) -> 6958761.5 | O69: =SUM(O59:O68) -> 1.9747877e+08 | P69: =SUM(P59:P68) -> 64365379 | Q69: =SUM(Q59:Q68) -> 32182689 | U69: =SUM(U59:U68) -> 2766295 | V69: =SUM(V59:V68) -> 1.1550106e+08 | W69: =SUM(W59:W68) -> 92209.9 | X69: =ROUND(V69/U69,4) -> 41.753 | Y69: =ROUND(Z69/U69,4) -> 7.0309 | Z69: =SUM(Z59:Z68) -> 19449424 | AA69: =SUM(AA59:AA68) -> 37580491 | AB69: =SUM(AB59:AB68) -> 79651024 | AC69: =SUM(AC59:AC68) -> 1252683.1 | AD69: =ROUND(AB69/AA69,4) -> 2.1195 | AE69: =ROUND(AF69/AA69,4) -> 0.3405 | AF69: =SUM(AF59:AF68) -> 12797144 | AG69: =Q69-Z69-AF69 -> -63878.55
C70: =TEXT(A$58,)&" S/." -> Cusco S/. | G70: =SUMPRODUCT(I64:I65,G64:G65)/SUM(G64:G65) -> 1.8213587 | H70: =SUMPRODUCT(J64:J65,H64:H65)/SUM(H64:H65) -> 2.2033492 | J70: =+N70+M70 -> 0 | Q70: =Q69*F1 -> 0
A71: Total General | G71: =G69*G70 -> 11791014 | H71: =H69*H70 -> 15332581 | I71: =H71+G71 -> 27123595 | J71: =O64+O65 -> 27123595 | K71: =I71-J71 -> 0 | M71: =SUM(M10:M68) -> 11586.45 | N71: =SUM(N10:N68) -> 77732.83 | O71: =O36+O42+O56+O69 -> 2.989216e+08 | P71: =Q69+P56+P42+P36 -> 50976368 | Q71: =Q70+P57+P43+P37 -> 0 | U71: =U36+U42+U56+U69 -> 4553195 | V71: =V36+V42+V56+V69 -> 2.1302929e+08 | W71: =W36+W42+W56+W69 -> 151773.3 | X71: =ROUND(V71/U71,4) -> 46.7868 | Y71: =ROUND(Z71/U71,4) -> 8.2392 | Z71: =Z36+Z42+Z56+Z69 -> 37514629 | AA71: =AA36+AA42+AA56+AA69 -> 39028309 | AB71: =AB36+AB42+AB56+AB69 -> 83269920 | AC71: =AC36+AC42+AC56+AC69 -> 1300943.7 | AD71: =ROUND(AB71/AA71,4) -> 2.1336 | AE71: =ROUND(AF71/AA71,4) -> 0.3453 | AF71: =AF36+AF42+AF56+AF69 -> 13475687 | AG71: =P71-Z71-AF71 -> -13948.14
A73: (*) | B73: Determinación de Canasta de los Líquidos de Gas Natural (VLGNF) | H73: = ( VC * %P + (PB - TF - TT) * (1 - %P)) | O73: =120853382.49+139352381.96+36326849.05-6337.84-11586.45-77732.83+2622270.38 -> 2.9905923e+08 | U73: Regalía 1Q | V73: =6376757.84-V80 -> 5654249 | W73: =+P36 -> 12872363 | X73: Piura / Tumbes
B74: Simbolo | C74: Descripcion | E74: 1ra. Q | F74: 2da. Q | H74: 1ra. Q | U74: Regalía 2Q | V74: =6872699.93-V83 -> 6177558.7 | W74: =+P56 -> 5013909.3 | X74: Loreto / Ucayali
B75: VC | C75: Canasta de Petróleo | H75: ="= ("&TEXT(E75,"0.0000")&" * "&TEXT(E78,"0.00%")&" + ("&TEXT(E76,"0.0000")&" - "&TEXT(E77,"0.0000")&" - "&TEXT(E80,"0.0000")&") * (1 - "&TEXT(E78,"0.00%")&"))" -> = (0.0000 * 0.00% + (0.0000 - 0.0000 - 0.0000) * (1 - 0.00%)) | O75: =+O71-O73 -> -137624.78 | U75: Servicios | V75: 6805097.1 | W75: =+P42 -> 907406.96 | X75: Huanuco
B76: PB | C76: Precio del GLP | H76: =((85.98%*E75+4.4221)*E78+(E76-E77-E80)*(1-E78)) -> 0 | U76: Otras quinc. | V76: =16534.58+15763.21+22056.33 -> 54354.12
B77: TF | C77: Tarifa de Fraccionam. | O77: =32320129.05+1807524.68+1379621.36+920500.01-100926.05 -> 36326849 | V77: =SUM(V73:V76) -> 18691259 | W77: =SUM(W73:W75) -> 18793679 | X77: =V77-W77 -> -102420.03 | Z77: Maple 31-D | AA77: 1Q. Abril
B78: %P | C78: % Contenido Pentanos | H78: 2da. Q | O78: 2622270.4 | U78: Lote 56 1Q | V78: 5651197.2 | Z78: Regalias no pagadas
B79: QLGNF | C79: Volumen de LGN | H79: ="= ("&TEXT(F75,"0.0000")&" * "&TEXT(F78,"0.00%")&" + ("&TEXT(F76,"0.0000")&" - "&TEXT(F77,"0.0000")&" - "&TEXT(F80,"0.0000")&") * (1 - "&TEXT(F78,"0.00%")&"))" -> = (0.0000 * 0.00% + (0.0000 - 0.0000 - 0.0000) * (1 - 0.00%)) | O79: =+O78-O75 -> 2759895.2 | U79: Lote 88 1Q | V79: 8360344.3 | Z79: V. Producción | AA79: Regalías | AB79: Canon/ Particip.
B80: TT | C80: Tarifa de Transporte | H80: =((85.98%*F75+4.4221)*F78+(F76-F77-F80)*(1-F78)) -> 0 | U80: Lote 57 1Q | V80: 722508.82 | Z80: 137745.71 | AA80: 41323.71 | AB80: =+Z80*15% -> 20661.856
U81: Lote 56 2Q | V81: 6860381.4
U82: Lote 88 2Q | V82: 9893093.8
A83: ="AJUSTES PARA "&UPPER(TEXT(E1,"MMMMMMM YYYY")) -> AJUSTES PARA ABRIL 2018 | U83: Lote 57 2Q | V83: 695141.22
V84: =SUM(V78:V83) -> 32182667 | W84: =Q69 -> 32182689 | X84: =V84-W84 -> -22.78
A85: (4) | B85: Ajuste correspondiente de Febrero 2018 (Reporte de Regalía 1ra. Quincena de Marzo 2018) - Liq. 1196
A86: Cusco | D86: Período | E86: Fórmula | F86: Unidades | G86: 1ra. Q | H86: 2da. Q / Mes | I86: 1ra. Q | J86: 2da. Q / Mes | K86: Flete Marítimo | L86: Comercialización | M86: Oleoducto | N86: Fiscalización | O86: Valor Producción | P86: V. Regalías | Q86: Cuzco | V86: =+V73+V78+V79+V80 -> 20388299
A87: - | B87: 56 GAS-Mlocal | C87: Licencia | D87: Calculo Efectuado | F87: MM BTU | G87: 256658.83 | H87: 220308.01 | I87: 1.8294 | J87: 1.8294 | O87: =G87*I87+H87*J87 -> 872563.15 | P87: =ROUND(37.24%*(G87*I87+H87*J87),2) -> 324942.52 | Q87: =ROUND(R87*P87,2) -> 162471.26 | R87: 0.5 | V87: =+V74+V81+V82+V83 -> 23626175
A88: - | B88: =B87 -> 56 GAS-Mlocal | C88: Licencia | D88: Modificación | F88: =F87 -> MM BTU | G88: =+G87 -> 256658.83 | H88: =+H87 -> 220308.01 | I88: 1.8303 | J88: 1.8303 | O88: =G88*I88+H88*J88 -> 872992.42 | P88: =ROUND(37.24%*(G88*I88+H88*J88),2) -> 325102.38 | Q88: =ROUND(R88*P88,2) -> 162551.19 | R88: 0.5 | V88: =+V75 -> 6805097.1
B89: Ajuste | G89: =G88-G87 -> 0 | H89: =H88-H87 -> 0 | I89: =I88-I87 -> 0.0009 | J89: =J88-J87 -> 0.0009 | K89: =K88-K87 -> 0 | L89: =L88-L87 -> 0 | M89: =M88-M87 -> 0 | N89: =N88-N87 -> 0 | ... Q89: =Q88-Q87 -> 79.93 | S89: ok | V89: =SUM(V86:V88) -> 50819571 | X89: =+V89-P71 -> -156796.93
V90: =P71 -> 50976368
B91: Ajuste correspondiente de Febrero 2018 (Reporte de Regalía 1ra. Quincena de Marzo 2018) - Liq. 1196 | V91: =+V89-V90 -> -156796.93
A92: Cusco | D92: Período | E92: Fórmula | F92: Unidades | G92: 1ra. Q | H92: 2da. Q / Mes | I92: 1ra. Q | J92: 2da. Q / Mes | K92: Flete Marítimo | L92: Comercialización | M92: Oleoducto | N92: Fiscalización | O92: Valor Producción | P92: V. Regalías | Q92: Cuzco
A93: - | B93: 57 GAS | C93: Licencia | D93: Quincena | E93: F4 | F93: MM BTU | G93: 3185893.5 | H93: 2793721 | I93: 2.356 | J93: 2.356 | O93: =G93*I93+H93*J93 -> 14087972 | P93: =ROUND(G93*I93,2)*9.8%+ROUND(H93*J93,2)*9.46% -> 1358242.4 | Q93: =ROUND(R93*P93,2) -> 679121.2 | R93: 0.5
A94: - | B94: =B93 -> 57 GAS | C94: Licencia | D94: Modificación | F94: =F93 -> MM BTU | G94: =+G93 -> 3185893.5 | H94: =+H93 -> 2793721 | I94: 2.504 | J94: 2.504 | O94: =G94*I94+H94*J94 -> 14972955 | P94: =ROUND(G94*I94,2)*9.8%+ROUND(H94*J94,2)*9.46% -> 1443564.9 | Q94: =ROUND(R94*P94,2) -> 721782.47 | R94: 0.5
B95: Ajuste | G95: =G94-G93 -> 0 | H95: =H94-H93 -> 0 | I95: =I94-I93 -> 0.148 | J95: =J94-J93 -> 0.148 | K95: =K94-K93 -> 0 | L95: =L94-L93 -> 0 | M95: =M94-M93 -> 0 | N95: =N94-N93 -> 0 | ... Q95: =Q94-Q93 -> 42661.27 | S95: ok
B97: Ajuste correspondiente de Enero 2018 (Reporte de Regalía 1ra. Quincena de Marzo 2018) - Liq. 1196
A98: Cusco | D98: Período | E98: Fórmula | F98: Unidades | G98: 1ra. Q | H98: 2da. Q / Mes | I98: 1ra. Q | J98: 2da. Q / Mes | K98: Flete Marítimo | L98: Comercialización | M98: Oleoducto | N98: Fiscalización | O98: Valor Producción | P98: V. Regalías | Q98: Cuzco
A99: - | B99: 88 GAS | C99: Licencia | D99: Quincena | E99: F4 | F99: MM BTU | G99: 6714461.6 | H99: 6354405.1 | I99: 2.1133 | J99: 2.1133 | O99: =G99*I99+H99*J99 -> 27618436 | P99: =ROUND(37.24%*(G99*I99+H99*J99),2) -> 10285106 | Q99: =ROUND(R99*P99,2) -> 5142552.8 | R99: 0.5
A100: - | B100: =B99 -> 88 GAS | C100: Licencia | D100: Modificación | F100: =F99 -> MM BTU | G100: =+G99 -> 6714461.6 | H100: =+H99 -> 6354405.1 | I100: 2.1038 | J100: 2.1038 | O100: =G100*I100+H100*J100 -> 27494282 | P100: =ROUND(37.24%*(G100*I100+H100*J100),2) -> 10238870 | Q100: =ROUND(R100*P100,2) -> 5119435.2 | R100: 0.5
B101: Ajuste | G101: =G100-G99 -> 0 | H101: =H100-H99 -> 0 | I101: =I100-I99 -> -0.0095 | J101: =J100-J99 -> -0.0095 | K101: =K100-K99 -> 0 | L101: =L100-L99 -> 0 | M101: =M100-M99 -> 0 | N101: =N100-N99 -> 0 | ... Q101: =Q100-Q99 -> -23117.51 | S101: ok
B103: Ajuste correspondiente de Enero 2018 (Reporte de Regalía 1ra. Quincena de Marzo 2018) - Liq. 1196
A104: Cusco | D104: Período | E104: Fórmula | F104: Unidades | G104: 1ra. Q | H104: 2da. Q / Mes | I104: 1ra. Q | J104: 2da. Q / Mes | K104: Flete Marítimo | L104: Comercialización | M104: Oleoducto | N104: Fiscalización | O104: Valor Producción | P104: V. Regalías | Q104: Cuzco
...

Sheet Ene
A1: Período de Cálculo: | E1: 44197 | F1: 3.655
A2: PERUPETRO S.A.
A3: DETERMINACION DEL CANON, SOBRECANON y PARTICIPACION (US$)
A4: Correspondiente a Enero 2021
A5: Tipo de Cambio= 3.655
A7: Localidad | C7: Modalidad de Contrato | D7: Calculo del Canon | F7: Volumen Producción / Venta | I7: Canasta o Valor Venta (US$/Unidad) | K7: Deducción de Gastos para determinación de valor de producción en Punto de Fiscalización (US$) | O7: Valor de la Producción (US$) | P7: Canon y Sobrecanon / Participación (US$)
A8: - Lote | D8: Período | E8: Fórmula | F8: Unidades | G8: 1ra. Q | H8: 2da. Q / Mes | I8: 1ra. Q | J8: 2da. Q / Mes | K8: Flete Marítimo | L8: Comercialización | M8: Oleoducto | N8: Fiscalización | P8: Total | Q8: Localidad 1 | S8: Localidad 2
A9: Piura / Tumbes | Q9: Piura | S9: Tumbes
A10: - | B10: I | C10: Servicios | D10: Mes | E10: F1 | F10: Bls | H10: 17592 | J10: 53.882 | N10: 236.1393 | O10: 947656 | P10: 177685.5 | Q10: 142148.4 | R10: 0.15 | S10: 35537.1 | T10: 0.0375
A11: - | B11: I GAS | C11: Servicios | D11: Mes | E11: F1 | F11: MM BTU | H11: 130347.93 | J11: 3.173 | N11: 661.1928 | O11: 412932.79 | P11: 77424.9 | Q11: 61939.92 | R11: 0.15 | S11: 15484.98 | T11: 0.0375
A12: - | B12: I GAS (T) | C12: Servicios | D12: Mes | E12: F1 | F12: MM BTU | R12: 0.15 | T12: 0.0375
A13: - | B13: II | C13: Licencia | D13: Quincena | E13: F2 | F13: Bls | G13: 6265 | H13: 6586 | I13: 54.5138 | J13: 55.3384 | N13: 607.2196 | O13: 705380.44 | P13: 132258.83 | Q13: 105807.07 | R13: 0.15 | S13: 26451.77 | T13: 0.0375
A14: - | B14: II-GAS | C14: Servicios | D14: Mes | E14: F1 | F14: MM BTU | G14: 26813.92 | H14: 31263 | I14: 2.2439 | J14: 2.2315 | N14: 651.0721 | O14: 129280.07 | P14: 24240.01 | Q14: 19392.01 | R14: 0.15 | S14: 4848 | T14: 0.0375
A15: - | B15: III | C15: Licencia | D15: Quincena | E15: F2 | F15: Bls | G15: 8850 | H15: 9535 | I15: 53.3042 | J15: 54.4598 | N15: 435.1741 | O15: 990581.19 | P15: 185733.97 | Q15: 148587.18 | R15: 0.15 | S15: 37146.79 | T15: 0.0375
A16: - | B16: IV | C16: Licencia | D16: Quincena | E16: F2 | F16: Bls | G16: 28451 | H16: 29677 | I16: 53.3042 | J16: 54.4598 | N16: 1119.9835 | O16: 3131641.3 | P16: 587182.74 | Q16: 469746.19 | R16: 0.15 | S16: 117436.55 | T16: 0.0375
A17: - | B17: IV-GAS | C17: Licencia | D17: Quincena | E17: F2 | F17: MM BTU | G17: 12149.21 | H17: 5383.34 | I17: 3.1615 | J17: 3.1615 | O17: 55429.16 | P17: 10392.97 | Q17: 8314.37 | R17: 0.15 | S17: 2078.59 | T17: 0.0375
A18: - | B18: V | C18: Servicios | D18: Mes | E18: F1 | F18: Bls | H18: 2631 | J18: 53.882 | N18: 512.7639 | O18: 141250.78 | P18: 26484.52 | Q18: 21187.62 | R18: 0.15 | S18: 5296.9 | T18: 0.0375
A19: - | B19: VII/VI | C19: Licencia | D19: Quincena | E19: F2 | F19: Bls | G19: 51835 | H19: 52329 | I19: 52.7542 | J19: 53.9098 | N19: 3123.8059 | O19: 5552436.1 | P19: 1041081.8 | Q19: 832865.41 | R19: 0.15 | S19: 208216.35 | T19: 0.0375
A20: - | B20: VII | C20: Servicios | D20: Mes | E20: F1 | F20: Bls | O20: 0 | P20: 0 | Q20: 0 | R20: 0.15 | S20: 0 | T20: 0.0375
A21: - | B21: VII/VI-GAS | C21: Licencia | D21: Quincena | E21: F2 | F21: MM BTU | G21: 61491.14 | H21: 44546.67 | I21: 2.3734 | J21: 2.3734 | N21: 732.0373 | O21: 250938.1 | P21: 47050.89 | Q21: 37640.72 | R21: 0.15 | S21: 9410.18 | T21: 0.0375
A22: - | B22: IX | C22: Licencia | D22: Quincena | E22: F2 | F22: Bls | G22: 2002 | H22: 2901 | I22: 53.3042 | J22: 54.4598 | N22: 253.008 | O22: 264449.88 | P22: 49584.35 | Q22: 39667.48 | R22: 0.15 | S22: 9916.87 | T22: 0.0375
A23: - | B23: X | C23: Licencia | D23: Quincena | E23: F2 | F23: Bls | G23: 182223 | H23: 191910 | I23: 53.3042 | J23: 54.4598 | N23: 3909.819 | O23: 20160722 | P23: 3780135.3 | Q23: 3024108.2 | R23: 0.15 | S23: 756027.06 | T23: 0.0375
A24: - | B24: X-GAS | C24: Licencia | D24: Mes | E24: F2 | F24: MM BTU | G24: 267428.8 | H24: 266391.19 | I24: 1.8721 | J24: 1.8721 | N24: 772.5171 | O24: 998591.89 | P24: 187235.98 | Q24: 149788.78 | R24: 0.15 | S24: 37447.2 | T24: 0.0375
A25: - | B25: XIV | C25: Licencia | D25: Mes | E25: F2 | F25: Bls | O25: 0 | P25: 0 | Q25: 0 | R25: 0.15 | S25: 0 | T25: 0.0375
A26: - | B26: XV | C26: Licencia | D26: Quincena | E26: F2 | F26: Bls | G26: 397 | H26: 540 | I26: 54.3058 | J26: 54.9224 | N26: 276.6219 | O26: 50940.878 | P26: 9551.41 | Q26: 7641.13 | R26: 0.15 | S26: 1910.28 | T26: 0.0375
A27: - | B27: XIII Crudo | C27: Licencia | D27: Quincena | E27: F2 | F27: Bls | G27: 13785 | H27: 21066 | I27: 51.3242 | J27: 52.4798 | N27: 2624.5352 | O27: 1810419 | P27: 339453.57 | Q27: 271562.86 | R27: 0.15 | S27: 67890.71 | T27: 0.0375
A28: - | B28: XIII COND | C28: Licencia | D28: Quincena | E28: F2 | F28: Bls | O28: 0 | P28: 0 | Q28: 0 | R28: 0.15 | S28: 0 | T28: 0.0375
A29: - | B29: XIII Gas -A | C29: Licencia | D29: Quincena | E29: F2 | F29: MM BTU | G29: 109238.63 | H29: 111420.98 | I29: 1.5 | J29: 1.5 | N29: 1089.6216 | O29: 329899.8 | P29: 61856.21 | Q29: 49484.97 | R29: 0.15 | S29: 12371.24 | T29: 0.0375
A30: - | B30: XIII Gas -B | C30: Licencia | D30: Quincena | E30: F2 | F30: MM BTU | G30: 67408.29 | H30: 100421.55 | I30: 3.2733 | J30: 3.3239 | O30: 554438.75 | P30: 103957.27 | Q30: 83165.81 | R30: 0.15 | S30: 20791.45 | T30: 0.0375
A31: - | B31: XIII Gas Lantera | C31: Licencia | D31: Quincena | E31: F2 | F31: MM BTU | O31: 0 | P31: 0 | Q31: 0 | R31: 0.15 | S31: 0 | T31: 0.0375
A32: - | B32: XIII Gas Expectativa | C32: Licencia | D32: Quincena | E32: F2 | F32: MM BTU | O32: 0 | P32: 0 | Q32: 0 | R32: 0.15 | S32: 0 | T32: 0.0375
A33: - | B33: XIII Gas Paita | C33: Licencia | D33: Quincena | E33: F2 | F33: MM BTU | G33: 1905.46 | H33: 2452.02 | I33: 3.1 | J33: 3.1 | O33: 13508.19 | P33: 2532.79 | Q33: 2026.23 | R33: 0.15 | S33: 506.56 | T33: 0.0375
A34: - | B34: Z-2B | C34: Servicios | D34: Mes | E34: F1 | F34: Bls | H34: 178202 | J34: 55.3215 | N34: 843.3589 | O34: 9857558.6 | P34: 1848292.2 | Q34: 1478633.8 | R34: 0.15 | S34: 369658.45 | T34: 0.0375
A35: - | B35: Z-2B GAS | C35: Servicios | D35: Mes | E35: F1 | F35: MM BTU | H35: 209790.37 | J35: 5.3624 | N35: 745.5306 | O35: 1124234.3 | P35: 210793.94 | Q35: 168635.15 | R35: 0.15 | S35: 42158.79 | T35: 0.0375
A36: - | B36: XX | C36: Licencia | D36: Quincena | E36: F2 | F36: Bls | G36: 198 | H36: 230 | I36: 53.3042 | J36: 54.4598 | N36: 161.9249 | O36: 22918.055 | P36: 4297.14 | Q36: 859.43 | R36: 0.0375 | S36: 3437.71 | T36: 0.15
A37: - | B37: Z1 Crudo | C37: Licencia | D37: Quincena | E37: F2 | F37: Bls | O37: 0 | P37: 0 | Q37: 0 | R37: 0.0375 | S37: 0 | T37: 0.15
A38: - | B38: Z1 Gas | C38: Licencia | D38: Quincena | E38: F2 | F38: MM BTU | O38: 0 | P38: 0 | Q38: 0 | R38: 0.0375 | S38: 0 | T38: 0.15
A39: - | B39: Z-2B - LGN | C39: Servicios | D39: Mes | E39: F1 | F39: Bls | H39: 24340 | J39: 60.0385 | N39: 809.6243 | O39: 1460527.5 | P39: 273848.9 | Q39: 219079.12 | R39: 0.15 | S39: 54769.78 | T39: 0.0375
A40: - | B40: Z-6 | C40: Licencia | D40: Quincena | E40: F2 | F40: MM BTU | O40: 0 | P40: 0 | Q40: 0 | R40: 0.15 | S40: 0 | T40: 0.0375
A41: - | B41: Ajustes meses anteriores (1) | O41: -50344.82 | P41: -9439.67 | Q41: -7551.72 | S41: -1887.93
B42: Subtotal | C42: Piura / Tumbes US$ | O42: 48915390 | P42: 9171635.5 | Q42: 7334730.2 | S42: 1836905.4
C43: Piura / Tumbes S/. | P43: 33522328 | Q43: 26808439 | S43: 6713889.2
A44: Provincia Puerto Inca Huanuco | Q44: Puerto Inca
A45: - | B45: 31-D | C45: Licencia | D45: Quincena | E45: F2 | F45: Bls | O45: 0 | P45: 0 | Q45: 0 | R45: 0.15
A46: - | B46: 131 | C46: Licencia | D46: Quincena | E46: F2 | F46: Bls | G46: 24482 | H46: 23827 | I46: 42.4705 | J46: 43.358 | N46: 3258.7442 | O46: 2069595.1 | P46: 310439.27 | Q46: 310439.27 | R46: 0.15
A47: - | B47: Ajustes meses anteriores (2)
B48: Subtotal | C48: Provincia Puerto Inca Huanuco US$ | O48: 2069595.1 | P48: 310439.27 | Q48: 310439.27 | S48: 0
C49: Provincia Puerto Inca Huanuco S/. | P49: 1134655.5 | Q49: 1134655.5 | S49: 0
A50: Loreto / Ucayali | Q50: Loreto | S50: Ucayali
A51: - | B51: 31-E | C51: Licencia | D51: Mes | E51: F2 | F51: Bls | O51: 0 | P51: 0 | Q51: 0 | R51: 0.15 | S51: 0 | T51: 0.0375
A52: - | B52: 192 | C52: Servicios | D52: Mes | E52: F1 | F52: Bls | O52: 0 | P52: 0 | Q52: 0 | R52: 0.15 | S52: 0 | T52: 0.0375
A53: - | B53: 8 | C53: Licencia | D53: Quincena | E53: F2 | F53: Bls | O53: 0 | P53: 0 | Q53: 0 | R53: 0.15 | S53: 0 | T53: 0.0375
A54: - | B54: 8 - Crudo Corrientes | C54: Licencia | D54: Quincena | E54: F2 | F54: Bls | O54: 0 | P54: 0 | Q54: 0 | R54: 0.15 | S54: 0 | T54: 0.0375
A55: - | B55: 31-B | C55: Licencia | D55: Quincena | E55: F2 | F55: Bls | O55: 0 | P55: 0 | Q55: 0 | R55: 0.15 | S55: 0 | T55: 0.0375
A56: - | B56: 31-C GAS | C56: Licencia | D56: Quincena | E56: F2 | F56: MM BTU | G56: 53261.23 | H56: 868.55 | I56: 3.655 | J56: 3.655 | N56: 408.1848 | O56: 197436.17 | P56: 37019.28 | Q56: 7403.86 | R56: 0.0375 | S56: 29615.42 | T56: 0.15
A57: - | B57: 31-C LGN (*) | C57: Licencia | D57: Quincena | E57: F3 | F57: Bls | G57: 6888 | H57: 7391 | I57: 44.2921 | J57: 44.7044 | N57: 1848.6455 | O57: 633645.55 | P57: 118808.54 | Q57: 23761.71 | R57: 0.0375 | S57: 95046.83 | T57: 0.15
A58: - | B58: 31-C COND | C58: Licencia | D58: Quincena | E58: F2 | F58: Bls | O58: 0 | P58: 0 | Q58: 0 | R58: 0.0375 | S58: 0 | T58: 0.15
A59: - | B59: 102 | C59: Licencia | D59: Quincena | E59: F2 | F59: Bls | O59: 0 | P59: 0 | Q59: 0 | R59: 0.15 | S59: 0 | T59: 0.0375
A60: - | B60: 95 | C60: Licencia | D60: Quincena | E60: F2 | F60: Bls | G60: 141002 | H60: 100506 | I60: 38.0806 | J60: 39.1902 | N60: 4358.4837 | O60: 9303932.5 | P60: 1744487.4 | Q60: 1395589.9 | R60: 0.15 | S60: 348897.47 | T60: 0.0375
A61: - | B61: 67 | C61: Licencia | D61: Quincena | E61: F2 | F61: Bls | O61: 0 | P61: 0 | Q61: 0 | R61: 0.15 | S61: 0 | T61: 0.0375
A62: - | B62: Ajustes meses anteriores (3)
B63: Subtotal | C63: Loreto / Ucayali US$ | O63: 10135014 | P63: 1900315.2 | Q63: 1426755.4 | S63: 473559.72
C64: Loreto / Ucayali S/. | P64: 6945652 | Q64: 5214791.2 | S64: 1730860.8
A65: Cusco | P65: V. Regalías | Q65: Cusco
A66: - | B66: 88 LGN | C66: Licencia | D66: Quincena | E66: F4 | F66: Bls | G66: 730522 | H66: 779045 | I66: 36.2522 | J66: 37.5101 | O66: 55705086 | P66: 20744574 | Q66: 10372287 | R66: 0.5
A67: - | B67: 88 GAS | C67: Licencia | D67: Quincena | E67: F4 | F67: MM BTU | G67: 7784608.5 | H67: 7875338.1 | I67: 2.1198 | J67: 2.1198 | O67: 33195955 | P67: 12362174 | Q67: 6181086.8 | R67: 0.5
A68: - | B68: 88 GAS -Mlocal | C68: Licencia | D68: Quincena | E68: F4 | F68: MM BTU | G68: 26937.95 | H68: 17758.12 | I68: 2.8586 | J68: 2.8586 | O68: 127768.19 | P68: 47580.87 | Q68: 23790.44 | R68: 0.5
A69: - | B69: 88 GAS -PM | C69: Licencia | D69: Quincena | E69: F4 | F69: MM BTU | G69: 906020.25 | H69: 1112851.3 | I69: 12.822 | J69: 2.877 | O69: 14818665 | P69: 5631092.7 | Q69: 2815546.3 | R69: 0.5
A70: - | B70: 56 LGN | C70: Licencia | D70: Quincena | E70: F4 | F70: Bls | G70: 365476 | H70: 410555 | I70: 36.2486 | J70: 37.5153 | O70: 28650087 | P70: 11460035 | Q70: 5730017.5 | R70: 0.5
A71: - | B71: 56 GAS | C71: Licencia | D71: Quincena | E71: F4 | F71: MM BTU | G71: 6235556.5 | H71: 7039503.7 | I71: 12.822 | J71: 2.877 | O71: 1.0020496e+08 | P71: 38077884 | Q71: 19038942 | R71: 0.5
A72: - | B72: 56 GAS-Mlocal | C72: Licencia | D72: Quincena | E72: F4 | F72: MM BTU | G72: 256861.8 | H72: 249661.27 | I72: 1.9232 | J72: 1.9232 | O72: 974145.17 | P72: 362771.66 | Q72: 181385.83 | R72: 0.5
A73: - | B73: 57 LGN | C73: Licencia | D73: Quincena | E73: F4 | F73: Bls | G73: 187265 | H73: 127785 | I73: 32.7227 | J73: 33.9611 | O73: 10467536 | P73: 649063.56 | Q73: 324531.78 | R73: 0.5
A74: - | B74: 57 GAS | C74: Licencia | D74: Quincena | E74: F4 | F74: MM BTU | G74: 3073714.4 | H74: 2077352.7 | I74: 4.134 | J74: 4.134 | O74: 21294511 | P74: 2049013.9 | Q74: 1024506.9 | R74: 0.5
A75: - | B75: Ajustes meses anteriores (4) | O75: 19737332 | P75: 2741107.2 | Q75: 1370553.6
B76: Subtotal | C76: Cusco US$ | G76: 6492418.3 | H76: 7289165 | O76: 2.8517604e+08 | P76: 94125296 | Q76: 47062648
C77: Cusco S/. | G77: 12.390807 | H77: 2.8443314 | Q77: 1.7201398e+08
A78: Total General | H78: 20732801 | I78: 20732801 | J78: 1.011791e+08 | K78: -80446302 | M78: 0 | N78: 29440.008 | O78: 3.4629604e+08 | P78: 58445038 | Q78: 2.1361661e+08
A80: (*) | B80: Determinación de Canasta de los Líquidos de Gas Natural (VLGNF) | H80: = ( VC * %P + (PB - TF - TT) * (1 - %P)) | O80: 3.0994382e+08
B81: Simbolo | C81: Descripcion | E81: 1ra. Q | F81: 2da. Q | H81: 1ra. Q | O81: -36352219
B82: VC | C82: Canasta de Petróleo | E82: 53.7042 | F82: 54.6498 | H82: = (53.7042 * 65.51% + (39.4936 - 0.0000 - 7.1770) * (1 - 65.51%)) | M82: 0.0622 | N82: 0.064199999
B83: PB | C83: Precio del GLP | E83: 39.4936 | F83: 39.257 | H83: 44.292071 | M83: 0.0942 | N83: 0.0989
B84: TF | C84: Tarifa de Fraccionam. | M84: 0.4 | N84: 0.4
B85: %P | C85: % Contenido Pentanos | E85: 0.6551 | F85: 0.6531 | H85: 2da. Q | M85: 0.38
B86: QLGNF | C86: Volumen de LGN | H86: = (54.6498 * 65.31% + (39.2570 - 0.0000 - 7.1770) * (1 - 65.31%))
B87: TT | C87: Tarifa de Transporte | E87: 7.177 | F87: 7.177 | H87: 44.704422

Sheet Ene-2
A1: Período de Cálculo: | E1: 43101 | U1: Días en el mes | W1: =DATE(YEAR(E1),MONTH(E1)+1,1)-DATE(YEAR(E1),MONTH(E1),1) -> 31
A2: PERUPETRO S.A.
A3: DETERMINACION DEL CANON, SOBRECANON y PARTICIPACION (US$)
A4: ="Correspondiente a "&TEXT(E1,"MMMMMMM YYYY") -> Correspondiente a enero 2018
A5: ="Tipo de Cambio= "&TEXT(F1,"0.000") -> Tipo de Cambio= 0.000
A7: Localidad | C7: Modalidad de Contrato | D7: Calculo del Canon | F7: Volumen Producción / Venta | I7: Canasta o Valor Venta (US$/Unidad) | K7: Deducción de Gastos para determinación de valor de producción en Punto de Fiscalización (US$) | O7: Valor de la Producción (US$) | P7: Canon y Sobrecanon / Participación (US$) | U7: Resumen por Petróleo y Condensados | AA7: Resumen por Gas Natural | AG7: Control
A8: - Lote | D8: Período | E8: Fórmula | F8: Unidades | G8: 1ra. Q | H8: 2da. Q / Mes | I8: 1ra. Q | J8: 2da. Q / Mes | K8: Flete Marítimo | L8: Comercialización | M8: Oleoducto | N8: Fiscalización | P8: Total | Q8: Localidad 1 | S8: Localidad 2 | U8: Producción / Venta | X8: Valor Prod | Y8: Valor Canon | AA8: Producción / Venta | AD8: Valor Prod | AE8: Valor Canon | AG8: Total
A9: Piura / Tumbes | Q9: Piura | S9: Tumbes | U9: Bls/Mes | V9: V P (US$) | W9: Bls/Día | X9: US$/Bl | Y9: US$/Bl | Z9: US$ | AA9: MM BTU/Mes | AB9: V P (US$) | AC9: MM BTU/Día | AD9: US$/MM BTU | AE9: US$/MM BTU | AF9: US$ | AG9: Canon
A10: - | B10: I | C10: Servicios | D10: Mes | E10: F1 | F10: Bls | H10: 24582 | J10: 67.0812 | N10: 683.58 | O10: =ROUND(G10*I10,2)+ROUND(H10*J10,2)-K10-L10-M10-N10 -> 1648306.5 | P10: =ROUND(18.75%*O10,2) -> 309057.47 | Q10: =ROUND($O10*R10,2) -> 247245.97 | R10: 0.15 | S10: =ROUND($O10*T10,2) -> 61811.49 | T10: 0.0375 | U10: =IF($F10&"/Día"=W$9,SUM($G10:$H10),"") -> 24582 | V10: =IF(U10<>"",$O10,"") -> 1648306.5 | W10: =IF($F10&"/Día"=W$9,ROUND(U10/$W$1,1),"") -> 793 | X10: =IF(U10=0,0,IF($F10&"/Día"=W$9,ROUND(V10/U10,4),"")) -> 67.0534 | Y10: =IF(U10=0,0,IF($F10&"/Día"=W$9,ROUND(Z10/U10,4),"")) -> 12.5725 | Z10: =IF(U10<>"",$P10,"") -> 309057.47 | AA10: =IF($F10&"/Día"=AC$9,SUM($G10:$H10),"") | AB10: =IF(AA10<>"",$O10,"") | AC10: =IF($F10&"/Día"=AC$9,ROUND(AA10/$W$1,1),"") | AD10: =IF(AA10=0,0,IF($F10&"/Día"=AC$9,ROUND(AB10/AA10,4),"")) | AE10: =IF(AA10=0,0,IF($F10&"/Día"=AC$9,ROUND(AF10/AA10,4),"")) | AF10: =IF(AA10<>"",$P10,"")
A11: - | B11: I GAS | C11: Servicios | D11: Mes | E11: F1 | F11: MM BTU | H11: 253218.78 | J11: 2.9822 | N11: 1914.05 | O11: =ROUND(G11*I11,2)+ROUND(H11*J11,2)-K11-L11-M11-N11 -> 753235 | P11: =ROUND(18.75%*O11,2) -> 141231.56 | Q11: =ROUND($O11*R11,2) -> 112985.25 | R11: 0.15 | S11: =ROUND($O11*T11,2) -> 28246.31 | T11: 0.0375 | U11: =IF($F11&"/Día"=W$9,SUM($G11:$H11),"") | V11: =IF(U11<>"",$O11,"") | W11: =IF($F11&"/Día"=W$9,ROUND(U11/$W$1,1),"") | X11: =IF(U11=0,0,IF($F11&"/Día"=W$9,ROUND(V11/U11,4),"")) | Y11: =IF(U11=0,0,IF($F11&"/Día"=W$9,ROUND(Z11/U11,4),"")) | Z11: =IF(U11<>"",$P11,"") | AA11: =IF($F11&"/Día"=AC$9,SUM($G11:$H11),"") -> 253218.78 | AB11: =IF(AA11<>"",$O11,"") -> 753235 | AC11: =IF($F11&"/Día"=AC$9,ROUND(AA11/$W$1,1),"") -> 8168.3 | AD11: =IF(AA11=0,0,IF($F11&"/Día"=AC$9,ROUND(AB11/AA11,4),"")) -> 2.9746 | AE11: =IF(AA11=0,0,IF($F11&"/Día"=AC$9,ROUND(AF11/AA11,4),"")) -> 0.5577 | AF11: =IF(AA11<>"",$P11,"") -> 141231.56
A12: - | B12: II | C12: Licencia | D12: Quincena | E12: F2 | F12: Bls | G12: 4562 | H12: 4721 | I12: 64.1613 | J12: 65.1575 | N12: 1764.83 | O12: =ROUND(G12*I12,2)+ROUND(H12*J12,2)-K12-L12-M12-N12 -> 598547.58 | P12: =ROUND(18.75%*O12,2) -> 112227.67 | Q12: =ROUND($O12*R12,2) -> 89782.14 | R12: 0.15 | S12: =ROUND($O12*T12,2) -> 22445.53 | T12: 0.0375 | U12: =IF($F12&"/Día"=W$9,SUM($G12:$H12),"") -> 9283 | V12: =IF(U12<>"",$O12,"") -> 598547.58 | W12: =IF($F12&"/Día"=W$9,ROUND(U12/$W$1,1),"") -> 299.5 | X12: =IF(U12=0,0,IF($F12&"/Día"=W$9,ROUND(V12/U12,4),"")) -> 64.4778 | Y12: =IF(U12=0,0,IF($F12&"/Día"=W$9,ROUND(Z12/U12,4),"")) -> 12.0896 | Z12: =IF(U12<>"",$P12,"") -> 112227.67 | AA12: =IF($F12&"/Día"=AC$9,SUM($G12:$H12),"") | AB12: =IF(AA12<>"",$O12,"") | AC12: =IF($F12&"/Día"=AC$9,ROUND(AA12/$W$1,1),"") | AD12: =IF(AA12=0,0,IF($F12&"/Día"=AC$9,ROUND(AB12/AA12,4),"")) | AE12: =IF(AA12=0,0,IF($F12&"/Día"=AC$9,ROUND(AF12/AA12,4),"")) | AF12: =IF(AA12<>"",$P12,"")
A13: - | B13: II-GAS | C13: Servicios | D13: Mes | E13: F1 | F13: MM BTU | G13: 40281.697 | H13: 44653.33 | I13: 2.55 | J13: 2.55 | N13: 1884.53 | O13: =ROUND(G13*I13,2)+ROUND(H13*J13,2)-K13-L13-M13-N13 -> 214699.79 | P13: =ROUND(18.75%*O13,2) -> 40256.21 | Q13: =ROUND($P13*R13/(R13+T13),2) -> 32204.97 | R13: 0.15 | S13: =P13-Q13 -> 8051.24 | T13: 0.0375 | U13: =IF($F13&"/Día"=W$9,SUM($G13:$H13),"") | V13: =IF(U13<>"",$O13,"") | W13: =IF($F13&"/Día"=W$9,ROUND(U13/$W$1,1),"") | X13: =IF(U13=0,0,IF($F13&"/Día"=W$9,ROUND(V13/U13,4),"")) | Y13: =IF(U13=0,0,IF($F13&"/Día"=W$9,ROUND(Z13/U13,4),"")) | Z13: =IF(U13<>"",$P13,"") | AA13: =IF($F13&"/Día"=AC$9,SUM($G13:$H13),"") -> 84935.027 | AB13: =IF(AA13<>"",$O13,"") -> 214699.79 | AC13: =IF($F13&"/Día"=AC$9,ROUND(AA13/$W$1,1),"") -> 2739.8 | AD13: =IF(AA13=0,0,IF($F13&"/Día"=AC$9,ROUND(AB13/AA13,4),"")) -> 2.5278 | AE13: =IF(AA13=0,0,IF($F13&"/Día"=AC$9,ROUND(AF13/AA13,4),"")) -> 0.474 | AF13: =IF(AA13<>"",$P13,"") -> 40256.21
A14: - | B14: III | C14: Licencia | D14: Quincena | E14: F2 | F14: Bls | G14: 11836 | H14: 12495 | I14: 66.7972 | J14: 67.3179 | N14: 1257.31 | O14: =ROUND(G14*I14,2)+ROUND(H14*J14,2)-K14-L14-M14-N14 -> 1630491.5 | P14: =ROUND(18.75%*O14,2) -> 305717.16 | Q14: =ROUND($O14*R14,2) -> 244573.73 | R14: 0.15 | S14: =ROUND($O14*T14,2) -> 61143.43 | T14: 0.0375 | U14: =IF($F14&"/Día"=W$9,SUM($G14:$H14),"") -> 24331 | V14: =IF(U14<>"",$O14,"") -> 1630491.5 | W14: =IF($F14&"/Día"=W$9,ROUND(U14/$W$1,1),"") -> 784.9 | X14: =IF(U14=0,0,IF($F14&"/Día"=W$9,ROUND(V14/U14,4),"")) -> 67.0129 | Y14: =IF(U14=0,0,IF($F14&"/Día"=W$9,ROUND(Z14/U14,4),"")) -> 12.5649 | Z14: =IF(U14<>"",$P14,"") -> 305717.16 | AA14: =IF($F14&"/Día"=AC$9,SUM($G14:$H14),"") | AB14: =IF(AA14<>"",$O14,"") | AC14: =IF($F14&"/Día"=AC$9,ROUND(AA14/$W$1,1),"") | AD14: =IF(AA14=0,0,IF($F14&"/Día"=AC$9,ROUND(AB14/AA14,4),"")) | AE14: =IF(AA14=0,0,IF($F14&"/Día"=AC$9,ROUND(AF14/AA14,4),"")) | AF14: =IF(AA14<>"",$P14,"")
A15: - | B15: IV | C15: Licencia | D15: Quincena | E15: F2 | F15: Bls | G15: 17378 | H15: 20845 | I15: 66.7972 | J15: 67.3179 | N15: 3247.24 | O15: =ROUND(G15*I15,2)+ROUND(H15*J15,2)-K15-L15-M15-N15 -> 2560796.1 | P15: =ROUND(18.75%*O15,2) -> 480149.27 | Q15: =ROUND($O15*R15,2) -> 384119.42 | R15: 0.15 | S15: =ROUND($O15*T15,2) -> 96029.85 | T15: 0.0375 | U15: =IF($F15&"/Día"=W$9,SUM($G15:$H15),"") -> 38223 | V15: =IF(U15<>"",$O15,"") -> 2560796.1 | W15: =IF($F15&"/Día"=W$9,ROUND(U15/$W$1,1),"") -> 1233 | X15: =IF(U15=0,0,IF($F15&"/Día"=W$9,ROUND(V15/U15,4),"")) -> 66.9962 | Y15: =IF(U15=0,0,IF($F15&"/Día"=W$9,ROUND(Z15/U15,4),"")) -> 12.5618 | Z15: =IF(U15<>"",$P15,"") -> 480149.27 | AA15: =IF($F15&"/Día"=AC$9,SUM($G15:$H15),"") | AB15: =IF(AA15<>"",$O15,"") | AC15: =IF($F15&"/Día"=AC$9,ROUND(AA15/$W$1,1),"") | AD15: =IF(AA15=0,0,IF($F15&"/Día"=AC$9,ROUND(AB15/AA15,4),"")) | AE15: =IF(AA15=0,0,IF($F15&"/Día"=AC$9,ROUND(AF15/AA15,4),"")) | AF15: =IF(AA15<>"",$P15,"")
A16: - | B16: V | C16: Servicios | D16: Mes | E16: F1 | F16: Bls | H16: 2532 | J16: 67.0812 | N16: 1487.58 | O16: =ROUND(G16*I16,2)+ROUND(H16*J16,2)-K16-L16-M16-N16 -> 168362.02 | P16: =ROUND(18.75%*O16,2) -> 31567.88 | Q16: =ROUND($O16*R16,2) -> 25254.3 | R16: 0.15 | S16: =ROUND($O16*T16,2) -> 6313.58 | T16: 0.0375 | U16: =IF($F16&"/Día"=W$9,SUM($G16:$H16),"") -> 2532 | V16: =IF(U16<>"",$O16,"") -> 168362.02 | W16: =IF($F16&"/Día"=W$9,ROUND(U16/$W$1,1),"") -> 81.7 | X16: =IF(U16=0,0,IF($F16&"/Día"=W$9,ROUND(V16/U16,4),"")) -> 66.4937 | Y16: =IF(U16=0,0,IF($F16&"/Día"=W$9,ROUND(Z16/U16,4),"")) -> 12.4676 | Z16: =IF(U16<>"",$P16,"") -> 31567.88 | AA16: =IF($F16&"/Día"=AC$9,SUM($G16:$H16),"") | AB16: =IF(AA16<>"",$O16,"") | AC16: =IF($F16&"/Día"=AC$9,ROUND(AA16/$W$1,1),"") | AD16: =IF(AA16=0,0,IF($F16&"/Día"=AC$9,ROUND(AB16/AA16,4),"")) | AE16: =IF(AA16=0,0,IF($F16&"/Día"=AC$9,ROUND(AF16/AA16,4),"")) | AF16: =IF(AA16<>"",$P16,"")
A17: - | B17: VII/VI | C17: Licencia | D17: Quincena | E17: F2 | F17: Bls | G17: 46815 | H17: 59830 | I17: 66.2472 | J17: 66.7679 | N17: 2221.88 | O17: =ROUND(G17*I17,2)+ROUND(H17*J17,2)-K17-L17-M17-N17 -> 7093864.2 | P17: =ROUND(18.75%*O17,2) -> 1330099.6 | Q17: =ROUND($O17*R17,2) -> 1064079.6 | R17: 0.15 | S17: =ROUND($O17*T17,2) -> 266019.91 | T17: 0.0375 | U17: =IF($F17&"/Día"=W$9,SUM($G17:$H17),"") -> 106645 | V17: =IF(U17<>"",$O17,"") -> 7093864.2 | W17: =IF($F17&"/Día"=W$9,ROUND(U17/$W$1,1),"") -> 3440.2 | X17: =IF(U17=0,0,IF($F17&"/Día"=W$9,ROUND(V17/U17,4),"")) -> 66.5185 | Y17: =IF(U17=0,0,IF($F17&"/Día"=W$9,ROUND(Z17/U17,4),"")) -> 12.4722 | Z17: =IF(U17<>"",$P17,"") -> 1330099.6 | AA17: =IF($F17&"/Día"=AC$9,SUM($G17:$H17),"") | AB17: =IF(AA17<>"",$O17,"") | AC17: =IF($F17&"/Día"=AC$9,ROUND(AA17/$W$1,1),"") | AD17: =IF(AA17=0,0,IF($F17&"/Día"=AC$9,ROUND(AB17/AA17,4),"")) | AE17: =IF(AA17=0,0,IF($F17&"/Día"=AC$9,ROUND(AF17/AA17,4),"")) | AF17: =IF(AA17<>"",$P17,"")
A18: - | B18: VII | C18: Servicios | D18: Mes | E18: F1 | F18: Bls | O18: =ROUND(G18*I18,2)+ROUND(H18*J18,2)-K18-L18-M18-N18 -> 0 | P18: =ROUND(18.75%*O18,2) -> 0 | Q18: =ROUND($O18*R18,2) -> 0 | R18: 0.15 | S18: =ROUND($O18*T18,2) -> 0 | T18: 0.0375 | U18: =IF($F18&"/Día"=W$9,SUM($G18:$H18),"") -> 0 | V18: =IF(U18<>"",$O18,"") -> 0 | W18: =IF($F18&"/Día"=W$9,ROUND(U18/$W$1,1),"") -> 0 | X18: =IF(U18=0,0,IF($F18&"/Día"=W$9,ROUND(V18/U18,4),"")) -> 0 | Y18: =IF(U18=0,0,IF($F18&"/Día"=W$9,ROUND(Z18/U18,4),"")) -> 0 | Z18: =IF(U18<>"",$P18,"") -> 0 | AA18: =IF($F18&"/Día"=AC$9,SUM($G18:$H18),"") | AB18: =IF(AA18<>"",$O18,"") | AC18: =IF($F18&"/Día"=AC$9,ROUND(AA18/$W$1,1),"") | AD18: =IF(AA18=0,0,IF($F18&"/Día"=AC$9,ROUND(AB18/AA18,4),"")) | AE18: =IF(AA18=0,0,IF($F18&"/Día"=AC$9,ROUND(AF18/AA18,4),"")) | AF18: =IF(AA18<>"",$P18,"")
A19: - | B19: VII/VI-GAS | C19: Licencia | D19: Quincena | E19: F2 | F19: MM BTU | G19: 58474.37 | H19: 64682.42 | I19: 2.1708 | J19: 2.1708 | N19: 2121.65 | O19: =ROUND(G19*I19,2)+ROUND(H19*J19,2)-K19-L19-M19-N19 -> 265227.11 | P19: =ROUND(18.75%*O19,2) -> 49730.08 | Q19: =ROUND($O19*R19,2) -> 39784.07 | R19: 0.15 | S19: =ROUND($O19*T19,2) -> 9946.02 | T19: 0.0375 | U19: =IF($F19&"/Día"=W$9,SUM($G19:$H19),"") | V19: =IF(U19<>"",$O19,"") | W19: =IF($F19&"/Día"=W$9,ROUND(U19/$W$1,1),"") | X19: =IF(U19=0,0,IF($F19&"/Día"=W$9,ROUND(V19/U19,4),"")) | Y19: =IF(U19=0,0,IF($F19&"/Día"=W$9,ROUND(Z19/U19,4),"")) | Z19: =IF(U19<>"",$P19,"") | AA19: =IF($F19&"/Día"=AC$9,SUM($G19:$H19),"") -> 123156.79 | AB19: =IF(AA19<>"",$O19,"") -> 265227.11 | AC19: =IF($F19&"/Día"=AC$9,ROUND(AA19/$W$1,1),"") -> 3972.8 | AD19: =IF(AA19=0,0,IF($F19&"/Día"=AC$9,ROUND(AB19/AA19,4),"")) -> 2.1536 | AE19: =IF(AA19=0,0,IF($F19&"/Día"=AC$9,ROUND(AF19/AA19,4),"")) -> 0.4038 | AF19: =IF(AA19<>"",$P19,"") -> 49730.08
A20: - | B20: IX | C20: Licencia | D20: Quincena | E20: F2 | F20: Bls | G20: 2083 | H20: 3260 | I20: 66.7972 | J20: 67.3179 | N20: 737.78 | O20: =ROUND(G20*I20,2)+ROUND(H20*J20,2)-K20-L20-M20-N20 -> 357857.14 | P20: =ROUND(18.75%*O20,2) -> 67098.21 | Q20: =ROUND($O20*R20,2) -> 53678.57 | R20: 0.15 | S20: =ROUND($O20*T20,2) -> 13419.64 | T20: 0.0375 | U20: =IF($F20&"/Día"=W$9,SUM($G20:$H20),"") -> 5343 | V20: =IF(U20<>"",$O20,"") -> 357857.14 | W20: =IF($F20&"/Día"=W$9,ROUND(U20/$W$1,1),"") -> 172.4 | X20: =IF(U20=0,0,IF($F20&"/Día"=W$9,ROUND(V20/U20,4),"")) -> 66.9768 | Y20: =IF(U20=0,0,IF($F20&"/Día"=W$9,ROUND(Z20/U20,4),"")) -> 12.5582 | Z20: =IF(U20<>"",$P20,"") -> 67098.21 | AA20: =IF($F20&"/Día"=AC$9,SUM($G20:$H20),"") | AB20: =IF(AA20<>"",$O20,"") | AC20: =IF($F20&"/Día"=AC$9,ROUND(AA20/$W$1,1),"") | AD20: =IF(AA20=0,0,IF($F20&"/Día"=AC$9,ROUND(AB20/AA20,4),"")) | AE20: =IF(AA20=0,0,IF($F20&"/Día"=AC$9,ROUND(AF20/AA20,4),"")) | AF20: =IF(AA20<>"",$P20,"")
A21: - | B21: X | C21: Licencia | D21: Quincena | E21: F2 | F21: Bls | G21: 195037 | H21: 205982 | I21: 66.7972 | J21: 67.3179 | N21: 4334.18 | O21: =ROUND(G21*I21,2)+ROUND(H21*J21,2)-K21-L21-M21-N21 -> 26889867 | P21: =ROUND(18.75%*O21,2) -> 5041850.1 | Q21: =ROUND($O21*R21,2) -> 4033480 | R21: 0.15 | S21: =ROUND($O21*T21,2) -> 1008370 | T21: 0.0375 | U21: =IF($F21&"/Día"=W$9,SUM($G21:$H21),"") -> 401019 | V21: =IF(U21<>"",$O21,"") -> 26889867 | W21: =IF($F21&"/Día"=W$9,ROUND(U21/$W$1,1),"") -> 12936.1 | X21: =IF(U21=0,0,IF($F21&"/Día"=W$9,ROUND(V21/U21,4),"")) -> 67.0538 | Y21: =IF(U21=0,0,IF($F21&"/Día"=W$9,ROUND(Z21/U21,4),"")) -> 12.5726 | Z21: =IF(U21<>"",$P21,"") -> 5041850.1 | AA21: =IF($F21&"/Día"=AC$9,SUM($G21:$H21),"") | AB21: =IF(AA21<>"",$O21,"") | AC21: =IF($F21&"/Día"=AC$9,ROUND(AA21/$W$1,1),"") | AD21: =IF(AA21=0,0,IF($F21&"/Día"=AC$9,ROUND(AB21/AA21,4),"")) | AE21: =IF(AA21=0,0,IF($F21&"/Día"=AC$9,ROUND(AF21/AA21,4),"")) | AF21: =IF(AA21<>"",$P21,"")
A22: - | B22: X-GAS | C22: Licencia | D22: Mes | E22: F2 | F22: MM BTU | G22: 251980.16 | H22: 254840.6 | I22: 1.8012 | J22: 1.8012 | N22: 2235.16 | O22: =ROUND(G22*I22,2)+ROUND(H22*J22,2)-K22-L22-M22-N22 -> 910650.39 | P22: =ROUND(18.75%*O22,2) -> 170746.95 | Q22: =ROUND($O22*R22,2) -> 136597.56 | R22: 0.15 | S22: =ROUND($O22*T22,2) -> 34149.39 | T22: 0.0375 | U22: =IF($F22&"/Día"=W$9,SUM($G22:$H22),"") | V22: =IF(U22<>"",$O22,"") | W22: =IF($F22&"/Día"=W$9,ROUND(U22/$W$1,1),"") | X22: =IF(U22=0,0,IF($F22&"/Día"=W$9,ROUND(V22/U22,4),"")) | Y22: =IF(U22=0,0,IF($F22&"/Día"=W$9,ROUND(Z22/U22,4),"")) | Z22: =IF(U22<>"",$P22,"") | AA22: =IF($F22&"/Día"=AC$9,SUM($G22:$H22),"") -> 506820.76 | AB22: =IF(AA22<>"",$O22,"") -> 910650.39 | AC22: =IF($F22&"/Día"=AC$9,ROUND(AA22/$W$1,1),"") -> 16349.1 | AD22: =IF(AA22=0,0,IF($F22&"/Día"=AC$9,ROUND(AB22/AA22,4),"")) -> 1.7968 | AE22: =IF(AA22=0,0,IF($F22&"/Día"=AC$9,ROUND(AF22/AA22,4),"")) -> 0.3369 | AF22: =IF(AA22<>"",$P22,"") -> 170746.95
